[
  {
    "Nation": "Mikeswill",
    "Junk Value": 21016.09,
    "Bank": 81804.66,
    "Deck Value": 3640515.96,
    "Card Count": 80681,
    "Deck Capacity": 81168,
    "Ultra-Rare": 9087,
    "Rare": 6556,
    "Common": 13609,
    "Uncommon": 32962,
    "Legendary": 16362,
    "Epic": 2105,
    "S1": 6773,
    "S2": 49330,
    "S3": 24578,
    "S1 Ultra-Rare": 122,
    "S1 Rare": 120,
    "S2 Common": 9164,
    "S1 Common": 1906,
    "S1 Uncommon": 2993,
    "S1 Legendary": 1485,
    "S2 Uncommon": 29376,
    "S2 Rare": 3638,
    "S1 Epic": 147,
    "S2 Ultra-Rare": 544,
    "S2 Legendary": 5974,
    "S2 Epic": 634,
    "S3 Ultra-Rare": 8421,
    "S3 Legendary": 8903,
    "S3 Rare": 2798,
    "S3 Epic": 1324,
    "S3 Common": 2539,
    "S3 Uncommon": 593
  },
  {
    "Nation": "Giovanniland",
    "Junk Value": 2091.74,
    "Bank": 6503.12,
    "Deck Value": 2304213.0,
    "Card Count": 80957,
    "Deck Capacity": 81336,
    "Uncommon": 10222,
    "Rare": 2319,
    "Common": 65844,
    "Ultra-Rare": 1681,
    "Legendary": 281,
    "Epic": 610,
    "S1": 2200,
    "S2": 16750,
    "S3": 62007,
    "S1 Uncommon": 691,
    "S1 Rare": 239,
    "S1 Common": 966,
    "S2 Common": 12025,
    "S2 Uncommon": 3026,
    "S2 Ultra-Rare": 876,
    "S1 Legendary": 7,
    "S1 Ultra-Rare": 212,
    "S1 Epic": 85,
    "S2 Rare": 422,
    "S2 Epic": 397,
    "S2 Legendary": 4,
    "S3 Uncommon": 6505,
    "S3 Common": 52853,
    "S3 Epic": 128,
    "S3 Rare": 1658,
    "S3 Ultra-Rare": 593,
    "S3 Legendary": 270
  },
  {
    "Nation": "Koem Kab",
    "Junk Value": 29716.75,
    "Bank": 41384.29,
    "Deck Value": 2213265.37,
    "Card Count": 49332,
    "Deck Capacity": 50336,
    "Ultra-Rare": 1848,
    "Common": 8245,
    "Uncommon": 6534,
    "Epic": 4100,
    "Legendary": 26888,
    "Rare": 1717,
    "S1": 10160,
    "S2": 18661,
    "S3": 20511,
    "S1 Ultra-Rare": 475,
    "S1 Common": 2272,
    "S1 Uncommon": 1394,
    "S1 Epic": 834,
    "S2 Common": 4268,
    "S1 Legendary": 4684,
    "S1 Rare": 501,
    "S2 Ultra-Rare": 291,
    "S2 Uncommon": 4541,
    "S2 Legendary": 8662,
    "S2 Rare": 364,
    "S2 Epic": 535,
    "S3 Legendary": 13542,
    "S3 Rare": 852,
    "S3 Common": 1705,
    "S3 Epic": 2731,
    "S3 Ultra-Rare": 1082,
    "S3 Uncommon": 599
  },
  {
    "Nation": "Second Best Card Collector",
    "Junk Value": 1355.46,
    "Bank": 10756.29,
    "Deck Value": 2106096.64,
    "Card Count": 17537,
    "Deck Capacity": 17862,
    "Uncommon": 1784,
    "Rare": 2338,
    "Common": 10346,
    "Legendary": 153,
    "Epic": 1422,
    "Ultra-Rare": 1494,
    "S2": 1653,
    "S1": 238,
    "S3": 15646,
    "S2 Uncommon": 255,
    "S2 Rare": 583,
    "S2 Common": 738,
    "S1 Common": 49,
    "S1 Uncommon": 69,
    "S2 Legendary": 60,
    "S2 Epic": 14,
    "S1 Epic": 19,
    "S3 Common": 9559,
    "S3 Uncommon": 1460,
    "S3 Ultra-Rare": 1478,
    "S3 Legendary": 9,
    "S3 Rare": 1751,
    "S3 Epic": 1389,
    "S1 Ultra-Rare": 13,
    "S1 Rare": 4,
    "S1 Legendary": 84,
    "S2 Ultra-Rare": 3
  },
  {
    "Nation": "Varanius",
    "Junk Value": 6078.56,
    "Bank": 3988.36,
    "Deck Value": 845765.3,
    "Card Count": 24917,
    "Deck Capacity": 25212,
    "Common": 10081,
    "Uncommon": 3231,
    "Ultra-Rare": 4071,
    "Rare": 1837,
    "Legendary": 4307,
    "Epic": 1390,
    "S1": 178,
    "S2": 1139,
    "S3": 23600,
    "S1 Common": 71,
    "S2 Common": 344,
    "S1 Uncommon": 66,
    "S2 Ultra-Rare": 21,
    "S2 Uncommon": 525,
    "S2 Rare": 33,
    "S2 Legendary": 210,
    "S2 Epic": 6,
    "S3 Rare": 1796,
    "S3 Common": 9666,
    "S3 Uncommon": 2640,
    "S3 Ultra-Rare": 4041,
    "S3 Legendary": 4097,
    "S3 Epic": 1360,
    "S1 Rare": 8,
    "S1 Ultra-Rare": 9,
    "S1 Epic": 24
  },
  {
    "Nation": "Noahs Second Country",
    "Junk Value": 12618.47,
    "Bank": 110755.26,
    "Deck Value": 802409.0,
    "Card Count": 12764,
    "Deck Capacity": 16074,
    "Common": 147,
    "Legendary": 12617,
    "S2": 147,
    "S3": 12617,
    "S2 Common": 147,
    "S3 Legendary": 12617
  },
  {
    "Nation": "9003",
    "Junk Value": 3515.42,
    "Bank": 6706.58,
    "Deck Value": 707722.2,
    "Card Count": 282740,
    "Deck Capacity": 131010,
    "Common": 275537,
    "Rare": 1578,
    "Ultra-Rare": 641,
    "Uncommon": 4247,
    "Epic": 635,
    "Legendary": 102,
    "S1": 25553,
    "S2": 257187,
    "S1 Common": 21819,
    "S2 Common": 253718,
    "S1 Rare": 943,
    "S1 Ultra-Rare": 335,
    "S1 Uncommon": 2145,
    "S1 Epic": 301,
    "S2 Rare": 635,
    "S2 Uncommon": 2102,
    "S2 Epic": 334,
    "S1 Legendary": 10,
    "S2 Ultra-Rare": 306,
    "S2 Legendary": 92
  },
  {
    "Nation": "Upper Tuchoim",
    "Junk Value": 493.24,
    "Bank": 2882.96,
    "Deck Value": 527813.38,
    "Card Count": 8152,
    "Deck Capacity": 8288,
    "Rare": 1114,
    "Common": 4259,
    "Uncommon": 1053,
    "Ultra-Rare": 1550,
    "Epic": 176,
    "S1": 201,
    "S2": 221,
    "S3": 7730,
    "S1 Rare": 16,
    "S1 Common": 146,
    "S2 Common": 148,
    "S2 Uncommon": 51,
    "S2 Rare": 13,
    "S2 Ultra-Rare": 7,
    "S2 Epic": 2,
    "S3 Common": 3965,
    "S3 Ultra-Rare": 1539,
    "S3 Rare": 1085,
    "S3 Uncommon": 972,
    "S1 Uncommon": 30,
    "S3 Epic": 169,
    "S1 Epic": 5,
    "S1 Ultra-Rare": 4
  },
  {
    "Nation": "Kractero",
    "Junk Value": 6308.23,
    "Bank": 6494.23,
    "Deck Value": 480351.36,
    "Card Count": 10395,
    "Deck Capacity": 10510,
    "Legendary": 6162,
    "Common": 3443,
    "Epic": 180,
    "Uncommon": 436,
    "Rare": 174,
    "S1": 2173,
    "S2": 181,
    "S3": 8041,
    "S1 Legendary": 224,
    "S1 Common": 1598,
    "S1 Epic": 39,
    "S1 Uncommon": 289,
    "S1 Rare": 23,
    "S2 Legendary": 181,
    "S3 Legendary": 5757,
    "S3 Common": 1845,
    "S3 Epic": 141,
    "S3 Uncommon": 147,
    "S3 Rare": 151
  },
  {
    "Nation": "New Makasta",
    "Junk Value": 9724.75,
    "Bank": 6266.91,
    "Deck Value": 477416.42,
    "Card Count": 65533,
    "Deck Capacity": 70188,
    "Legendary": 5191,
    "Common": 30075,
    "Rare": 5958,
    "Ultra-Rare": 3602,
    "Uncommon": 15202,
    "Epic": 5505,
    "S1": 2510,
    "S2": 34328,
    "S3": 28695,
    "S1 Legendary": 87,
    "S1 Common": 779,
    "S1 Rare": 538,
    "S1 Ultra-Rare": 224,
    "S1 Uncommon": 739,
    "S1 Epic": 143,
    "S2 Uncommon": 9942,
    "S2 Rare": 3617,
    "S2 Epic": 1458,
    "S2 Common": 15477,
    "S2 Ultra-Rare": 2195,
    "S2 Legendary": 1639,
    "S3 Epic": 3904,
    "S3 Common": 13819,
    "S3 Ultra-Rare": 1183,
    "S3 Legendary": 3465,
    "S3 Uncommon": 4521,
    "S3 Rare": 1803
  },
  {
    "Nation": "Vulxo",
    "Junk Value": 3254.51,
    "Bank": 399.49,
    "Deck Value": 411950.69,
    "Card Count": 7256,
    "Deck Capacity": 7336,
    "Common": 2926,
    "Epic": 379,
    "Legendary": 2989,
    "Uncommon": 407,
    "Ultra-Rare": 132,
    "Rare": 423,
    "S1": 139,
    "S2": 190,
    "S3": 6927,
    "S1 Common": 71,
    "S1 Epic": 29,
    "S1 Legendary": 23,
    "S1 Uncommon": 15,
    "S2 Legendary": 89,
    "S2 Uncommon": 20,
    "S2 Common": 73,
    "S2 Ultra-Rare": 1,
    "S3 Common": 2782,
    "S3 Rare": 422,
    "S3 Uncommon": 372,
    "S3 Legendary": 2877,
    "S3 Epic": 344,
    "S2 Epic": 6,
    "S3 Ultra-Rare": 130,
    "S2 Rare": 1,
    "S1 Ultra-Rare": 1
  },
  {
    "Nation": "Seanat",
    "Junk Value": 7030.99,
    "Bank": 2652.53,
    "Deck Value": 404070.82,
    "Card Count": 15523,
    "Deck Capacity": 15770,
    "Common": 3904,
    "Uncommon": 2129,
    "Rare": 1095,
    "Legendary": 5610,
    "Ultra-Rare": 390,
    "Epic": 2395,
    "S1": 2283,
    "S2": 5332,
    "S3": 7908,
    "S1 Common": 583,
    "S1 Uncommon": 1165,
    "S1 Rare": 100,
    "S2 Legendary": 4412,
    "S1 Legendary": 264,
    "S1 Ultra-Rare": 81,
    "S2 Ultra-Rare": 13,
    "S1 Epic": 90,
    "S2 Common": 451,
    "S2 Uncommon": 99,
    "S2 Epic": 218,
    "S2 Rare": 139,
    "S3 Common": 2870,
    "S3 Uncommon": 865,
    "S3 Ultra-Rare": 296,
    "S3 Legendary": 934,
    "S3 Epic": 2087,
    "S3 Rare": 856
  },
  {
    "Nation": "Panagouge",
    "Junk Value": 516.82,
    "Bank": 1873.57,
    "Deck Value": 389267.71,
    "Card Count": 3644,
    "Deck Capacity": 5010,
    "Common": 1687,
    "Epic": 290,
    "Legendary": 272,
    "Rare": 165,
    "Ultra-Rare": 143,
    "Uncommon": 1087,
    "S1": 193,
    "S2": 1501,
    "S3": 1950,
    "S1 Common": 70,
    "S1 Epic": 13,
    "S1 Legendary": 15,
    "S1 Rare": 21,
    "S1 Ultra-Rare": 29,
    "S2 Common": 732,
    "S1 Uncommon": 45,
    "S2 Legendary": 189,
    "S2 Uncommon": 470,
    "S2 Epic": 25,
    "S2 Ultra-Rare": 43,
    "S2 Rare": 42,
    "S3 Uncommon": 572,
    "S3 Common": 885,
    "S3 Rare": 102,
    "S3 Legendary": 68,
    "S3 Epic": 252,
    "S3 Ultra-Rare": 71
  },
  {
    "Nation": "Thelandoffunfunfun",
    "Junk Value": 1583.97,
    "Bank": 3937.9,
    "Deck Value": 340329.07,
    "Card Count": 6704,
    "Deck Capacity": 6885,
    "Common": 2272,
    "Legendary": 1160,
    "Epic": 287,
    "Ultra-Rare": 1068,
    "Uncommon": 883,
    "Rare": 1034,
    "S1": 68,
    "S2": 641,
    "S3": 5995,
    "S1 Common": 14,
    "S1 Legendary": 16,
    "S2 Common": 311,
    "S2 Epic": 11,
    "S2 Ultra-Rare": 33,
    "S2 Uncommon": 154,
    "S2 Legendary": 125,
    "S2 Rare": 7,
    "S1 Epic": 12,
    "S1 Uncommon": 18,
    "S3 Rare": 1025,
    "S3 Common": 1947,
    "S3 Uncommon": 711,
    "S3 Legendary": 1019,
    "S3 Ultra-Rare": 1029,
    "S3 Epic": 264,
    "S1 Rare": 2,
    "S1 Ultra-Rare": 6
  },
  {
    "Nation": "Communist-Denmark",
    "Junk Value": 2780.6,
    "Bank": 5383.15,
    "Deck Value": 292645.27,
    "Card Count": 26293,
    "Deck Capacity": 26500,
    "Common": 20005,
    "Uncommon": 1889,
    "Rare": 833,
    "Epic": 907,
    "Legendary": 1876,
    "Ultra-Rare": 783,
    "S2": 341,
    "S1": 124,
    "S3": 25828,
    "S2 Common": 100,
    "S2 Uncommon": 62,
    "S2 Rare": 16,
    "S2 Epic": 50,
    "S2 Legendary": 82,
    "S2 Ultra-Rare": 31,
    "S1 Uncommon": 35,
    "S1 Ultra-Rare": 8,
    "S1 Legendary": 18,
    "S1 Epic": 13,
    "S3 Common": 19860,
    "S3 Uncommon": 1792,
    "S3 Ultra-Rare": 744,
    "S3 Rare": 812,
    "S3 Epic": 844,
    "S3 Legendary": 1776,
    "S1 Common": 45,
    "S1 Rare": 5
  },
  {
    "Nation": "Fhaengshia",
    "Junk Value": 3054.21,
    "Bank": 4573.37,
    "Deck Value": 289658.87,
    "Card Count": 5457,
    "Deck Capacity": 6833,
    "Rare": 558,
    "Legendary": 2504,
    "Epic": 718,
    "Ultra-Rare": 832,
    "Common": 436,
    "Uncommon": 409,
    "S1": 568,
    "S2": 2702,
    "S3": 2187,
    "S1 Rare": 54,
    "S1 Legendary": 200,
    "S2 Legendary": 1810,
    "S1 Epic": 118,
    "S1 Ultra-Rare": 109,
    "S1 Common": 47,
    "S2 Common": 300,
    "S1 Uncommon": 40,
    "S2 Ultra-Rare": 298,
    "S2 Uncommon": 87,
    "S2 Epic": 173,
    "S2 Rare": 34,
    "S3 Uncommon": 282,
    "S3 Rare": 470,
    "S3 Ultra-Rare": 425,
    "S3 Epic": 427,
    "S3 Legendary": 494,
    "S3 Common": 89
  },
  {
    "Nation": "Aerilia",
    "Junk Value": 3398.18,
    "Bank": 17913.15,
    "Deck Value": 275813.64,
    "Card Count": 5585,
    "Deck Capacity": 9862,
    "Common": 753,
    "Legendary": 3018,
    "Uncommon": 519,
    "Rare": 319,
    "Epic": 505,
    "Ultra-Rare": 471,
    "S1": 521,
    "S2": 1310,
    "S3": 3754,
    "S1 Common": 120,
    "S1 Legendary": 264,
    "S1 Uncommon": 74,
    "S1 Rare": 15,
    "S1 Epic": 22,
    "S2 Uncommon": 135,
    "S2 Ultra-Rare": 132,
    "S2 Legendary": 669,
    "S2 Rare": 51,
    "S1 Ultra-Rare": 26,
    "S2 Epic": 100,
    "S2 Common": 223,
    "S3 Uncommon": 310,
    "S3 Rare": 253,
    "S3 Ultra-Rare": 313,
    "S3 Common": 410,
    "S3 Epic": 383,
    "S3 Legendary": 2085
  },
  {
    "Nation": "Aragesh",
    "Junk Value": 4290.72,
    "Bank": 1070.81,
    "Deck Value": 263121.68,
    "Card Count": 7000,
    "Deck Capacity": 7284,
    "Legendary": 3664,
    "Common": 402,
    "Epic": 818,
    "Ultra-Rare": 910,
    "Uncommon": 634,
    "Rare": 572,
    "S1": 984,
    "S2": 1554,
    "S3": 4462,
    "S1 Legendary": 162,
    "S2 Legendary": 206,
    "S1 Common": 7,
    "S2 Epic": 257,
    "S1 Ultra-Rare": 262,
    "S1 Epic": 227,
    "S1 Uncommon": 181,
    "S2 Common": 335,
    "S1 Rare": 145,
    "S2 Ultra-Rare": 310,
    "S2 Rare": 191,
    "S2 Uncommon": 255,
    "S3 Ultra-Rare": 338,
    "S3 Legendary": 3296,
    "S3 Common": 60,
    "S3 Uncommon": 198,
    "S3 Epic": 334,
    "S3 Rare": 236
  },
  {
    "Nation": "Racoda",
    "Junk Value": 3984.05,
    "Bank": 2259.65,
    "Deck Value": 248345.22,
    "Card Count": 31308,
    "Deck Capacity": 31668,
    "Common": 740,
    "Legendary": 2530,
    "Epic": 81,
    "Ultra-Rare": 68,
    "Uncommon": 27851,
    "Rare": 38,
    "S1": 559,
    "S2": 3121,
    "S3": 27628,
    "S1 Common": 62,
    "S1 Legendary": 216,
    "S2 Common": 635,
    "S1 Epic": 39,
    "S1 Ultra-Rare": 21,
    "S1 Uncommon": 206,
    "S2 Legendary": 2040,
    "S2 Ultra-Rare": 41,
    "S1 Rare": 15,
    "S2 Rare": 16,
    "S2 Uncommon": 358,
    "S2 Epic": 31,
    "S3 Uncommon": 27287,
    "S3 Legendary": 274,
    "S3 Common": 43,
    "S3 Rare": 7,
    "S3 Epic": 11,
    "S3 Ultra-Rare": 6
  },
  {
    "Nation": "Kwaj",
    "Junk Value": 2237.6,
    "Bank": 4273.45,
    "Deck Value": 238694.39,
    "Card Count": 5530,
    "Deck Capacity": 10786,
    "Epic": 837,
    "Legendary": 1737,
    "Common": 2195,
    "Ultra-Rare": 217,
    "Uncommon": 335,
    "Rare": 209,
    "S1": 1272,
    "S2": 860,
    "S3": 3398,
    "S1 Epic": 175,
    "S1 Legendary": 483,
    "S1 Common": 514,
    "S1 Ultra-Rare": 17,
    "S1 Uncommon": 70,
    "S1 Rare": 13,
    "S2 Legendary": 242,
    "S2 Epic": 295,
    "S2 Common": 283,
    "S2 Uncommon": 28,
    "S2 Ultra-Rare": 8,
    "S2 Rare": 4,
    "S3 Legendary": 1012,
    "S3 Common": 1398,
    "S3 Epic": 367,
    "S3 Rare": 192,
    "S3 Ultra-Rare": 192,
    "S3 Uncommon": 237
  },
  {
    "Nation": "The Northern Light",
    "Junk Value": 3014.56,
    "Bank": 522.16,
    "Deck Value": 237568.87,
    "Card Count": 3032,
    "Deck Capacity": 15600,
    "Legendary": 3012,
    "Uncommon": 6,
    "Epic": 4,
    "Common": 6,
    "Rare": 3,
    "Ultra-Rare": 1,
    "S1": 842,
    "S2": 1473,
    "S3": 717,
    "S1 Legendary": 837,
    "S2 Uncommon": 3,
    "S2 Legendary": 1467,
    "S2 Epic": 1,
    "S1 Uncommon": 2,
    "S1 Common": 3,
    "S2 Common": 2,
    "S3 Legendary": 708,
    "S3 Rare": 3,
    "S3 Epic": 3,
    "S3 Uncommon": 1,
    "S3 Ultra-Rare": 1,
    "S3 Common": 1
  },
  {
    "Nation": "National Park Service",
    "Junk Value": 2639.38,
    "Bank": 5718.96,
    "Deck Value": 222667.37,
    "Card Count": 4518,
    "Deck Capacity": 5000,
    "Epic": 254,
    "Legendary": 2435,
    "Common": 963,
    "Uncommon": 239,
    "Ultra-Rare": 279,
    "Rare": 348,
    "S1": 54,
    "S3": 4419,
    "S2": 45,
    "S1 Epic": 6,
    "S3 Legendary": 2413,
    "S3 Common": 936,
    "S2 Common": 8,
    "S3 Uncommon": 208,
    "S3 Ultra-Rare": 274,
    "S3 Epic": 247,
    "S3 Rare": 341,
    "S1 Common": 19,
    "S1 Rare": 2,
    "S2 Uncommon": 18,
    "S1 Legendary": 12,
    "S1 Uncommon": 13,
    "S2 Legendary": 10,
    "S2 Epic": 1,
    "S2 Ultra-Rare": 3,
    "S1 Ultra-Rare": 2,
    "S2 Rare": 5
  },
  {
    "Nation": "Upc",
    "Junk Value": 2742.32,
    "Bank": 930.32,
    "Deck Value": 221353.09,
    "Card Count": 3003,
    "Deck Capacity": 3500,
    "Legendary": 2734,
    "Ultra-Rare": 2,
    "Uncommon": 21,
    "Epic": 9,
    "Common": 237,
    "S1": 295,
    "S2": 1999,
    "S3": 709,
    "S1 Legendary": 292,
    "S2 Legendary": 1970,
    "S1 Ultra-Rare": 2,
    "S2 Uncommon": 21,
    "S1 Epic": 1,
    "S2 Epic": 8,
    "S3 Legendary": 472,
    "S3 Common": 237
  },
  {
    "Nation": "9001",
    "Junk Value": 464.54,
    "Bank": 2662.41,
    "Deck Value": 217850.77,
    "Card Count": 3631,
    "Deck Capacity": 4000,
    "Rare": 303,
    "Common": 1964,
    "Epic": 305,
    "Uncommon": 588,
    "Legendary": 211,
    "Ultra-Rare": 260,
    "S1": 159,
    "S2": 556,
    "S3": 2916,
    "S1 Rare": 10,
    "S1 Common": 85,
    "S1 Epic": 27,
    "S1 Uncommon": 35,
    "S2 Common": 312,
    "S2 Rare": 47,
    "S2 Epic": 60,
    "S2 Legendary": 1,
    "S2 Ultra-Rare": 11,
    "S2 Uncommon": 125,
    "S3 Common": 1567,
    "S3 Ultra-Rare": 247,
    "S3 Rare": 246,
    "S3 Uncommon": 428,
    "S3 Legendary": 210,
    "S3 Epic": 218,
    "S1 Ultra-Rare": 2
  },
  {
    "Nation": "Witchcraft And Sorcery",
    "Junk Value": 2568.58,
    "Bank": 1956.82,
    "Deck Value": 215454.25,
    "Card Count": 12349,
    "Deck Capacity": 12786,
    "Legendary": 2169,
    "Rare": 305,
    "Uncommon": 429,
    "Common": 8553,
    "Epic": 380,
    "Ultra-Rare": 513,
    "S1": 610,
    "S2": 1536,
    "S3": 10203,
    "S1 Legendary": 229,
    "S1 Rare": 28,
    "S1 Uncommon": 56,
    "S2 Common": 374,
    "S1 Common": 225,
    "S1 Epic": 53,
    "S2 Legendary": 714,
    "S1 Ultra-Rare": 19,
    "S2 Epic": 131,
    "S2 Rare": 158,
    "S2 Ultra-Rare": 91,
    "S2 Uncommon": 68,
    "S3 Legendary": 1226,
    "S3 Ultra-Rare": 403,
    "S3 Common": 7954,
    "S3 Uncommon": 305,
    "S3 Epic": 196,
    "S3 Rare": 119
  },
  {
    "Nation": "Riemstagrad",
    "Junk Value": 7527.51,
    "Bank": 4307.14,
    "Deck Value": 213280.97,
    "Card Count": 15055,
    "Deck Capacity": 15372,
    "Epic": 11716,
    "Legendary": 1519,
    "Uncommon": 264,
    "Rare": 175,
    "Common": 731,
    "Ultra-Rare": 650,
    "S1": 4304,
    "S2": 5221,
    "S3": 5530,
    "S1 Epic": 3888,
    "S1 Legendary": 235,
    "S2 Legendary": 319,
    "S1 Uncommon": 54,
    "S1 Rare": 22,
    "S1 Common": 51,
    "S2 Epic": 4230,
    "S1 Ultra-Rare": 54,
    "S2 Uncommon": 79,
    "S2 Ultra-Rare": 410,
    "S2 Common": 157,
    "S2 Rare": 26,
    "S3 Epic": 3598,
    "S3 Legendary": 965,
    "S3 Common": 523,
    "S3 Rare": 127,
    "S3 Uncommon": 131,
    "S3 Ultra-Rare": 186
  },
  {
    "Nation": "Osheiga",
    "Junk Value": 2964.11,
    "Bank": 4300.58,
    "Deck Value": 210056.01,
    "Card Count": 3818,
    "Deck Capacity": 4092,
    "Rare": 69,
    "Legendary": 2743,
    "Common": 376,
    "Uncommon": 137,
    "Epic": 373,
    "Ultra-Rare": 120,
    "S1": 224,
    "S2": 479,
    "S3": 3115,
    "S1 Rare": 3,
    "S1 Legendary": 191,
    "S1 Common": 13,
    "S1 Uncommon": 14,
    "S2 Legendary": 190,
    "S2 Epic": 34,
    "S2 Ultra-Rare": 53,
    "S2 Common": 75,
    "S2 Rare": 38,
    "S2 Uncommon": 89,
    "S3 Ultra-Rare": 67,
    "S3 Epic": 336,
    "S3 Rare": 28,
    "S3 Common": 288,
    "S3 Legendary": 2362,
    "S3 Uncommon": 34,
    "S1 Epic": 3
  },
  {
    "Nation": "Laudesia",
    "Junk Value": 1893.46,
    "Bank": 2710.14,
    "Deck Value": 197049.42,
    "Card Count": 7735,
    "Deck Capacity": 9862,
    "Common": 3806,
    "Legendary": 1566,
    "Rare": 361,
    "Uncommon": 1446,
    "Epic": 353,
    "Ultra-Rare": 203,
    "S1": 807,
    "S2": 1205,
    "S3": 5723,
    "S1 Common": 473,
    "S1 Legendary": 102,
    "S1 Rare": 28,
    "S1 Uncommon": 138,
    "S1 Epic": 29,
    "S1 Ultra-Rare": 37,
    "S2 Common": 271,
    "S2 Legendary": 505,
    "S2 Uncommon": 365,
    "S2 Ultra-Rare": 28,
    "S2 Rare": 10,
    "S2 Epic": 26,
    "S3 Common": 3062,
    "S3 Rare": 323,
    "S3 Uncommon": 943,
    "S3 Legendary": 959,
    "S3 Epic": 298,
    "S3 Ultra-Rare": 138
  },
  {
    "Nation": "Thorn1000",
    "Junk Value": 2496.45,
    "Bank": 623.29,
    "Deck Value": 185363.56,
    "Card Count": 4796,
    "Deck Capacity": 5092,
    "Common": 1255,
    "Epic": 330,
    "Legendary": 2257,
    "Rare": 376,
    "Ultra-Rare": 220,
    "Uncommon": 358,
    "S1": 83,
    "S2": 246,
    "S3": 4467,
    "S1 Common": 34,
    "S1 Epic": 7,
    "S2 Legendary": 172,
    "S2 Common": 43,
    "S1 Legendary": 6,
    "S2 Epic": 5,
    "S2 Rare": 5,
    "S2 Ultra-Rare": 5,
    "S2 Uncommon": 16,
    "S1 Uncommon": 31,
    "S1 Rare": 4,
    "S3 Uncommon": 311,
    "S3 Legendary": 2079,
    "S3 Ultra-Rare": 214,
    "S3 Rare": 367,
    "S3 Common": 1178,
    "S3 Epic": 318,
    "S1 Ultra-Rare": 1
  },
  {
    "Nation": "Captain Woodhouse",
    "Junk Value": 2511.5,
    "Bank": 618.78,
    "Deck Value": 183555.62,
    "Card Count": 8219,
    "Deck Capacity": 12688,
    "Legendary": 1167,
    "Common": 2185,
    "Ultra-Rare": 2505,
    "Rare": 239,
    "Epic": 1590,
    "Uncommon": 533,
    "S1": 1403,
    "S2": 2381,
    "S3": 4435,
    "S1 Legendary": 611,
    "S2 Common": 1218,
    "S1 Ultra-Rare": 76,
    "S1 Common": 448,
    "S1 Rare": 31,
    "S2 Legendary": 357,
    "S1 Epic": 82,
    "S1 Uncommon": 155,
    "S2 Ultra-Rare": 370,
    "S2 Uncommon": 195,
    "S2 Epic": 184,
    "S2 Rare": 57,
    "S3 Epic": 1324,
    "S3 Ultra-Rare": 2059,
    "S3 Uncommon": 183,
    "S3 Legendary": 199,
    "S3 Rare": 151,
    "S3 Common": 519
  },
  {
    "Nation": "Portsville",
    "Junk Value": 2416.63,
    "Bank": 2693.33,
    "Deck Value": 178958.0,
    "Card Count": 3836,
    "Deck Capacity": 4029,
    "Legendary": 2194,
    "Uncommon": 225,
    "Ultra-Rare": 612,
    "Common": 498,
    "Epic": 168,
    "Rare": 139,
    "S1": 241,
    "S2": 921,
    "S3": 2674,
    "S1 Legendary": 95,
    "S1 Uncommon": 62,
    "S2 Legendary": 797,
    "S1 Ultra-Rare": 6,
    "S1 Common": 69,
    "S2 Epic": 23,
    "S2 Uncommon": 22,
    "S1 Epic": 9,
    "S2 Common": 72,
    "S2 Ultra-Rare": 5,
    "S3 Legendary": 1302,
    "S3 Uncommon": 141,
    "S3 Common": 357,
    "S3 Rare": 137,
    "S3 Epic": 136,
    "S3 Ultra-Rare": 601,
    "S2 Rare": 2
  },
  {
    "Nation": "New Kowloon Bay",
    "Junk Value": 2253.55,
    "Bank": 3943.53,
    "Deck Value": 174785.98,
    "Card Count": 4185,
    "Deck Capacity": 4279,
    "Legendary": 1881,
    "Epic": 333,
    "Ultra-Rare": 961,
    "Uncommon": 174,
    "Common": 515,
    "Rare": 321,
    "S1": 417,
    "S2": 762,
    "S3": 3006,
    "S1 Legendary": 114,
    "S1 Epic": 79,
    "S2 Legendary": 281,
    "S2 Epic": 95,
    "S1 Ultra-Rare": 160,
    "S1 Uncommon": 29,
    "S2 Ultra-Rare": 312,
    "S2 Common": 46,
    "S2 Uncommon": 26,
    "S1 Common": 32,
    "S2 Rare": 2,
    "S3 Legendary": 1486,
    "S3 Common": 437,
    "S3 Epic": 159,
    "S3 Ultra-Rare": 489,
    "S3 Uncommon": 119,
    "S3 Rare": 316,
    "S1 Rare": 3
  },
  {
    "Nation": "Frisbeeteria",
    "Junk Value": 20117.75,
    "Bank": 50438.98,
    "Deck Value": 172165.83,
    "Card Count": 38949,
    "Deck Capacity": 40558,
    "Epic": 36756,
    "Legendary": 1729,
    "Common": 360,
    "Uncommon": 75,
    "Ultra-Rare": 17,
    "Rare": 12,
    "S1": 7659,
    "S2": 14265,
    "S3": 17025,
    "S1 Epic": 6135,
    "S1 Legendary": 1291,
    "S2 Epic": 13649,
    "S1 Common": 168,
    "S2 Legendary": 386,
    "S1 Uncommon": 55,
    "S1 Ultra-Rare": 9,
    "S1 Rare": 1,
    "S2 Common": 192,
    "S2 Rare": 11,
    "S2 Uncommon": 20,
    "S2 Ultra-Rare": 7,
    "S3 Epic": 16972,
    "S3 Legendary": 52,
    "S3 Ultra-Rare": 1
  },
  {
    "Nation": "Feu De Glace",
    "Junk Value": 1033.48,
    "Bank": 27408.78,
    "Deck Value": 161330.32,
    "Card Count": 1563,
    "Deck Capacity": 4479,
    "Legendary": 954,
    "Uncommon": 59,
    "Ultra-Rare": 128,
    "Common": 293,
    "Epic": 96,
    "Rare": 33,
    "S2": 638,
    "S1": 652,
    "S3": 273,
    "S2 Legendary": 432,
    "S1 Uncommon": 37,
    "S1 Ultra-Rare": 104,
    "S1 Common": 119,
    "S1 Epic": 79,
    "S1 Legendary": 292,
    "S1 Rare": 21,
    "S2 Rare": 9,
    "S2 Ultra-Rare": 21,
    "S2 Common": 143,
    "S2 Epic": 14,
    "S2 Uncommon": 19,
    "S3 Epic": 3,
    "S3 Legendary": 230,
    "S3 Uncommon": 3,
    "S3 Common": 31,
    "S3 Ultra-Rare": 3,
    "S3 Rare": 3
  },
  {
    "Nation": "East Chimore",
    "Junk Value": 4959.86,
    "Bank": 335.09,
    "Deck Value": 156302.0,
    "Card Count": 13234,
    "Deck Capacity": 13336,
    "Epic": 6803,
    "Uncommon": 1148,
    "Rare": 824,
    "Legendary": 1397,
    "Ultra-Rare": 386,
    "Common": 2676,
    "S1": 152,
    "S2": 657,
    "S3": 12425,
    "S1 Epic": 67,
    "S2 Epic": 526,
    "S1 Uncommon": 25,
    "S1 Rare": 12,
    "S2 Legendary": 20,
    "S2 Ultra-Rare": 16,
    "S2 Uncommon": 41,
    "S2 Common": 39,
    "S2 Rare": 15,
    "S3 Common": 2601,
    "S3 Epic": 6210,
    "S3 Rare": 797,
    "S3 Ultra-Rare": 362,
    "S3 Uncommon": 1082,
    "S3 Legendary": 1373,
    "S1 Common": 36,
    "S1 Ultra-Rare": 8,
    "S1 Legendary": 4
  },
  {
    "Nation": "The Shaymen",
    "Junk Value": 2674.0,
    "Bank": 7153.3,
    "Deck Value": 148308.06,
    "Card Count": 2674,
    "Deck Capacity": 4010,
    "Legendary": 2674,
    "S1": 64,
    "S2": 764,
    "S3": 1846,
    "S1 Legendary": 64,
    "S2 Legendary": 764,
    "S3 Legendary": 1846
  },
  {
    "Nation": "Philville2",
    "Junk Value": 1308.3,
    "Bank": 33.35,
    "Deck Value": 145665.34,
    "Card Count": 2411,
    "Deck Capacity": 3186,
    "Uncommon": 226,
    "Rare": 99,
    "Common": 720,
    "Legendary": 1252,
    "Epic": 50,
    "Ultra-Rare": 64,
    "S1": 161,
    "S2": 1326,
    "S3": 924,
    "S1 Uncommon": 34,
    "S1 Rare": 23,
    "S2 Common": 514,
    "S1 Common": 50,
    "S2 Legendary": 604,
    "S2 Uncommon": 177,
    "S1 Legendary": 50,
    "S2 Rare": 11,
    "S1 Epic": 4,
    "S2 Epic": 7,
    "S2 Ultra-Rare": 13,
    "S3 Legendary": 598,
    "S3 Epic": 39,
    "S3 Ultra-Rare": 51,
    "S3 Common": 156,
    "S3 Rare": 65,
    "S3 Uncommon": 15
  },
  {
    "Nation": "Ever Testing",
    "Junk Value": 5059.65,
    "Bank": 1481.84,
    "Deck Value": 142352.79,
    "Card Count": 15230,
    "Deck Capacity": 15574,
    "Common": 4465,
    "Epic": 7859,
    "Uncommon": 838,
    "Legendary": 912,
    "Rare": 498,
    "Ultra-Rare": 658,
    "S1": 360,
    "S2": 3831,
    "S3": 11039,
    "S1 Common": 174,
    "S1 Epic": 133,
    "S2 Epic": 1926,
    "S1 Uncommon": 27,
    "S1 Legendary": 8,
    "S2 Legendary": 195,
    "S2 Common": 1428,
    "S2 Uncommon": 156,
    "S2 Rare": 65,
    "S2 Ultra-Rare": 61,
    "S1 Ultra-Rare": 11,
    "S1 Rare": 7,
    "S3 Common": 2863,
    "S3 Uncommon": 655,
    "S3 Epic": 5800,
    "S3 Rare": 426,
    "S3 Ultra-Rare": 586,
    "S3 Legendary": 709
  },
  {
    "Nation": "Dr Hooves",
    "Junk Value": 1470.44,
    "Bank": 12755.72,
    "Deck Value": 133316.25,
    "Card Count": 5221,
    "Deck Capacity": 9862,
    "Common": 2024,
    "Uncommon": 1064,
    "Rare": 439,
    "Ultra-Rare": 265,
    "Epic": 170,
    "Legendary": 1259,
    "S1": 308,
    "S2": 1157,
    "S3": 3756,
    "S1 Common": 141,
    "S2 Common": 429,
    "S1 Uncommon": 94,
    "S2 Uncommon": 404,
    "S2 Rare": 77,
    "S1 Ultra-Rare": 15,
    "S1 Rare": 35,
    "S1 Epic": 9,
    "S1 Legendary": 14,
    "S2 Ultra-Rare": 32,
    "S2 Legendary": 201,
    "S2 Epic": 14,
    "S3 Uncommon": 566,
    "S3 Ultra-Rare": 218,
    "S3 Common": 1454,
    "S3 Rare": 327,
    "S3 Legendary": 1044,
    "S3 Epic": 147
  },
  {
    "Nation": "Empire Of Caldrasa",
    "Junk Value": 52.96,
    "Bank": 3035.6,
    "Deck Value": 117295.86,
    "Card Count": 868,
    "Deck Capacity": 1000,
    "Epic": 66,
    "Common": 211,
    "Legendary": 8,
    "Rare": 434,
    "Uncommon": 133,
    "Ultra-Rare": 16,
    "S2": 37,
    "S3": 809,
    "S1": 22,
    "S2 Epic": 1,
    "S2 Common": 21,
    "S2 Legendary": 3,
    "S2 Rare": 5,
    "S2 Uncommon": 5,
    "S2 Ultra-Rare": 2,
    "S3 Common": 176,
    "S3 Rare": 427,
    "S3 Epic": 64,
    "S3 Uncommon": 124,
    "S3 Ultra-Rare": 13,
    "S3 Legendary": 5,
    "S1 Common": 14,
    "S1 Ultra-Rare": 1,
    "S1 Uncommon": 4,
    "S1 Epic": 1,
    "S1 Rare": 2
  },
  {
    "Nation": "Rotenaplistan",
    "Junk Value": 2178.43,
    "Bank": 3063.61,
    "Deck Value": 116522.45,
    "Card Count": 4609,
    "Deck Capacity": 4784,
    "Common": 573,
    "Epic": 1307,
    "Ultra-Rare": 724,
    "Uncommon": 408,
    "Legendary": 1354,
    "Rare": 243,
    "S1": 84,
    "S2": 369,
    "S3": 4156,
    "S1 Common": 19,
    "S2 Epic": 34,
    "S1 Ultra-Rare": 11,
    "S1 Uncommon": 30,
    "S1 Epic": 12,
    "S2 Common": 98,
    "S2 Legendary": 103,
    "S2 Ultra-Rare": 73,
    "S2 Rare": 23,
    "S2 Uncommon": 38,
    "S1 Rare": 6,
    "S3 Epic": 1261,
    "S3 Ultra-Rare": 640,
    "S3 Common": 456,
    "S3 Uncommon": 340,
    "S3 Rare": 214,
    "S3 Legendary": 1245,
    "S1 Legendary": 6
  },
  {
    "Nation": "Ioavollr",
    "Junk Value": 1646.37,
    "Bank": 196.66,
    "Deck Value": 112895.58,
    "Card Count": 3189,
    "Deck Capacity": 5864,
    "Ultra-Rare": 556,
    "Epic": 1004,
    "Legendary": 1022,
    "Uncommon": 149,
    "Common": 372,
    "Rare": 86,
    "S1": 280,
    "S2": 1196,
    "S3": 1713,
    "S1 Ultra-Rare": 68,
    "S1 Epic": 45,
    "S1 Legendary": 87,
    "S1 Uncommon": 38,
    "S1 Common": 24,
    "S1 Rare": 18,
    "S2 Uncommon": 69,
    "S2 Ultra-Rare": 326,
    "S2 Legendary": 584,
    "S2 Common": 97,
    "S2 Epic": 91,
    "S2 Rare": 29,
    "S3 Rare": 39,
    "S3 Common": 251,
    "S3 Uncommon": 42,
    "S3 Ultra-Rare": 162,
    "S3 Epic": 868,
    "S3 Legendary": 351
  },
  {
    "Nation": "The Overseer",
    "Junk Value": 1661.0,
    "Bank": 90.67,
    "Deck Value": 107162.42,
    "Card Count": 2086,
    "Deck Capacity": 2500,
    "Ultra-Rare": 140,
    "Legendary": 1617,
    "Epic": 21,
    "Common": 220,
    "Uncommon": 66,
    "Rare": 22,
    "S1": 19,
    "S2": 111,
    "S3": 1956,
    "S1 Ultra-Rare": 3,
    "S1 Legendary": 11,
    "S1 Epic": 1,
    "S2 Legendary": 80,
    "S1 Common": 2,
    "S2 Ultra-Rare": 16,
    "S2 Uncommon": 5,
    "S2 Common": 7,
    "S2 Epic": 1,
    "S2 Rare": 2,
    "S1 Rare": 1,
    "S3 Common": 211,
    "S3 Uncommon": 60,
    "S3 Legendary": 1526,
    "S3 Ultra-Rare": 121,
    "S3 Rare": 19,
    "S3 Epic": 19,
    "S1 Uncommon": 1
  },
  {
    "Nation": "Minskiev",
    "Junk Value": 1192.26,
    "Bank": 704.77,
    "Deck Value": 106319.57,
    "Card Count": 2281,
    "Deck Capacity": 6344,
    "Legendary": 1113,
    "Epic": 91,
    "Uncommon": 291,
    "Ultra-Rare": 62,
    "Rare": 43,
    "Common": 681,
    "S1": 233,
    "S2": 1399,
    "S3": 649,
    "S1 Legendary": 172,
    "S1 Epic": 21,
    "S1 Uncommon": 20,
    "S1 Ultra-Rare": 6,
    "S2 Legendary": 911,
    "S1 Rare": 3,
    "S2 Common": 322,
    "S2 Ultra-Rare": 33,
    "S2 Uncommon": 64,
    "S2 Rare": 11,
    "S2 Epic": 58,
    "S1 Common": 11,
    "S3 Common": 348,
    "S3 Uncommon": 207,
    "S3 Ultra-Rare": 23,
    "S3 Legendary": 30,
    "S3 Epic": 12,
    "S3 Rare": 29
  },
  {
    "Nation": "9006",
    "Junk Value": 240.44,
    "Bank": 2891.0,
    "Deck Value": 105713.94,
    "Card Count": 4568,
    "Deck Capacity": 5296,
    "Common": 3329,
    "Epic": 239,
    "Ultra-Rare": 282,
    "Rare": 226,
    "Uncommon": 485,
    "Legendary": 7,
    "S1": 164,
    "S2": 2314,
    "S3": 2090,
    "S1 Common": 87,
    "S2 Common": 2152,
    "S1 Epic": 30,
    "S2 Ultra-Rare": 131,
    "S2 Rare": 4,
    "S1 Uncommon": 32,
    "S3 Common": 1090,
    "S3 Uncommon": 436,
    "S2 Uncommon": 17,
    "S2 Epic": 10,
    "S3 Ultra-Rare": 144,
    "S1 Ultra-Rare": 7,
    "S3 Rare": 214,
    "S3 Epic": 199,
    "S1 Rare": 8,
    "S3 Legendary": 7
  },
  {
    "Nation": "Troc",
    "Junk Value": 1295.13,
    "Bank": 129.62,
    "Deck Value": 102385.3,
    "Card Count": 1428,
    "Deck Capacity": 1750,
    "Legendary": 1274,
    "Ultra-Rare": 22,
    "Epic": 31,
    "Common": 48,
    "Rare": 38,
    "Uncommon": 15,
    "S1": 14,
    "S2": 122,
    "S3": 1292,
    "S1 Legendary": 13,
    "S2 Legendary": 120,
    "S3 Legendary": 1141,
    "S3 Ultra-Rare": 22,
    "S3 Epic": 29,
    "S3 Common": 48,
    "S3 Rare": 38,
    "S3 Uncommon": 14,
    "S1 Uncommon": 1,
    "S2 Epic": 2
  },
  {
    "Nation": "Sylh Alanor",
    "Junk Value": 1106.84,
    "Bank": 1435.27,
    "Deck Value": 101092.18,
    "Card Count": 1247,
    "Deck Capacity": 3186,
    "Legendary": 1082,
    "Common": 84,
    "Rare": 12,
    "Epic": 39,
    "Ultra-Rare": 20,
    "Uncommon": 10,
    "S1": 281,
    "S2": 740,
    "S3": 226,
    "S1 Legendary": 264,
    "S2 Common": 69,
    "S1 Rare": 3,
    "S2 Legendary": 632,
    "S2 Epic": 25,
    "S1 Epic": 6,
    "S1 Ultra-Rare": 6,
    "S2 Uncommon": 4,
    "S2 Ultra-Rare": 8,
    "S2 Rare": 2,
    "S1 Uncommon": 2,
    "S3 Legendary": 186,
    "S3 Common": 15,
    "S3 Rare": 7,
    "S3 Ultra-Rare": 6,
    "S3 Uncommon": 4,
    "S3 Epic": 8
  },
  {
    "Nation": "Triseria",
    "Junk Value": 1353.14,
    "Bank": 12868.22,
    "Deck Value": 98518.34,
    "Card Count": 2492,
    "Deck Capacity": 5864,
    "Legendary": 1318,
    "Common": 834,
    "Uncommon": 174,
    "Rare": 122,
    "Epic": 31,
    "Ultra-Rare": 13,
    "S1": 78,
    "S2": 603,
    "S3": 1811,
    "S1 Legendary": 72,
    "S2 Legendary": 588,
    "S2 Common": 7,
    "S2 Uncommon": 4,
    "S2 Rare": 2,
    "S2 Epic": 2,
    "S3 Legendary": 658,
    "S3 Common": 826,
    "S3 Uncommon": 165,
    "S3 Ultra-Rare": 13,
    "S3 Rare": 120,
    "S3 Epic": 29,
    "S1 Uncommon": 5,
    "S1 Common": 1
  },
  {
    "Nation": "Siwale",
    "Junk Value": 1165.51,
    "Bank": 3503.52,
    "Deck Value": 98125.33,
    "Card Count": 1408,
    "Deck Capacity": 3186,
    "Common": 71,
    "Legendary": 1073,
    "Ultra-Rare": 61,
    "Epic": 156,
    "Uncommon": 32,
    "Rare": 15,
    "S1": 718,
    "S2": 219,
    "S3": 471,
    "S1 Common": 70,
    "S1 Legendary": 407,
    "S2 Legendary": 214,
    "S1 Ultra-Rare": 58,
    "S1 Epic": 143,
    "S1 Uncommon": 27,
    "S1 Rare": 13,
    "S2 Uncommon": 4,
    "S2 Epic": 1,
    "S3 Legendary": 452,
    "S3 Epic": 12,
    "S3 Rare": 2,
    "S3 Ultra-Rare": 3,
    "S3 Uncommon": 1,
    "S3 Common": 1
  },
  {
    "Nation": "Eugeniee",
    "Junk Value": 1132.87,
    "Bank": 2913.57,
    "Deck Value": 98069.4,
    "Card Count": 4745,
    "Deck Capacity": 4918,
    "Common": 1712,
    "Epic": 699,
    "Uncommon": 473,
    "Ultra-Rare": 568,
    "Legendary": 629,
    "Rare": 664,
    "S1": 85,
    "S2": 210,
    "S3": 4450,
    "S1 Common": 26,
    "S1 Epic": 38,
    "S1 Uncommon": 12,
    "S1 Ultra-Rare": 9,
    "S2 Uncommon": 19,
    "S2 Epic": 33,
    "S2 Common": 43,
    "S2 Ultra-Rare": 25,
    "S2 Legendary": 80,
    "S2 Rare": 10,
    "S3 Ultra-Rare": 534,
    "S3 Legendary": 549,
    "S3 Common": 1643,
    "S3 Rare": 654,
    "S3 Uncommon": 442,
    "S3 Epic": 628
  },
  {
    "Nation": "Yodle",
    "Junk Value": 1391.61,
    "Bank": 1240.64,
    "Deck Value": 97163.58,
    "Card Count": 26838,
    "Deck Capacity": 27074,
    "Common": 12561,
    "Uncommon": 6624,
    "Rare": 4271,
    "Ultra-Rare": 2579,
    "Epic": 768,
    "Legendary": 35,
    "S1": 3151,
    "S2": 10941,
    "S3": 12746,
    "S1 Common": 1666,
    "S1 Uncommon": 802,
    "S1 Rare": 354,
    "S1 Ultra-Rare": 244,
    "S1 Epic": 83,
    "S2 Rare": 1663,
    "S2 Common": 4636,
    "S2 Uncommon": 3243,
    "S2 Ultra-Rare": 1228,
    "S1 Legendary": 2,
    "S2 Epic": 164,
    "S2 Legendary": 7,
    "S3 Ultra-Rare": 1107,
    "S3 Epic": 521,
    "S3 Common": 6259,
    "S3 Uncommon": 2579,
    "S3 Legendary": 26,
    "S3 Rare": 2254
  },
  {
    "Nation": "Apexiala",
    "Junk Value": 1889.51,
    "Bank": 2522.46,
    "Deck Value": 86606.25,
    "Card Count": 41891,
    "Deck Capacity": 42284,
    "Common": 31816,
    "Uncommon": 5667,
    "Rare": 1768,
    "Ultra-Rare": 1340,
    "Legendary": 740,
    "Epic": 560,
    "S2": 14072,
    "S1": 1126,
    "S3": 26693,
    "S2 Common": 9830,
    "S1 Common": 487,
    "S1 Uncommon": 330,
    "S2 Uncommon": 2311,
    "S1 Rare": 153,
    "S1 Ultra-Rare": 90,
    "S2 Ultra-Rare": 521,
    "S1 Legendary": 27,
    "S1 Epic": 39,
    "S2 Epic": 278,
    "S2 Legendary": 380,
    "S2 Rare": 752,
    "S3 Common": 21499,
    "S3 Rare": 863,
    "S3 Uncommon": 3026,
    "S3 Legendary": 333,
    "S3 Ultra-Rare": 729,
    "S3 Epic": 243
  },
  {
    "Nation": "Benevolent 1",
    "Junk Value": 654.62,
    "Bank": 20394.7,
    "Deck Value": 81062.42,
    "Card Count": 3206,
    "Deck Capacity": 6372,
    "Epic": 183,
    "Uncommon": 591,
    "Common": 1337,
    "Rare": 262,
    "Ultra-Rare": 391,
    "Legendary": 442,
    "S1": 1271,
    "S2": 986,
    "S3": 949,
    "S1 Epic": 102,
    "S1 Uncommon": 212,
    "S1 Common": 625,
    "S1 Rare": 146,
    "S2 Uncommon": 248,
    "S1 Ultra-Rare": 62,
    "S2 Common": 349,
    "S2 Ultra-Rare": 142,
    "S1 Legendary": 124,
    "S2 Rare": 40,
    "S2 Legendary": 175,
    "S2 Epic": 32,
    "S3 Ultra-Rare": 187,
    "S3 Legendary": 143,
    "S3 Rare": 76,
    "S3 Epic": 49,
    "S3 Common": 363,
    "S3 Uncommon": 131
  },
  {
    "Nation": "Klaus Devestatorie",
    "Junk Value": 3715.63,
    "Bank": 14165.6,
    "Deck Value": 80857.2,
    "Card Count": 10772,
    "Deck Capacity": 11092,
    "Ultra-Rare": 1384,
    "Common": 1903,
    "Epic": 4954,
    "Rare": 718,
    "Uncommon": 916,
    "Legendary": 897,
    "S1": 676,
    "S2": 157,
    "S3": 9939,
    "S1 Ultra-Rare": 190,
    "S1 Common": 237,
    "S1 Epic": 104,
    "S1 Rare": 36,
    "S1 Uncommon": 95,
    "S1 Legendary": 14,
    "S2 Epic": 63,
    "S2 Uncommon": 43,
    "S2 Rare": 21,
    "S2 Common": 22,
    "S2 Ultra-Rare": 5,
    "S3 Common": 1644,
    "S3 Epic": 4787,
    "S3 Uncommon": 778,
    "S3 Legendary": 880,
    "S3 Ultra-Rare": 1189,
    "S3 Rare": 661,
    "S2 Legendary": 3
  },
  {
    "Nation": "Valoptia",
    "Junk Value": 790.2,
    "Bank": 5478.73,
    "Deck Value": 79187.05,
    "Card Count": 1131,
    "Deck Capacity": 1336,
    "Legendary": 778,
    "Common": 150,
    "Rare": 154,
    "Ultra-Rare": 19,
    "Epic": 12,
    "Uncommon": 18,
    "S1": 194,
    "S2": 187,
    "S3": 750,
    "S1 Legendary": 186,
    "S2 Legendary": 182,
    "S3 Legendary": 410,
    "S3 Common": 143,
    "S3 Rare": 152,
    "S3 Ultra-Rare": 18,
    "S1 Rare": 2,
    "S3 Epic": 12,
    "S2 Uncommon": 2,
    "S3 Uncommon": 15,
    "S1 Common": 5,
    "S2 Common": 2,
    "S1 Uncommon": 1,
    "S2 Ultra-Rare": 1
  },
  {
    "Nation": "Midlands",
    "Junk Value": 3457.59,
    "Bank": 3001.97,
    "Deck Value": 78821.33,
    "Card Count": 8781,
    "Deck Capacity": 8958,
    "Uncommon": 1129,
    "Epic": 4733,
    "Common": 164,
    "Ultra-Rare": 1065,
    "Rare": 870,
    "Legendary": 820,
    "S1": 177,
    "S2": 1234,
    "S3": 7370,
    "S1 Uncommon": 33,
    "S1 Epic": 44,
    "S1 Common": 7,
    "S1 Ultra-Rare": 26,
    "S1 Rare": 12,
    "S1 Legendary": 55,
    "S2 Uncommon": 163,
    "S2 Rare": 116,
    "S2 Ultra-Rare": 134,
    "S2 Legendary": 610,
    "S2 Epic": 191,
    "S2 Common": 20,
    "S3 Common": 137,
    "S3 Ultra-Rare": 905,
    "S3 Rare": 742,
    "S3 Legendary": 155,
    "S3 Uncommon": 933,
    "S3 Epic": 4498
  },
  {
    "Nation": "Elegarth",
    "Junk Value": 864.49,
    "Bank": 551.59,
    "Deck Value": 77739.8,
    "Card Count": 2155,
    "Deck Capacity": 4479,
    "Uncommon": 192,
    "Legendary": 722,
    "Common": 349,
    "Ultra-Rare": 442,
    "Epic": 82,
    "Rare": 368,
    "S1": 342,
    "S2": 778,
    "S3": 1035,
    "S1 Uncommon": 65,
    "S1 Legendary": 184,
    "S2 Legendary": 277,
    "S1 Common": 63,
    "S1 Ultra-Rare": 14,
    "S1 Epic": 13,
    "S2 Epic": 8,
    "S1 Rare": 3,
    "S2 Common": 69,
    "S2 Ultra-Rare": 109,
    "S2 Rare": 291,
    "S2 Uncommon": 24,
    "S3 Ultra-Rare": 319,
    "S3 Legendary": 261,
    "S3 Common": 217,
    "S3 Epic": 61,
    "S3 Uncommon": 103,
    "S3 Rare": 74
  },
  {
    "Nation": "Power For People",
    "Junk Value": 136.74,
    "Bank": 1703.55,
    "Deck Value": 76437.49,
    "Card Count": 3623,
    "Deck Capacity": 3894,
    "Uncommon": 520,
    "Rare": 187,
    "Common": 2724,
    "Legendary": 35,
    "Ultra-Rare": 100,
    "Epic": 57,
    "S1": 38,
    "S2": 106,
    "S3": 3479,
    "S1 Uncommon": 17,
    "S1 Rare": 5,
    "S1 Common": 14,
    "S1 Legendary": 1,
    "S2 Common": 51,
    "S2 Uncommon": 23,
    "S2 Rare": 18,
    "S2 Ultra-Rare": 8,
    "S2 Epic": 6,
    "S3 Common": 2659,
    "S3 Ultra-Rare": 91,
    "S3 Epic": 51,
    "S3 Rare": 164,
    "S3 Uncommon": 480,
    "S3 Legendary": 34,
    "S1 Ultra-Rare": 1
  },
  {
    "Nation": "One Small Island",
    "Junk Value": 847.56,
    "Bank": 174.23,
    "Deck Value": 72351.42,
    "Card Count": 1803,
    "Deck Capacity": 4037,
    "Legendary": 752,
    "Common": 651,
    "Uncommon": 181,
    "Epic": 148,
    "Rare": 41,
    "Ultra-Rare": 30,
    "S1": 267,
    "S2": 1314,
    "S3": 222,
    "S1 Legendary": 74,
    "S1 Common": 75,
    "S1 Uncommon": 17,
    "S1 Epic": 88,
    "S2 Epic": 37,
    "S2 Common": 553,
    "S2 Legendary": 532,
    "S1 Rare": 4,
    "S1 Ultra-Rare": 9,
    "S2 Uncommon": 158,
    "S2 Rare": 25,
    "S2 Ultra-Rare": 9,
    "S3 Legendary": 146,
    "S3 Ultra-Rare": 12,
    "S3 Epic": 23,
    "S3 Common": 23,
    "S3 Uncommon": 6,
    "S3 Rare": 12
  },
  {
    "Nation": "New Sunville",
    "Junk Value": 802.47,
    "Bank": 24.72,
    "Deck Value": 70501.08,
    "Card Count": 2640,
    "Deck Capacity": 5393,
    "Common": 847,
    "Uncommon": 480,
    "Rare": 110,
    "Epic": 298,
    "Ultra-Rare": 355,
    "Legendary": 550,
    "S2": 1172,
    "S1": 159,
    "S3": 1309,
    "S2 Common": 455,
    "S1 Common": 36,
    "S1 Uncommon": 32,
    "S1 Rare": 9,
    "S2 Epic": 58,
    "S1 Ultra-Rare": 22,
    "S1 Epic": 31,
    "S1 Legendary": 29,
    "S2 Ultra-Rare": 84,
    "S2 Uncommon": 357,
    "S2 Legendary": 169,
    "S2 Rare": 49,
    "S3 Common": 356,
    "S3 Legendary": 352,
    "S3 Uncommon": 91,
    "S3 Ultra-Rare": 249,
    "S3 Epic": 209,
    "S3 Rare": 52
  },
  {
    "Nation": "Shibutani",
    "Junk Value": 790.29,
    "Bank": 675.57,
    "Deck Value": 69891.14,
    "Card Count": 3161,
    "Deck Capacity": 4037,
    "Epic": 269,
    "Ultra-Rare": 364,
    "Uncommon": 601,
    "Legendary": 542,
    "Common": 1094,
    "Rare": 291,
    "S1": 223,
    "S2": 466,
    "S3": 2472,
    "S1 Epic": 84,
    "S1 Ultra-Rare": 56,
    "S1 Uncommon": 16,
    "S1 Legendary": 42,
    "S2 Legendary": 134,
    "S2 Common": 181,
    "S1 Rare": 5,
    "S1 Common": 20,
    "S2 Uncommon": 56,
    "S2 Ultra-Rare": 58,
    "S2 Epic": 31,
    "S2 Rare": 6,
    "S3 Common": 893,
    "S3 Epic": 154,
    "S3 Legendary": 366,
    "S3 Uncommon": 529,
    "S3 Ultra-Rare": 250,
    "S3 Rare": 280
  },
  {
    "Nation": "The Atlae Isles",
    "Junk Value": 880.93,
    "Bank": 30.06,
    "Deck Value": 62587.54,
    "Card Count": 3926,
    "Deck Capacity": 5393,
    "Rare": 99,
    "Epic": 240,
    "Ultra-Rare": 471,
    "Common": 2213,
    "Legendary": 631,
    "Uncommon": 272,
    "S1": 569,
    "S2": 1750,
    "S3": 1607,
    "S1 Rare": 34,
    "S1 Epic": 82,
    "S2 Ultra-Rare": 333,
    "S1 Common": 105,
    "S1 Ultra-Rare": 117,
    "S1 Legendary": 137,
    "S1 Uncommon": 94,
    "S2 Common": 701,
    "S2 Uncommon": 85,
    "S2 Epic": 124,
    "S2 Legendary": 461,
    "S2 Rare": 46,
    "S3 Common": 1407,
    "S3 Uncommon": 93,
    "S3 Ultra-Rare": 21,
    "S3 Legendary": 33,
    "S3 Epic": 34,
    "S3 Rare": 19
  },
  {
    "Nation": "Giraffeton",
    "Junk Value": 1521.2,
    "Bank": 1904.31,
    "Deck Value": 57053.79,
    "Card Count": 39641,
    "Deck Capacity": 50440,
    "Uncommon": 5039,
    "Common": 30165,
    "Ultra-Rare": 2003,
    "Rare": 1506,
    "Epic": 722,
    "Legendary": 206,
    "S1": 59,
    "S2": 3978,
    "S3": 35604,
    "S1 Uncommon": 15,
    "S1 Common": 26,
    "S2 Uncommon": 830,
    "S2 Ultra-Rare": 852,
    "S2 Rare": 279,
    "S2 Epic": 272,
    "S2 Common": 1680,
    "S1 Rare": 6,
    "S2 Legendary": 65,
    "S1 Ultra-Rare": 6,
    "S1 Epic": 4,
    "S3 Common": 28459,
    "S3 Ultra-Rare": 1145,
    "S3 Uncommon": 4194,
    "S3 Epic": 446,
    "S3 Rare": 1221,
    "S3 Legendary": 139,
    "S1 Legendary": 2
  },
  {
    "Nation": "Andusre",
    "Junk Value": 788.96,
    "Bank": 1603.92,
    "Deck Value": 56823.52,
    "Card Count": 1032,
    "Deck Capacity": 3186,
    "Common": 111,
    "Legendary": 772,
    "Uncommon": 77,
    "Ultra-Rare": 30,
    "Epic": 12,
    "Rare": 30,
    "S1": 72,
    "S2": 783,
    "S3": 177,
    "S1 Common": 2,
    "S2 Legendary": 642,
    "S1 Legendary": 67,
    "S1 Uncommon": 2,
    "S2 Uncommon": 49,
    "S2 Common": 50,
    "S2 Ultra-Rare": 24,
    "S1 Epic": 1,
    "S2 Epic": 5,
    "S2 Rare": 13,
    "S3 Uncommon": 26,
    "S3 Legendary": 63,
    "S3 Rare": 17,
    "S3 Common": 59,
    "S3 Ultra-Rare": 6,
    "S3 Epic": 6
  },
  {
    "Nation": "Waterfall State",
    "Junk Value": 1012.27,
    "Bank": 224.07,
    "Deck Value": 54594.35,
    "Card Count": 6456,
    "Deck Capacity": 6558,
    "Common": 4427,
    "Uncommon": 542,
    "Legendary": 789,
    "Ultra-Rare": 197,
    "Epic": 225,
    "Rare": 276,
    "S1": 854,
    "S2": 1472,
    "S3": 4130,
    "S1 Common": 295,
    "S1 Uncommon": 273,
    "S2 Legendary": 198,
    "S1 Ultra-Rare": 71,
    "S2 Common": 870,
    "S1 Epic": 26,
    "S1 Rare": 176,
    "S1 Legendary": 13,
    "S2 Rare": 72,
    "S2 Uncommon": 179,
    "S2 Epic": 88,
    "S2 Ultra-Rare": 65,
    "S3 Common": 3262,
    "S3 Legendary": 578,
    "S3 Ultra-Rare": 61,
    "S3 Rare": 28,
    "S3 Uncommon": 90,
    "S3 Epic": 111
  },
  {
    "Nation": "The Bank Of Caprica",
    "Junk Value": 28.75,
    "Bank": 505.69,
    "Deck Value": 54521.77,
    "Card Count": 2096,
    "Deck Capacity": 2592,
    "Common": 1000,
    "Uncommon": 361,
    "Rare": 733,
    "Ultra-Rare": 1,
    "Epic": 1,
    "S2": 861,
    "S1": 2,
    "S3": 1233,
    "S2 Common": 710,
    "S1 Uncommon": 2,
    "S2 Uncommon": 151,
    "S3 Common": 290,
    "S3 Uncommon": 208,
    "S3 Rare": 733,
    "S3 Ultra-Rare": 1,
    "S3 Epic": 1
  },
  {
    "Nation": "Drew Durrnil",
    "Junk Value": 896.07,
    "Bank": 1708.38,
    "Deck Value": 54220.1,
    "Card Count": 3196,
    "Deck Capacity": 3255,
    "Epic": 302,
    "Ultra-Rare": 306,
    "Common": 1037,
    "Legendary": 646,
    "Rare": 355,
    "Uncommon": 550,
    "S1": 43,
    "S2": 310,
    "S3": 2843,
    "S1 Epic": 3,
    "S1 Ultra-Rare": 5,
    "S1 Common": 19,
    "S2 Legendary": 14,
    "S2 Rare": 41,
    "S2 Epic": 39,
    "S2 Ultra-Rare": 106,
    "S2 Uncommon": 51,
    "S2 Common": 59,
    "S1 Rare": 11,
    "S1 Uncommon": 4,
    "S3 Uncommon": 495,
    "S3 Epic": 260,
    "S3 Ultra-Rare": 195,
    "S3 Common": 959,
    "S3 Rare": 303,
    "S3 Legendary": 631,
    "S1 Legendary": 1
  },
  {
    "Nation": "Inven",
    "Junk Value": 414.38,
    "Bank": 5175.64,
    "Deck Value": 52202.09,
    "Card Count": 1166,
    "Deck Capacity": 3606,
    "Uncommon": 359,
    "Epic": 105,
    "Rare": 58,
    "Legendary": 310,
    "Common": 173,
    "Ultra-Rare": 161,
    "S1": 196,
    "S2": 407,
    "S3": 563,
    "S1 Uncommon": 48,
    "S1 Epic": 34,
    "S1 Rare": 20,
    "S1 Legendary": 29,
    "S1 Common": 27,
    "S1 Ultra-Rare": 38,
    "S2 Uncommon": 239,
    "S2 Common": 62,
    "S2 Legendary": 37,
    "S2 Ultra-Rare": 32,
    "S2 Epic": 26,
    "S2 Rare": 11,
    "S3 Legendary": 244,
    "S3 Ultra-Rare": 91,
    "S3 Uncommon": 72,
    "S3 Epic": 45,
    "S3 Common": 84,
    "S3 Rare": 27
  },
  {
    "Nation": "Humansanity",
    "Junk Value": 591.06,
    "Bank": 917.61,
    "Deck Value": 50488.45,
    "Card Count": 892,
    "Deck Capacity": 3186,
    "Legendary": 538,
    "Uncommon": 59,
    "Rare": 96,
    "Ultra-Rare": 65,
    "Epic": 73,
    "Common": 61,
    "S1": 84,
    "S2": 772,
    "S3": 36,
    "S1 Legendary": 51,
    "S2 Uncommon": 45,
    "S1 Uncommon": 5,
    "S2 Rare": 87,
    "S2 Ultra-Rare": 45,
    "S2 Legendary": 485,
    "S1 Epic": 8,
    "S1 Ultra-Rare": 12,
    "S1 Common": 6,
    "S1 Rare": 2,
    "S2 Epic": 58,
    "S2 Common": 52,
    "S3 Uncommon": 9,
    "S3 Rare": 7,
    "S3 Ultra-Rare": 8,
    "S3 Common": 3,
    "S3 Epic": 7,
    "S3 Legendary": 2
  },
  {
    "Nation": "Ballotonia",
    "Junk Value": 1202.47,
    "Bank": 2191.53,
    "Deck Value": 48961.71,
    "Card Count": 5539,
    "Deck Capacity": 6344,
    "Uncommon": 1341,
    "Common": 992,
    "Ultra-Rare": 1090,
    "Rare": 869,
    "Epic": 679,
    "Legendary": 568,
    "S1": 3648,
    "S2": 834,
    "S3": 1057,
    "S1 Uncommon": 1054,
    "S1 Common": 667,
    "S1 Ultra-Rare": 726,
    "S1 Rare": 601,
    "S2 Epic": 125,
    "S1 Epic": 416,
    "S1 Legendary": 184,
    "S2 Rare": 103,
    "S2 Common": 135,
    "S2 Legendary": 169,
    "S2 Ultra-Rare": 167,
    "S2 Uncommon": 135,
    "S3 Rare": 165,
    "S3 Ultra-Rare": 197,
    "S3 Legendary": 215,
    "S3 Common": 190,
    "S3 Uncommon": 152,
    "S3 Epic": 138
  },
  {
    "Nation": "Numero Capitan",
    "Junk Value": 607.92,
    "Bank": 542.18,
    "Deck Value": 46707.69,
    "Card Count": 1769,
    "Deck Capacity": 3186,
    "Rare": 158,
    "Common": 417,
    "Ultra-Rare": 255,
    "Epic": 117,
    "Uncommon": 345,
    "Legendary": 477,
    "S1": 372,
    "S2": 828,
    "S3": 569,
    "S1 Rare": 40,
    "S1 Common": 105,
    "S1 Ultra-Rare": 60,
    "S1 Epic": 35,
    "S1 Uncommon": 68,
    "S2 Legendary": 171,
    "S1 Legendary": 64,
    "S2 Common": 219,
    "S2 Uncommon": 210,
    "S2 Ultra-Rare": 114,
    "S2 Rare": 73,
    "S2 Epic": 41,
    "S3 Uncommon": 67,
    "S3 Ultra-Rare": 81,
    "S3 Rare": 45,
    "S3 Legendary": 242,
    "S3 Common": 93,
    "S3 Epic": 41
  },
  {
    "Nation": "The Hoard Of The Dragon",
    "Junk Value": 336.53,
    "Bank": 256.53,
    "Deck Value": 45197.68,
    "Card Count": 2026,
    "Deck Capacity": 4000,
    "Legendary": 233,
    "Common": 678,
    "Rare": 326,
    "Ultra-Rare": 127,
    "Epic": 85,
    "Uncommon": 577,
    "S1": 9,
    "S2": 15,
    "S3": 2002,
    "S1 Legendary": 2,
    "S2 Common": 7,
    "S2 Rare": 3,
    "S2 Legendary": 2,
    "S2 Ultra-Rare": 1,
    "S3 Common": 670,
    "S3 Rare": 322,
    "S3 Legendary": 229,
    "S3 Epic": 83,
    "S3 Ultra-Rare": 125,
    "S3 Uncommon": 573,
    "S2 Uncommon": 1,
    "S1 Uncommon": 3,
    "S1 Rare": 1,
    "S1 Ultra-Rare": 1,
    "S1 Common": 1,
    "S2 Epic": 1,
    "S1 Epic": 1
  },
  {
    "Nation": "Hyperwolf",
    "Junk Value": 696.83,
    "Bank": 1575.02,
    "Deck Value": 44264.15,
    "Card Count": 3057,
    "Deck Capacity": 3336,
    "Epic": 140,
    "Common": 1073,
    "Ultra-Rare": 138,
    "Rare": 329,
    "Legendary": 547,
    "Uncommon": 830,
    "S2": 105,
    "S1": 129,
    "S3": 2823,
    "S2 Epic": 6,
    "S1 Common": 102,
    "S2 Ultra-Rare": 30,
    "S2 Rare": 11,
    "S2 Legendary": 5,
    "S1 Uncommon": 20,
    "S2 Common": 31,
    "S2 Uncommon": 22,
    "S3 Common": 940,
    "S3 Legendary": 542,
    "S3 Epic": 133,
    "S3 Uncommon": 788,
    "S3 Rare": 315,
    "S3 Ultra-Rare": 105,
    "S1 Ultra-Rare": 3,
    "S1 Epic": 1,
    "S1 Rare": 3
  },
  {
    "Nation": "Cleon The First",
    "Junk Value": 27.81,
    "Bank": 551.39,
    "Deck Value": 43023.86,
    "Card Count": 2048,
    "Deck Capacity": 2592,
    "Common": 1886,
    "Epic": 5,
    "Uncommon": 109,
    "Rare": 47,
    "Legendary": 1,
    "S2": 1602,
    "S1": 1,
    "S3": 445,
    "S2 Common": 1510,
    "S1 Epic": 1,
    "S2 Uncommon": 92,
    "S3 Common": 376,
    "S3 Uncommon": 17,
    "S3 Rare": 47,
    "S3 Epic": 4,
    "S3 Legendary": 1
  },
  {
    "Nation": "Montrandec",
    "Junk Value": 1667.36,
    "Bank": 19.95,
    "Deck Value": 42996.74,
    "Card Count": 5616,
    "Deck Capacity": 5770,
    "Legendary": 525,
    "Epic": 2014,
    "Ultra-Rare": 422,
    "Common": 1481,
    "Uncommon": 723,
    "Rare": 451,
    "S1": 418,
    "S2": 1554,
    "S3": 3644,
    "S1 Legendary": 13,
    "S1 Epic": 27,
    "S1 Ultra-Rare": 82,
    "S1 Common": 157,
    "S1 Uncommon": 91,
    "S2 Epic": 89,
    "S1 Rare": 48,
    "S2 Common": 934,
    "S2 Rare": 67,
    "S2 Legendary": 283,
    "S2 Uncommon": 166,
    "S2 Ultra-Rare": 15,
    "S3 Epic": 1898,
    "S3 Rare": 336,
    "S3 Uncommon": 466,
    "S3 Common": 390,
    "S3 Ultra-Rare": 325,
    "S3 Legendary": 229
  },
  {
    "Nation": "Hujen",
    "Junk Value": 671.96,
    "Bank": 5757.76,
    "Deck Value": 42616.01,
    "Card Count": 1733,
    "Deck Capacity": 1918,
    "Uncommon": 281,
    "Epic": 506,
    "Ultra-Rare": 266,
    "Rare": 159,
    "Common": 171,
    "Legendary": 350,
    "S1": 94,
    "S2": 263,
    "S3": 1376,
    "S1 Uncommon": 8,
    "S1 Epic": 76,
    "S1 Ultra-Rare": 6,
    "S1 Rare": 1,
    "S2 Ultra-Rare": 37,
    "S2 Common": 29,
    "S2 Legendary": 45,
    "S2 Epic": 84,
    "S2 Uncommon": 59,
    "S2 Rare": 9,
    "S3 Epic": 346,
    "S3 Rare": 149,
    "S3 Legendary": 303,
    "S3 Common": 141,
    "S3 Ultra-Rare": 223,
    "S3 Uncommon": 214,
    "S1 Common": 1,
    "S1 Legendary": 2
  },
  {
    "Nation": "Anjan Kloss",
    "Junk Value": 1809.3,
    "Bank": 1629.32,
    "Deck Value": 41860.11,
    "Card Count": 4565,
    "Deck Capacity": 4750,
    "Rare": 82,
    "Legendary": 583,
    "Common": 670,
    "Uncommon": 756,
    "Ultra-Rare": 184,
    "Epic": 2290,
    "S1": 39,
    "S2": 66,
    "S3": 4460,
    "S1 Rare": 2,
    "S2 Legendary": 1,
    "S2 Common": 16,
    "S2 Uncommon": 11,
    "S2 Ultra-Rare": 7,
    "S1 Legendary": 1,
    "S2 Rare": 2,
    "S2 Epic": 29,
    "S3 Common": 645,
    "S3 Uncommon": 740,
    "S3 Legendary": 581,
    "S3 Ultra-Rare": 176,
    "S3 Epic": 2240,
    "S3 Rare": 78,
    "S1 Epic": 21,
    "S1 Uncommon": 5,
    "S1 Common": 9,
    "S1 Ultra-Rare": 1
  },
  {
    "Nation": "Bastile",
    "Junk Value": 599.73,
    "Bank": 6668.0,
    "Deck Value": 41873.45,
    "Card Count": 3297,
    "Deck Capacity": 3500,
    "Legendary": 394,
    "Uncommon": 285,
    "Common": 1888,
    "Ultra-Rare": 183,
    "Rare": 275,
    "Epic": 272,
    "S1": 52,
    "S2": 65,
    "S3": 3180,
    "S1 Legendary": 8,
    "S1 Uncommon": 7,
    "S1 Common": 25,
    "S1 Ultra-Rare": 7,
    "S1 Rare": 1,
    "S1 Epic": 4,
    "S2 Uncommon": 5,
    "S2 Legendary": 12,
    "S2 Rare": 1,
    "S2 Epic": 11,
    "S2 Common": 34,
    "S3 Uncommon": 273,
    "S3 Common": 1829,
    "S3 Epic": 257,
    "S3 Legendary": 374,
    "S3 Rare": 273,
    "S3 Ultra-Rare": 174,
    "S2 Ultra-Rare": 2
  },
  {
    "Nation": "Rhenna",
    "Junk Value": 672.59,
    "Bank": 20.12,
    "Deck Value": 41690.46,
    "Card Count": 2746,
    "Deck Capacity": 3288,
    "Epic": 317,
    "Legendary": 452,
    "Common": 884,
    "Uncommon": 845,
    "Ultra-Rare": 55,
    "Rare": 193,
    "S1": 54,
    "S2": 53,
    "S3": 2639,
    "S1 Epic": 10,
    "S2 Epic": 12,
    "S2 Legendary": 4,
    "S2 Common": 18,
    "S2 Uncommon": 18,
    "S1 Uncommon": 6,
    "S1 Common": 34,
    "S2 Ultra-Rare": 1,
    "S3 Common": 832,
    "S3 Uncommon": 821,
    "S3 Legendary": 448,
    "S3 Rare": 189,
    "S3 Epic": 295,
    "S1 Rare": 4,
    "S3 Ultra-Rare": 54
  },
  {
    "Nation": "Super Awesome Fun Times",
    "Junk Value": 1243.88,
    "Bank": 2804.46,
    "Deck Value": 41481.56,
    "Card Count": 19930,
    "Deck Capacity": 27674,
    "Ultra-Rare": 1087,
    "Rare": 1175,
    "Epic": 462,
    "Uncommon": 5141,
    "Common": 11643,
    "Legendary": 422,
    "S1": 942,
    "S2": 7026,
    "S3": 11962,
    "S1 Ultra-Rare": 127,
    "S1 Rare": 94,
    "S1 Epic": 78,
    "S1 Uncommon": 319,
    "S1 Common": 321,
    "S2 Uncommon": 1592,
    "S2 Ultra-Rare": 345,
    "S2 Common": 4601,
    "S2 Epic": 145,
    "S2 Rare": 299,
    "S1 Legendary": 3,
    "S2 Legendary": 44,
    "S3 Uncommon": 3230,
    "S3 Common": 6721,
    "S3 Rare": 782,
    "S3 Ultra-Rare": 615,
    "S3 Epic": 239,
    "S3 Legendary": 375
  },
  {
    "Nation": "Zacbo",
    "Junk Value": 1291.01,
    "Bank": 45.04,
    "Deck Value": 39713.5,
    "Card Count": 3917,
    "Deck Capacity": 4000,
    "Rare": 268,
    "Uncommon": 485,
    "Common": 916,
    "Ultra-Rare": 253,
    "Epic": 1576,
    "Legendary": 419,
    "S1": 387,
    "S2": 470,
    "S3": 3060,
    "S1 Rare": 65,
    "S1 Uncommon": 146,
    "S1 Common": 138,
    "S1 Ultra-Rare": 20,
    "S1 Epic": 15,
    "S2 Common": 247,
    "S2 Epic": 23,
    "S2 Ultra-Rare": 25,
    "S2 Rare": 57,
    "S3 Epic": 1538,
    "S3 Uncommon": 224,
    "S3 Common": 531,
    "S3 Rare": 146,
    "S3 Legendary": 413,
    "S3 Ultra-Rare": 208,
    "S1 Legendary": 3,
    "S2 Uncommon": 115,
    "S2 Legendary": 3
  },
  {
    "Nation": "The Rhein States",
    "Junk Value": 512.54,
    "Bank": 1306.04,
    "Deck Value": 39281.28,
    "Card Count": 1720,
    "Deck Capacity": 3606,
    "Legendary": 424,
    "Common": 529,
    "Uncommon": 353,
    "Epic": 74,
    "Ultra-Rare": 143,
    "Rare": 197,
    "S2": 413,
    "S1": 159,
    "S3": 1148,
    "S2 Legendary": 185,
    "S1 Legendary": 90,
    "S2 Common": 77,
    "S1 Uncommon": 30,
    "S1 Common": 14,
    "S1 Epic": 12,
    "S1 Ultra-Rare": 9,
    "S1 Rare": 4,
    "S2 Rare": 55,
    "S2 Epic": 24,
    "S2 Uncommon": 66,
    "S2 Ultra-Rare": 6,
    "S3 Ultra-Rare": 128,
    "S3 Legendary": 149,
    "S3 Common": 438,
    "S3 Epic": 38,
    "S3 Rare": 138,
    "S3 Uncommon": 257
  },
  {
    "Nation": "Kyorgia",
    "Junk Value": 329.39,
    "Bank": 29.07,
    "Deck Value": 38901.06,
    "Card Count": 650,
    "Deck Capacity": 1642,
    "Ultra-Rare": 60,
    "Epic": 169,
    "Uncommon": 82,
    "Legendary": 228,
    "Common": 79,
    "Rare": 32,
    "S1": 92,
    "S2": 490,
    "S3": 68,
    "S1 Ultra-Rare": 15,
    "S1 Epic": 17,
    "S1 Uncommon": 19,
    "S1 Legendary": 21,
    "S1 Common": 16,
    "S1 Rare": 4,
    "S2 Epic": 145,
    "S2 Uncommon": 45,
    "S2 Ultra-Rare": 33,
    "S2 Common": 46,
    "S2 Legendary": 205,
    "S2 Rare": 16,
    "S3 Rare": 12,
    "S3 Ultra-Rare": 12,
    "S3 Uncommon": 18,
    "S3 Common": 17,
    "S3 Epic": 7,
    "S3 Legendary": 2
  },
  {
    "Nation": "Cavedweller",
    "Junk Value": 353.41,
    "Bank": 1090.18,
    "Deck Value": 36302.47,
    "Card Count": 761,
    "Deck Capacity": 2779,
    "Ultra-Rare": 105,
    "Uncommon": 111,
    "Common": 186,
    "Rare": 23,
    "Epic": 22,
    "Legendary": 314,
    "S1": 142,
    "S2": 606,
    "S3": 13,
    "S1 Ultra-Rare": 16,
    "S1 Uncommon": 34,
    "S1 Common": 26,
    "S1 Rare": 4,
    "S1 Epic": 4,
    "S1 Legendary": 58,
    "S2 Common": 159,
    "S2 Ultra-Rare": 87,
    "S2 Rare": 18,
    "S2 Legendary": 253,
    "S2 Epic": 18,
    "S2 Uncommon": 71,
    "S3 Ultra-Rare": 2,
    "S3 Uncommon": 6,
    "S3 Common": 1,
    "S3 Legendary": 3,
    "S3 Rare": 1
  },
  {
    "Nation": "Richardian Savoy",
    "Junk Value": 882.71,
    "Bank": 1195.62,
    "Deck Value": 34098.85,
    "Card Count": 3401,
    "Deck Capacity": 4010,
    "Legendary": 410,
    "Uncommon": 464,
    "Epic": 740,
    "Common": 1211,
    "Rare": 239,
    "Ultra-Rare": 337,
    "S1": 103,
    "S2": 973,
    "S3": 2325,
    "S1 Legendary": 2,
    "S1 Uncommon": 17,
    "S1 Epic": 14,
    "S2 Common": 413,
    "S2 Legendary": 18,
    "S2 Uncommon": 272,
    "S2 Rare": 114,
    "S2 Ultra-Rare": 69,
    "S2 Epic": 87,
    "S1 Common": 60,
    "S1 Rare": 7,
    "S3 Uncommon": 175,
    "S3 Common": 738,
    "S3 Epic": 639,
    "S3 Rare": 118,
    "S3 Ultra-Rare": 265,
    "S3 Legendary": 390,
    "S1 Ultra-Rare": 3
  },
  {
    "Nation": "Kakastania",
    "Junk Value": 692.44,
    "Bank": 2680.01,
    "Deck Value": 33957.37,
    "Card Count": 2980,
    "Deck Capacity": 3255,
    "Common": 1189,
    "Ultra-Rare": 203,
    "Rare": 264,
    "Uncommon": 489,
    "Legendary": 396,
    "Epic": 439,
    "S1": 218,
    "S2": 222,
    "S3": 2540,
    "S1 Common": 90,
    "S1 Ultra-Rare": 23,
    "S1 Rare": 49,
    "S1 Uncommon": 31,
    "S1 Legendary": 9,
    "S2 Common": 162,
    "S1 Epic": 16,
    "S2 Uncommon": 22,
    "S2 Epic": 6,
    "S2 Ultra-Rare": 9,
    "S2 Legendary": 13,
    "S2 Rare": 10,
    "S3 Common": 937,
    "S3 Epic": 417,
    "S3 Legendary": 374,
    "S3 Uncommon": 436,
    "S3 Rare": 205,
    "S3 Ultra-Rare": 171
  },
  {
    "Nation": "Rain Delay",
    "Junk Value": 1412.83,
    "Bank": 1010.55,
    "Deck Value": 33441.07,
    "Card Count": 15395,
    "Deck Capacity": 15666,
    "Rare": 1542,
    "Common": 6373,
    "Uncommon": 4158,
    "Epic": 1216,
    "Ultra-Rare": 1966,
    "Legendary": 140,
    "S1": 4058,
    "S2": 3608,
    "S3": 7729,
    "S1 Rare": 331,
    "S1 Common": 1455,
    "S1 Uncommon": 1204,
    "S1 Epic": 438,
    "S1 Ultra-Rare": 539,
    "S2 Common": 1532,
    "S1 Legendary": 91,
    "S2 Uncommon": 900,
    "S2 Epic": 294,
    "S2 Ultra-Rare": 547,
    "S2 Rare": 309,
    "S2 Legendary": 26,
    "S3 Common": 3386,
    "S3 Uncommon": 2054,
    "S3 Epic": 484,
    "S3 Rare": 902,
    "S3 Ultra-Rare": 880,
    "S3 Legendary": 23
  },
  {
    "Nation": "Slaggstone Bruntt",
    "Junk Value": 1158.7,
    "Bank": 182.47,
    "Deck Value": 33389.9,
    "Card Count": 11990,
    "Deck Capacity": 12500,
    "Ultra-Rare": 1170,
    "Common": 4275,
    "Rare": 1673,
    "Epic": 515,
    "Uncommon": 3929,
    "Legendary": 428,
    "S1": 325,
    "S2": 534,
    "S3": 11131,
    "S1 Ultra-Rare": 54,
    "S1 Common": 51,
    "S1 Rare": 55,
    "S1 Epic": 38,
    "S1 Uncommon": 115,
    "S1 Legendary": 12,
    "S2 Common": 96,
    "S2 Ultra-Rare": 87,
    "S2 Epic": 50,
    "S2 Uncommon": 174,
    "S2 Rare": 86,
    "S2 Legendary": 41,
    "S3 Uncommon": 3640,
    "S3 Common": 4128,
    "S3 Ultra-Rare": 1029,
    "S3 Rare": 1532,
    "S3 Epic": 427,
    "S3 Legendary": 375
  },
  {
    "Nation": "The United Peoples Of Centrism",
    "Junk Value": 294.44,
    "Bank": 2359.56,
    "Deck Value": 33226.07,
    "Card Count": 3426,
    "Deck Capacity": 6833,
    "Uncommon": 1282,
    "Common": 1384,
    "Rare": 219,
    "Ultra-Rare": 190,
    "Epic": 345,
    "Legendary": 6,
    "S1": 390,
    "S2": 1662,
    "S3": 1374,
    "S1 Uncommon": 147,
    "S1 Common": 129,
    "S1 Rare": 40,
    "S2 Rare": 119,
    "S1 Ultra-Rare": 49,
    "S2 Ultra-Rare": 78,
    "S1 Epic": 24,
    "S2 Common": 542,
    "S2 Uncommon": 887,
    "S2 Epic": 34,
    "S2 Legendary": 2,
    "S1 Legendary": 1,
    "S3 Common": 713,
    "S3 Epic": 287,
    "S3 Rare": 60,
    "S3 Uncommon": 248,
    "S3 Ultra-Rare": 63,
    "S3 Legendary": 3
  },
  {
    "Nation": "Independent Federation Of Croatia",
    "Junk Value": 688.03,
    "Bank": 82.45,
    "Deck Value": 32820.18,
    "Card Count": 2673,
    "Deck Capacity": 4931,
    "Common": 1098,
    "Legendary": 298,
    "Epic": 700,
    "Ultra-Rare": 43,
    "Uncommon": 409,
    "Rare": 125,
    "S1": 648,
    "S2": 358,
    "S3": 1667,
    "S1 Common": 133,
    "S1 Legendary": 235,
    "S2 Legendary": 44,
    "S1 Epic": 147,
    "S1 Ultra-Rare": 30,
    "S1 Uncommon": 81,
    "S1 Rare": 22,
    "S2 Epic": 224,
    "S2 Ultra-Rare": 8,
    "S2 Common": 19,
    "S2 Rare": 14,
    "S2 Uncommon": 49,
    "S3 Common": 946,
    "S3 Epic": 329,
    "S3 Rare": 89,
    "S3 Ultra-Rare": 5,
    "S3 Uncommon": 279,
    "S3 Legendary": 19
  },
  {
    "Nation": "Xoriet",
    "Junk Value": 406.66,
    "Bank": 13506.2,
    "Deck Value": 32726.75,
    "Card Count": 1649,
    "Deck Capacity": 5864,
    "Ultra-Rare": 345,
    "Legendary": 202,
    "Uncommon": 354,
    "Common": 346,
    "Rare": 173,
    "Epic": 229,
    "S1": 1028,
    "S2": 434,
    "S3": 187,
    "S1 Ultra-Rare": 217,
    "S1 Legendary": 77,
    "S1 Uncommon": 245,
    "S1 Common": 197,
    "S1 Rare": 129,
    "S2 Epic": 51,
    "S1 Epic": 163,
    "S2 Common": 107,
    "S2 Ultra-Rare": 87,
    "S2 Uncommon": 85,
    "S2 Rare": 23,
    "S2 Legendary": 81,
    "S3 Rare": 21,
    "S3 Ultra-Rare": 41,
    "S3 Legendary": 44,
    "S3 Uncommon": 24,
    "S3 Epic": 15,
    "S3 Common": 42
  },
  {
    "Nation": "Grea Kriopia",
    "Junk Value": 369.59,
    "Bank": 268.95,
    "Deck Value": 32495.26,
    "Card Count": 950,
    "Deck Capacity": 2779,
    "Legendary": 305,
    "Ultra-Rare": 71,
    "Common": 379,
    "Rare": 37,
    "Epic": 86,
    "Uncommon": 72,
    "S1": 70,
    "S2": 822,
    "S3": 58,
    "S1 Legendary": 39,
    "S1 Ultra-Rare": 6,
    "S2 Common": 363,
    "S1 Rare": 2,
    "S1 Epic": 16,
    "S2 Ultra-Rare": 54,
    "S2 Epic": 60,
    "S1 Uncommon": 4,
    "S2 Legendary": 252,
    "S1 Common": 3,
    "S2 Uncommon": 62,
    "S2 Rare": 31,
    "S3 Legendary": 14,
    "S3 Ultra-Rare": 11,
    "S3 Rare": 4,
    "S3 Common": 13,
    "S3 Uncommon": 6,
    "S3 Epic": 10
  },
  {
    "Nation": "Von Zeischter",
    "Junk Value": 543.52,
    "Bank": 805.41,
    "Deck Value": 32387.76,
    "Card Count": 3480,
    "Deck Capacity": 4392,
    "Common": 1777,
    "Uncommon": 789,
    "Epic": 233,
    "Legendary": 337,
    "Ultra-Rare": 164,
    "Rare": 180,
    "S1": 66,
    "S2": 328,
    "S3": 3086,
    "S1 Common": 24,
    "S1 Uncommon": 18,
    "S1 Epic": 5,
    "S1 Legendary": 5,
    "S1 Ultra-Rare": 3,
    "S1 Rare": 11,
    "S2 Common": 150,
    "S2 Epic": 3,
    "S2 Uncommon": 137,
    "S2 Legendary": 7,
    "S2 Rare": 14,
    "S2 Ultra-Rare": 17,
    "S3 Uncommon": 634,
    "S3 Legendary": 325,
    "S3 Common": 1603,
    "S3 Epic": 225,
    "S3 Rare": 155,
    "S3 Ultra-Rare": 144
  },
  {
    "Nation": "Refiria",
    "Junk Value": 329.16,
    "Bank": 308.54,
    "Deck Value": 32055.82,
    "Card Count": 1363,
    "Deck Capacity": 2005,
    "Legendary": 269,
    "Common": 531,
    "Uncommon": 427,
    "Epic": 55,
    "Ultra-Rare": 30,
    "Rare": 51,
    "S2": 395,
    "S1": 71,
    "S3": 897,
    "S2 Legendary": 123,
    "S2 Common": 185,
    "S1 Uncommon": 11,
    "S1 Legendary": 21,
    "S1 Epic": 9,
    "S1 Ultra-Rare": 2,
    "S1 Common": 20,
    "S2 Uncommon": 52,
    "S2 Ultra-Rare": 11,
    "S2 Epic": 13,
    "S2 Rare": 11,
    "S1 Rare": 8,
    "S3 Uncommon": 364,
    "S3 Common": 326,
    "S3 Legendary": 125,
    "S3 Rare": 32,
    "S3 Epic": 33,
    "S3 Ultra-Rare": 17
  },
  {
    "Nation": "Nationstates Nation State",
    "Junk Value": 503.28,
    "Bank": 529.87,
    "Deck Value": 31994.05,
    "Card Count": 3179,
    "Deck Capacity": 3250,
    "Common": 2553,
    "Uncommon": 15,
    "Legendary": 435,
    "Epic": 64,
    "Rare": 62,
    "Ultra-Rare": 50,
    "S2": 52,
    "S3": 3126,
    "S1": 1,
    "S2 Common": 51,
    "S2 Uncommon": 1,
    "S3 Common": 2502,
    "S3 Legendary": 435,
    "S3 Epic": 64,
    "S3 Rare": 62,
    "S3 Ultra-Rare": 50,
    "S1 Uncommon": 1,
    "S3 Uncommon": 13
  },
  {
    "Nation": "Sea Dolphin Lovers",
    "Junk Value": 802.09,
    "Bank": 104.93,
    "Deck Value": 31588.08,
    "Card Count": 2237,
    "Deck Capacity": 3606,
    "Legendary": 341,
    "Common": 434,
    "Uncommon": 323,
    "Ultra-Rare": 203,
    "Epic": 800,
    "Rare": 136,
    "S1": 612,
    "S2": 662,
    "S3": 963,
    "S1 Legendary": 95,
    "S1 Common": 181,
    "S1 Uncommon": 84,
    "S1 Ultra-Rare": 83,
    "S1 Epic": 112,
    "S2 Legendary": 191,
    "S1 Rare": 57,
    "S2 Epic": 150,
    "S2 Ultra-Rare": 57,
    "S2 Common": 118,
    "S2 Uncommon": 122,
    "S2 Rare": 24,
    "S3 Uncommon": 117,
    "S3 Ultra-Rare": 63,
    "S3 Legendary": 55,
    "S3 Epic": 538,
    "S3 Common": 135,
    "S3 Rare": 55
  },
  {
    "Nation": "Volikara",
    "Junk Value": 313.24,
    "Bank": 935.69,
    "Deck Value": 31558.39,
    "Card Count": 1489,
    "Deck Capacity": 1750,
    "Common": 764,
    "Ultra-Rare": 83,
    "Uncommon": 220,
    "Epic": 60,
    "Rare": 114,
    "Legendary": 248,
    "S1": 104,
    "S2": 133,
    "S3": 1252,
    "S1 Common": 51,
    "S1 Ultra-Rare": 4,
    "S1 Uncommon": 28,
    "S1 Epic": 2,
    "S2 Uncommon": 37,
    "S2 Epic": 3,
    "S2 Rare": 11,
    "S2 Common": 67,
    "S2 Legendary": 4,
    "S2 Ultra-Rare": 11,
    "S3 Rare": 89,
    "S3 Common": 646,
    "S3 Ultra-Rare": 68,
    "S3 Legendary": 239,
    "S3 Uncommon": 155,
    "S3 Epic": 55,
    "S1 Rare": 14,
    "S1 Legendary": 5
  },
  {
    "Nation": "Xink Cards",
    "Junk Value": 545.0,
    "Bank": 924.09,
    "Deck Value": 30967.18,
    "Card Count": 545,
    "Deck Capacity": 750,
    "Legendary": 545,
    "S1": 18,
    "S2": 17,
    "S3": 510,
    "S1 Legendary": 18,
    "S2 Legendary": 17,
    "S3 Legendary": 510
  },
  {
    "Nation": "Alistia",
    "Junk Value": 491.19,
    "Bank": 45.67,
    "Deck Value": 30479.99,
    "Card Count": 3483,
    "Deck Capacity": 4010,
    "Common": 1544,
    "Ultra-Rare": 277,
    "Legendary": 304,
    "Uncommon": 887,
    "Epic": 144,
    "Rare": 327,
    "S1": 428,
    "S2": 477,
    "S3": 2578,
    "S1 Common": 201,
    "S1 Ultra-Rare": 29,
    "S1 Legendary": 91,
    "S1 Uncommon": 76,
    "S1 Epic": 16,
    "S2 Legendary": 180,
    "S1 Rare": 15,
    "S2 Epic": 16,
    "S2 Uncommon": 185,
    "S2 Rare": 17,
    "S2 Common": 53,
    "S2 Ultra-Rare": 26,
    "S3 Ultra-Rare": 222,
    "S3 Common": 1290,
    "S3 Rare": 295,
    "S3 Uncommon": 626,
    "S3 Epic": 112,
    "S3 Legendary": 33
  },
  {
    "Nation": "Radicalania",
    "Junk Value": 1805.71,
    "Bank": 223.05,
    "Deck Value": 29999.29,
    "Card Count": 8230,
    "Deck Capacity": 8574,
    "Common": 521,
    "Uncommon": 426,
    "Epic": 46,
    "Ultra-Rare": 6801,
    "Rare": 40,
    "Legendary": 396,
    "S2": 1192,
    "S1": 14,
    "S3": 7024,
    "S2 Common": 517,
    "S2 Uncommon": 408,
    "S2 Epic": 28,
    "S1 Uncommon": 13,
    "S2 Ultra-Rare": 40,
    "S2 Rare": 29,
    "S2 Legendary": 170,
    "S3 Ultra-Rare": 6761,
    "S3 Legendary": 226,
    "S3 Epic": 17,
    "S3 Rare": 11,
    "S3 Uncommon": 5,
    "S3 Common": 4,
    "S1 Epic": 1
  }
]