[
  {
    "Nation": "Mikeswill",
    "Junk Value": 22519.98,
    "Bank": 89510.97,
    "Deck Value": 3963996.71,
    "Card Count": 85522,
    "Deck Capacity": 85668,
    "Legendary Value Raw": 1182770.11,
    "Legendary Value": 29.84,
    "Ultra-Rare": 10116,
    "Rare": 7050,
    "Common": 14988,
    "Uncommon": 33558,
    "Legendary": 17528,
    "Epic": 2282,
    "S1": 6856,
    "S2": 49379,
    "S3": 27505,
    "S4": 1782,
    "S1 Ultra-Rare": 124,
    "S1 Rare": 122,
    "S2 Common": 9178,
    "S1 Common": 1927,
    "S1 Uncommon": 3045,
    "S1 Legendary": 1489,
    "S2 Uncommon": 29410,
    "S2 Rare": 3639,
    "S1 Epic": 149,
    "S2 Ultra-Rare": 545,
    "S2 Legendary": 5973,
    "S2 Epic": 634,
    "S3 Epic": 1376,
    "S3 Rare": 3188,
    "S3 Ultra-Rare": 9149,
    "S3 Legendary": 8942,
    "S3 Common": 3791,
    "S3 Uncommon": 1059,
    "S4 Rare": 101,
    "S4 Ultra-Rare": 298,
    "S4 Legendary": 1124,
    "S4 Epic": 123,
    "S4 Common": 92,
    "S4 Uncommon": 44
  },
  {
    "Nation": "Giovanniland",
    "Junk Value": 2295.69,
    "Bank": 36743.38,
    "Deck Value": 2764388.1,
    "Card Count": 88181,
    "Deck Capacity": 88336,
    "Legendary Value Raw": 41587.27,
    "Legendary Value": 1.5,
    "Uncommon": 11755,
    "Rare": 2807,
    "Common": 70734,
    "Ultra-Rare": 1898,
    "Legendary": 255,
    "Epic": 732,
    "S1": 2079,
    "S2": 16336,
    "S3": 62209,
    "S4": 7557,
    "S1 Uncommon": 665,
    "S1 Rare": 235,
    "S1 Common": 899,
    "S2 Common": 11784,
    "S2 Uncommon": 2963,
    "S2 Ultra-Rare": 785,
    "S1 Legendary": 6,
    "S1 Ultra-Rare": 189,
    "S1 Epic": 85,
    "S2 Rare": 414,
    "S2 Epic": 387,
    "S2 Legendary": 3,
    "S3 Uncommon": 6639,
    "S3 Common": 52957,
    "S3 Epic": 129,
    "S3 Rare": 1673,
    "S3 Ultra-Rare": 595,
    "S3 Legendary": 216,
    "S4 Common": 5094,
    "S4 Uncommon": 1488,
    "S4 Rare": 485,
    "S4 Ultra-Rare": 329,
    "S4 Epic": 131,
    "S4 Legendary": 30
  },
  {
    "Nation": "Koem Kab",
    "Junk Value": 31387.42,
    "Bank": 44020.42,
    "Deck Value": 2569023.65,
    "Card Count": 55728,
    "Deck Capacity": 56336,
    "Legendary Value Raw": 1924648.34,
    "Legendary Value": 74.92,
    "Ultra-Rare": 4128,
    "Common": 9982,
    "Uncommon": 7010,
    "Epic": 4201,
    "Legendary": 28011,
    "Rare": 2396,
    "S1": 10211,
    "S2": 18850,
    "S3": 25907,
    "S4": 760,
    "S1 Ultra-Rare": 476,
    "S1 Common": 2297,
    "S1 Uncommon": 1407,
    "S1 Epic": 839,
    "S2 Common": 4329,
    "S1 Legendary": 4688,
    "S1 Rare": 504,
    "S2 Ultra-Rare": 344,
    "S2 Uncommon": 4591,
    "S2 Legendary": 8678,
    "S2 Rare": 369,
    "S2 Epic": 539,
    "S3 Legendary": 14127,
    "S3 Rare": 1497,
    "S3 Common": 3304,
    "S3 Epic": 2745,
    "S3 Ultra-Rare": 3250,
    "S3 Uncommon": 984,
    "S4 Legendary": 518,
    "S4 Epic": 78,
    "S4 Uncommon": 28,
    "S4 Ultra-Rare": 58,
    "S4 Common": 52,
    "S4 Rare": 26
  },
  {
    "Nation": "Second Best Card Collector",
    "Junk Value": 1416.04,
    "Bank": 8867.34,
    "Deck Value": 2151075.88,
    "Card Count": 19088,
    "Deck Capacity": 21362,
    "Legendary Value Raw": 15284.04,
    "Legendary Value": 0.71,
    "Uncommon": 2649,
    "Rare": 2392,
    "Common": 10959,
    "Legendary": 157,
    "Epic": 1436,
    "Ultra-Rare": 1495,
    "S2": 1653,
    "S1": 238,
    "S3": 15738,
    "S4": 1459,
    "S2 Uncommon": 255,
    "S2 Rare": 583,
    "S2 Common": 738,
    "S1 Common": 49,
    "S1 Uncommon": 69,
    "S2 Legendary": 60,
    "S2 Epic": 14,
    "S1 Epic": 19,
    "S3 Common": 9642,
    "S3 Uncommon": 1467,
    "S3 Ultra-Rare": 1479,
    "S3 Legendary": 10,
    "S3 Rare": 1751,
    "S3 Epic": 1389,
    "S1 Ultra-Rare": 13,
    "S1 Rare": 4,
    "S1 Legendary": 84,
    "S2 Ultra-Rare": 3,
    "S4 Uncommon": 858,
    "S4 Common": 530,
    "S4 Rare": 54,
    "S4 Epic": 14,
    "S4 Legendary": 3
  },
  {
    "Nation": "Varanius",
    "Junk Value": 6448.23,
    "Bank": 2634.43,
    "Deck Value": 926360.92,
    "Card Count": 30181,
    "Deck Capacity": 30712,
    "Legendary Value Raw": 328628.46,
    "Legendary Value": 35.48,
    "Common": 12908,
    "Uncommon": 5317,
    "Ultra-Rare": 4134,
    "Rare": 1896,
    "Legendary": 4527,
    "Epic": 1399,
    "S1": 193,
    "S2": 1138,
    "S3": 23780,
    "S4": 5070,
    "S1 Common": 81,
    "S2 Common": 334,
    "S1 Uncommon": 70,
    "S2 Ultra-Rare": 22,
    "S2 Uncommon": 531,
    "S2 Rare": 34,
    "S2 Legendary": 211,
    "S2 Epic": 6,
    "S3 Rare": 1809,
    "S3 Common": 9726,
    "S3 Uncommon": 2702,
    "S3 Ultra-Rare": 4092,
    "S3 Legendary": 4091,
    "S3 Epic": 1360,
    "S1 Rare": 8,
    "S1 Ultra-Rare": 9,
    "S1 Epic": 25,
    "S4 Common": 2767,
    "S4 Uncommon": 2014,
    "S4 Legendary": 225,
    "S4 Rare": 45,
    "S4 Ultra-Rare": 11,
    "S4 Epic": 8
  },
  {
    "Nation": "Noahs Second Country",
    "Junk Value": 13265.49,
    "Bank": 48447.45,
    "Deck Value": 861339.01,
    "Card Count": 13413,
    "Deck Capacity": 16074,
    "Legendary Value Raw": 859500.88,
    "Legendary Value": 99.79,
    "Legendary": 13264,
    "Common": 149,
    "S2": 163,
    "S3": 12601,
    "S4": 649,
    "S2 Legendary": 16,
    "S2 Common": 147,
    "S3 Legendary": 12600,
    "S3 Common": 1,
    "S4 Legendary": 648,
    "S4 Common": 1
  },
  {
    "Nation": "Communist-Denmark",
    "Junk Value": 4432.47,
    "Bank": 4361.93,
    "Deck Value": 724263.67,
    "Card Count": 32068,
    "Deck Capacity": 34000,
    "Legendary Value Raw": 192880.98,
    "Legendary Value": 26.63,
    "Legendary": 3037,
    "Common": 21372,
    "Uncommon": 2931,
    "Rare": 1403,
    "Epic": 1234,
    "Ultra-Rare": 2091,
    "S1": 163,
    "S2": 367,
    "S3": 26692,
    "S4": 4846,
    "S1 Legendary": 24,
    "S2 Common": 111,
    "S2 Uncommon": 68,
    "S2 Rare": 17,
    "S2 Epic": 52,
    "S2 Legendary": 87,
    "S2 Ultra-Rare": 32,
    "S1 Uncommon": 40,
    "S1 Ultra-Rare": 8,
    "S1 Epic": 13,
    "S3 Common": 19115,
    "S3 Uncommon": 2136,
    "S3 Ultra-Rare": 1652,
    "S3 Rare": 1098,
    "S3 Epic": 896,
    "S3 Legendary": 1795,
    "S1 Common": 73,
    "S1 Rare": 5,
    "S4 Legendary": 1131,
    "S4 Common": 2073,
    "S4 Uncommon": 687,
    "S4 Epic": 273,
    "S4 Ultra-Rare": 399,
    "S4 Rare": 283
  },
  {
    "Nation": "Kractero",
    "Junk Value": 7842.08,
    "Bank": 18987.39,
    "Deck Value": 590566.15,
    "Card Count": 16954,
    "Deck Capacity": 17010,
    "Legendary Value Raw": 508446.67,
    "Legendary Value": 86.09,
    "Legendary": 7624,
    "Common": 8108,
    "Epic": 185,
    "Uncommon": 646,
    "Rare": 330,
    "Ultra-Rare": 61,
    "S1": 2201,
    "S2": 194,
    "S3": 8281,
    "S4": 6278,
    "S1 Legendary": 238,
    "S1 Common": 1611,
    "S1 Epic": 39,
    "S1 Uncommon": 290,
    "S1 Rare": 23,
    "S2 Legendary": 194,
    "S3 Legendary": 5781,
    "S3 Common": 2044,
    "S3 Epic": 146,
    "S3 Uncommon": 154,
    "S3 Rare": 156,
    "S4 Common": 4453,
    "S4 Uncommon": 202,
    "S4 Legendary": 1411,
    "S4 Rare": 151,
    "S4 Ultra-Rare": 61
  },
  {
    "Nation": "New Makasta",
    "Junk Value": 10342.79,
    "Bank": 3628.73,
    "Deck Value": 534826.39,
    "Card Count": 71195,
    "Deck Capacity": 71188,
    "Legendary Value Raw": 325048.06,
    "Legendary Value": 60.78,
    "Legendary": 5543,
    "Common": 33449,
    "Rare": 6527,
    "Ultra-Rare": 3957,
    "Uncommon": 15968,
    "Epic": 5751,
    "S1": 2551,
    "S2": 33359,
    "S3": 29525,
    "S4": 5760,
    "S1 Legendary": 89,
    "S1 Common": 801,
    "S1 Rare": 541,
    "S1 Ultra-Rare": 225,
    "S1 Uncommon": 749,
    "S1 Epic": 146,
    "S2 Uncommon": 9962,
    "S2 Rare": 3622,
    "S2 Epic": 1461,
    "S2 Common": 14477,
    "S2 Ultra-Rare": 2196,
    "S2 Legendary": 1641,
    "S3 Epic": 3960,
    "S3 Common": 14216,
    "S3 Ultra-Rare": 1328,
    "S3 Legendary": 3477,
    "S3 Uncommon": 4668,
    "S3 Rare": 1876,
    "S4 Common": 3955,
    "S4 Epic": 184,
    "S4 Rare": 488,
    "S4 Ultra-Rare": 208,
    "S4 Legendary": 336,
    "S4 Uncommon": 589
  },
  {
    "Nation": "Vulxo",
    "Junk Value": 4324.29,
    "Bank": 272.37,
    "Deck Value": 532480.04,
    "Card Count": 11289,
    "Deck Capacity": 11336,
    "Legendary Value Raw": 257637.39,
    "Legendary Value": 48.38,
    "Common": 5379,
    "Epic": 711,
    "Uncommon": 536,
    "Legendary": 3827,
    "Ultra-Rare": 306,
    "Rare": 530,
    "S1": 156,
    "S2": 203,
    "S3": 7934,
    "S4": 2996,
    "S1 Common": 77,
    "S1 Epic": 29,
    "S1 Uncommon": 21,
    "S1 Legendary": 26,
    "S2 Legendary": 91,
    "S2 Uncommon": 27,
    "S2 Common": 77,
    "S2 Ultra-Rare": 1,
    "S3 Legendary": 3082,
    "S3 Common": 3206,
    "S3 Rare": 449,
    "S3 Uncommon": 426,
    "S3 Epic": 574,
    "S2 Epic": 6,
    "S3 Ultra-Rare": 197,
    "S2 Rare": 1,
    "S1 Ultra-Rare": 2,
    "S4 Common": 2019,
    "S4 Legendary": 628,
    "S4 Ultra-Rare": 106,
    "S4 Rare": 79,
    "S4 Uncommon": 62,
    "S4 Epic": 102,
    "S1 Rare": 1
  },
  {
    "Nation": "Thelandoffunfunfun",
    "Junk Value": 1847.44,
    "Bank": 2350.59,
    "Deck Value": 526427.64,
    "Card Count": 8688,
    "Deck Capacity": 8885,
    "Legendary Value Raw": 79941.03,
    "Legendary Value": 15.19,
    "Common": 3249,
    "Legendary": 1293,
    "Epic": 328,
    "Ultra-Rare": 1498,
    "Uncommon": 1167,
    "Rare": 1153,
    "S1": 70,
    "S2": 650,
    "S3": 7697,
    "S4": 271,
    "S1 Common": 15,
    "S1 Legendary": 16,
    "S2 Common": 316,
    "S2 Epic": 11,
    "S2 Ultra-Rare": 33,
    "S2 Uncommon": 155,
    "S2 Legendary": 127,
    "S2 Rare": 8,
    "S1 Epic": 12,
    "S1 Uncommon": 19,
    "S3 Rare": 1126,
    "S3 Common": 2900,
    "S3 Uncommon": 984,
    "S3 Legendary": 1021,
    "S3 Ultra-Rare": 1389,
    "S3 Epic": 277,
    "S1 Rare": 2,
    "S1 Ultra-Rare": 6,
    "S4 Ultra-Rare": 70,
    "S4 Common": 18,
    "S4 Legendary": 129,
    "S4 Epic": 28,
    "S4 Rare": 17,
    "S4 Uncommon": 9
  },
  {
    "Nation": "Seanat",
    "Junk Value": 12461.32,
    "Bank": 15816.94,
    "Deck Value": 497222.73,
    "Card Count": 29693,
    "Deck Capacity": 29770,
    "Legendary Value Raw": 410887.66,
    "Legendary Value": 82.64,
    "Epic": 11247,
    "Common": 6737,
    "Uncommon": 2985,
    "Rare": 1678,
    "Legendary": 6515,
    "Ultra-Rare": 531,
    "S1": 3251,
    "S2": 6791,
    "S3": 12674,
    "S4": 6977,
    "S1 Epic": 862,
    "S1 Common": 658,
    "S1 Uncommon": 1207,
    "S1 Rare": 127,
    "S2 Legendary": 4495,
    "S1 Legendary": 280,
    "S1 Ultra-Rare": 117,
    "S2 Ultra-Rare": 15,
    "S2 Epic": 2035,
    "S2 Uncommon": 21,
    "S2 Common": 144,
    "S2 Rare": 81,
    "S3 Common": 3419,
    "S3 Uncommon": 918,
    "S3 Ultra-Rare": 252,
    "S3 Legendary": 1020,
    "S3 Epic": 6268,
    "S3 Rare": 797,
    "S4 Rare": 673,
    "S4 Common": 2516,
    "S4 Epic": 2082,
    "S4 Uncommon": 839,
    "S4 Ultra-Rare": 147,
    "S4 Legendary": 720
  },
  {
    "Nation": "Laudesia",
    "Junk Value": 2423.1,
    "Bank": 15022.25,
    "Deck Value": 421897.7,
    "Card Count": 10460,
    "Deck Capacity": 10862,
    "Legendary Value Raw": 151891.77,
    "Legendary Value": 36.0,
    "Common": 5530,
    "Legendary": 2009,
    "Rare": 491,
    "Uncommon": 1712,
    "Epic": 432,
    "Ultra-Rare": 286,
    "S1": 829,
    "S2": 1230,
    "S3": 6251,
    "S4": 2150,
    "S1 Common": 481,
    "S1 Legendary": 110,
    "S1 Rare": 28,
    "S1 Uncommon": 146,
    "S1 Epic": 25,
    "S1 Ultra-Rare": 39,
    "S2 Common": 281,
    "S2 Legendary": 512,
    "S2 Uncommon": 368,
    "S2 Ultra-Rare": 33,
    "S2 Rare": 10,
    "S2 Epic": 26,
    "S3 Common": 3347,
    "S3 Rare": 352,
    "S3 Uncommon": 1022,
    "S3 Legendary": 1050,
    "S3 Epic": 315,
    "S3 Ultra-Rare": 165,
    "S4 Common": 1421,
    "S4 Ultra-Rare": 49,
    "S4 Uncommon": 176,
    "S4 Legendary": 337,
    "S4 Epic": 66,
    "S4 Rare": 101
  },
  {
    "Nation": "Panagouge",
    "Junk Value": 527.67,
    "Bank": 1605.82,
    "Deck Value": 393126.04,
    "Card Count": 3688,
    "Deck Capacity": 5010,
    "Legendary Value Raw": 18773.42,
    "Legendary Value": 4.78,
    "Common": 1707,
    "Epic": 311,
    "Legendary": 272,
    "Rare": 165,
    "Ultra-Rare": 143,
    "Uncommon": 1090,
    "S1": 192,
    "S2": 1501,
    "S3": 1954,
    "S4": 41,
    "S1 Common": 69,
    "S1 Epic": 13,
    "S1 Legendary": 15,
    "S1 Rare": 21,
    "S1 Ultra-Rare": 29,
    "S2 Common": 732,
    "S1 Uncommon": 45,
    "S2 Legendary": 189,
    "S2 Uncommon": 470,
    "S2 Epic": 25,
    "S2 Ultra-Rare": 43,
    "S2 Rare": 42,
    "S3 Uncommon": 572,
    "S3 Common": 884,
    "S3 Rare": 102,
    "S3 Legendary": 68,
    "S3 Epic": 257,
    "S3 Ultra-Rare": 71,
    "S4 Epic": 16,
    "S4 Common": 22,
    "S4 Uncommon": 3
  },
  {
    "Nation": "Kwaj",
    "Junk Value": 2347.12,
    "Bank": 2098.97,
    "Deck Value": 341707.51,
    "Card Count": 6116,
    "Deck Capacity": 10786,
    "Legendary Value Raw": 145484.35,
    "Legendary Value": 42.58,
    "Epic": 862,
    "Legendary": 1826,
    "Common": 2607,
    "Ultra-Rare": 230,
    "Uncommon": 361,
    "Rare": 230,
    "S1": 1309,
    "S2": 866,
    "S3": 3674,
    "S4": 267,
    "S1 Epic": 176,
    "S1 Legendary": 484,
    "S1 Common": 527,
    "S1 Ultra-Rare": 17,
    "S1 Uncommon": 92,
    "S1 Rare": 13,
    "S2 Legendary": 242,
    "S2 Epic": 300,
    "S2 Common": 284,
    "S2 Uncommon": 28,
    "S2 Ultra-Rare": 8,
    "S2 Rare": 4,
    "S3 Legendary": 1021,
    "S3 Common": 1691,
    "S3 Epic": 367,
    "S3 Rare": 191,
    "S3 Ultra-Rare": 191,
    "S3 Uncommon": 213,
    "S4 Epic": 19,
    "S4 Legendary": 79,
    "S4 Common": 105,
    "S4 Uncommon": 28,
    "S4 Rare": 22,
    "S4 Ultra-Rare": 14
  },
  {
    "Nation": "Fhaengshia",
    "Junk Value": 4520.55,
    "Bank": 2814.17,
    "Deck Value": 324101.41,
    "Card Count": 9324,
    "Deck Capacity": 13666,
    "Legendary Value Raw": 197069.76,
    "Legendary Value": 60.8,
    "Rare": 957,
    "Epic": 2890,
    "Legendary": 2746,
    "Uncommon": 811,
    "Ultra-Rare": 1420,
    "Common": 500,
    "S1": 675,
    "S2": 5500,
    "S3": 2459,
    "S4": 690,
    "S1 Rare": 64,
    "S1 Epic": 157,
    "S1 Legendary": 203,
    "S2 Uncommon": 410,
    "S1 Ultra-Rare": 127,
    "S1 Common": 55,
    "S2 Ultra-Rare": 680,
    "S2 Legendary": 1838,
    "S2 Rare": 379,
    "S1 Uncommon": 69,
    "S2 Epic": 1882,
    "S2 Common": 311,
    "S3 Uncommon": 294,
    "S3 Rare": 479,
    "S3 Ultra-Rare": 476,
    "S3 Epic": 611,
    "S3 Legendary": 491,
    "S3 Common": 108,
    "S4 Uncommon": 38,
    "S4 Epic": 240,
    "S4 Ultra-Rare": 137,
    "S4 Legendary": 214,
    "S4 Rare": 35,
    "S4 Common": 26
  },
  {
    "Nation": "Aerilia",
    "Junk Value": 3792.82,
    "Bank": 23138.88,
    "Deck Value": 298846.28,
    "Card Count": 6712,
    "Deck Capacity": 9862,
    "Legendary Value Raw": 229339.94,
    "Legendary Value": 76.74,
    "Common": 1077,
    "Legendary": 3354,
    "Uncommon": 747,
    "Rare": 413,
    "Epic": 555,
    "Ultra-Rare": 566,
    "S1": 517,
    "S2": 1302,
    "S3": 3896,
    "S4": 997,
    "S1 Common": 121,
    "S1 Legendary": 260,
    "S1 Uncommon": 73,
    "S1 Rare": 15,
    "S1 Epic": 22,
    "S2 Uncommon": 139,
    "S2 Ultra-Rare": 132,
    "S2 Legendary": 662,
    "S2 Rare": 51,
    "S1 Ultra-Rare": 26,
    "S2 Epic": 89,
    "S2 Common": 229,
    "S3 Uncommon": 350,
    "S3 Rare": 270,
    "S3 Ultra-Rare": 328,
    "S3 Common": 475,
    "S3 Epic": 386,
    "S3 Legendary": 2087,
    "S4 Rare": 77,
    "S4 Ultra-Rare": 80,
    "S4 Legendary": 345,
    "S4 Uncommon": 185,
    "S4 Common": 252,
    "S4 Epic": 58
  },
  {
    "Nation": "Aragesh",
    "Junk Value": 4944.56,
    "Bank": 672.95,
    "Deck Value": 297026.74,
    "Card Count": 8508,
    "Deck Capacity": 8784,
    "Legendary Value Raw": 268466.2,
    "Legendary Value": 90.38,
    "Legendary": 4135,
    "Epic": 1045,
    "Ultra-Rare": 1197,
    "Uncommon": 844,
    "Common": 546,
    "Rare": 741,
    "S1": 1091,
    "S2": 1615,
    "S3": 4484,
    "S4": 1318,
    "S1 Legendary": 176,
    "S2 Legendary": 213,
    "S2 Epic": 257,
    "S1 Ultra-Rare": 292,
    "S1 Epic": 241,
    "S1 Uncommon": 211,
    "S2 Common": 338,
    "S1 Rare": 163,
    "S2 Ultra-Rare": 322,
    "S2 Rare": 201,
    "S1 Common": 8,
    "S2 Uncommon": 284,
    "S3 Ultra-Rare": 338,
    "S3 Legendary": 3326,
    "S3 Common": 60,
    "S3 Uncommon": 197,
    "S3 Epic": 328,
    "S3 Rare": 235,
    "S4 Uncommon": 152,
    "S4 Common": 140,
    "S4 Rare": 142,
    "S4 Legendary": 420,
    "S4 Ultra-Rare": 245,
    "S4 Epic": 219
  },
  {
    "Nation": "New Kowloon Bay",
    "Junk Value": 3501.12,
    "Bank": 690.99,
    "Deck Value": 278315.55,
    "Card Count": 6674,
    "Deck Capacity": 6779,
    "Legendary Value Raw": 178711.32,
    "Legendary Value": 64.21,
    "Legendary": 2958,
    "Common": 1137,
    "Epic": 538,
    "Ultra-Rare": 1225,
    "Uncommon": 355,
    "Rare": 461,
    "S1": 543,
    "S2": 800,
    "S3": 3883,
    "S4": 1448,
    "S1 Legendary": 162,
    "S2 Common": 65,
    "S1 Epic": 100,
    "S2 Legendary": 274,
    "S2 Epic": 89,
    "S1 Ultra-Rare": 176,
    "S1 Common": 57,
    "S1 Uncommon": 45,
    "S2 Ultra-Rare": 321,
    "S2 Uncommon": 47,
    "S2 Rare": 4,
    "S3 Legendary": 1794,
    "S3 Common": 716,
    "S3 Epic": 227,
    "S3 Ultra-Rare": 560,
    "S3 Uncommon": 195,
    "S3 Rare": 391,
    "S1 Rare": 3,
    "S4 Legendary": 728,
    "S4 Common": 299,
    "S4 Epic": 122,
    "S4 Ultra-Rare": 168,
    "S4 Uncommon": 68,
    "S4 Rare": 63
  },
  {
    "Nation": "Racoda",
    "Junk Value": 3574.44,
    "Bank": 1005.11,
    "Deck Value": 256062.72,
    "Card Count": 22062,
    "Deck Capacity": 31668,
    "Legendary Value Raw": 232605.65,
    "Legendary Value": 90.84,
    "Common": 824,
    "Legendary": 2589,
    "Epic": 81,
    "Ultra-Rare": 68,
    "Uncommon": 18462,
    "Rare": 38,
    "S1": 559,
    "S2": 3203,
    "S3": 18298,
    "S4": 2,
    "S1 Common": 62,
    "S1 Legendary": 216,
    "S2 Common": 717,
    "S1 Epic": 39,
    "S1 Ultra-Rare": 21,
    "S1 Uncommon": 206,
    "S2 Legendary": 2040,
    "S2 Ultra-Rare": 41,
    "S1 Rare": 15,
    "S2 Rare": 16,
    "S2 Uncommon": 358,
    "S2 Epic": 31,
    "S3 Uncommon": 17898,
    "S3 Legendary": 331,
    "S3 Common": 45,
    "S3 Rare": 7,
    "S3 Epic": 11,
    "S3 Ultra-Rare": 6,
    "S4 Legendary": 2
  },
  {
    "Nation": "The Northern Light",
    "Junk Value": 2928.96,
    "Bank": 421.16,
    "Deck Value": 239891.15,
    "Card Count": 3008,
    "Deck Capacity": 15600,
    "Legendary Value Raw": 239860.02,
    "Legendary Value": 99.99,
    "Legendary": 2911,
    "Uncommon": 6,
    "Epic": 4,
    "Common": 6,
    "Rare": 3,
    "Ultra-Rare": 78,
    "S1": 812,
    "S2": 1422,
    "S3": 697,
    "S4": 77,
    "S1 Legendary": 807,
    "S2 Uncommon": 3,
    "S2 Legendary": 1416,
    "S2 Epic": 1,
    "S1 Uncommon": 2,
    "S1 Common": 3,
    "S2 Common": 2,
    "S3 Legendary": 688,
    "S3 Rare": 3,
    "S3 Epic": 3,
    "S3 Uncommon": 1,
    "S3 Ultra-Rare": 1,
    "S3 Common": 1,
    "S4 Ultra-Rare": 77
  },
  {
    "Nation": "Riemstagrad",
    "Junk Value": 8933.1,
    "Bank": 1576.9,
    "Deck Value": 234889.74,
    "Card Count": 18012,
    "Deck Capacity": 18372,
    "Legendary Value Raw": 130486.39,
    "Legendary Value": 55.55,
    "Epic": 14260,
    "Legendary": 1639,
    "Uncommon": 381,
    "Rare": 204,
    "Common": 845,
    "Ultra-Rare": 683,
    "S1": 4361,
    "S2": 5241,
    "S3": 5576,
    "S4": 2834,
    "S1 Epic": 3902,
    "S1 Legendary": 235,
    "S2 Legendary": 319,
    "S1 Uncommon": 97,
    "S1 Rare": 22,
    "S1 Common": 51,
    "S2 Epic": 4235,
    "S1 Ultra-Rare": 54,
    "S2 Uncommon": 80,
    "S2 Ultra-Rare": 411,
    "S2 Common": 164,
    "S2 Rare": 32,
    "S3 Epic": 3644,
    "S3 Legendary": 969,
    "S3 Common": 519,
    "S3 Rare": 131,
    "S3 Uncommon": 127,
    "S3 Ultra-Rare": 186,
    "S4 Epic": 2479,
    "S4 Ultra-Rare": 32,
    "S4 Legendary": 116,
    "S4 Uncommon": 77,
    "S4 Common": 111,
    "S4 Rare": 19
  },
  {
    "Nation": "National Park Service",
    "Junk Value": 2693.48,
    "Bank": 5178.01,
    "Deck Value": 229043.81,
    "Card Count": 5423,
    "Deck Capacity": 6000,
    "Legendary Value Raw": 156456.38,
    "Legendary Value": 68.31,
    "Epic": 254,
    "Uncommon": 942,
    "Legendary": 2452,
    "Common": 1138,
    "Ultra-Rare": 280,
    "Rare": 357,
    "S1": 54,
    "S2": 99,
    "S3": 4421,
    "S4": 849,
    "S1 Epic": 6,
    "S2 Uncommon": 72,
    "S3 Legendary": 2413,
    "S3 Common": 936,
    "S2 Common": 8,
    "S3 Uncommon": 208,
    "S3 Ultra-Rare": 275,
    "S3 Epic": 247,
    "S3 Rare": 342,
    "S1 Common": 19,
    "S1 Rare": 2,
    "S1 Legendary": 12,
    "S1 Uncommon": 13,
    "S2 Legendary": 10,
    "S2 Epic": 1,
    "S2 Ultra-Rare": 3,
    "S1 Ultra-Rare": 2,
    "S2 Rare": 5,
    "S4 Uncommon": 649,
    "S4 Common": 175,
    "S4 Rare": 8,
    "S4 Legendary": 17
  },
  {
    "Nation": "Upc",
    "Junk Value": 2766.85,
    "Bank": 746.53,
    "Deck Value": 228356.78,
    "Card Count": 3041,
    "Deck Capacity": 3500,
    "Legendary Value Raw": 176330.16,
    "Legendary Value": 77.22,
    "Legendary": 2751,
    "Ultra-Rare": 4,
    "Uncommon": 23,
    "Epic": 23,
    "Common": 240,
    "S1": 296,
    "S2": 1998,
    "S3": 710,
    "S4": 37,
    "S1 Legendary": 292,
    "S2 Legendary": 1969,
    "S1 Ultra-Rare": 3,
    "S2 Uncommon": 21,
    "S1 Epic": 1,
    "S2 Epic": 8,
    "S3 Legendary": 471,
    "S3 Common": 239,
    "S4 Epic": 14,
    "S4 Uncommon": 2,
    "S4 Legendary": 19,
    "S4 Common": 1,
    "S4 Ultra-Rare": 1
  },
  {
    "Nation": "Osheiga",
    "Junk Value": 2985.22,
    "Bank": 2596.6,
    "Deck Value": 216266.39,
    "Card Count": 3847,
    "Deck Capacity": 4092,
    "Legendary Value Raw": 212026.48,
    "Legendary Value": 98.04,
    "Rare": 71,
    "Legendary": 2761,
    "Common": 377,
    "Uncommon": 139,
    "Epic": 379,
    "Ultra-Rare": 120,
    "S1": 224,
    "S2": 479,
    "S3": 3120,
    "S4": 24,
    "S1 Rare": 3,
    "S1 Legendary": 191,
    "S1 Common": 13,
    "S1 Uncommon": 14,
    "S2 Legendary": 190,
    "S2 Epic": 34,
    "S2 Ultra-Rare": 53,
    "S2 Common": 75,
    "S2 Rare": 38,
    "S2 Uncommon": 89,
    "S3 Ultra-Rare": 67,
    "S3 Epic": 342,
    "S3 Rare": 28,
    "S3 Common": 284,
    "S3 Legendary": 2365,
    "S3 Uncommon": 34,
    "S1 Epic": 3,
    "S4 Legendary": 15,
    "S4 Uncommon": 2,
    "S4 Common": 5,
    "S4 Rare": 2
  },
  {
    "Nation": "Eugeniee",
    "Junk Value": 1199.28,
    "Bank": 12011.21,
    "Deck Value": 207601.1,
    "Card Count": 6898,
    "Deck Capacity": 6918,
    "Legendary Value Raw": 38747.84,
    "Legendary Value": 18.66,
    "Common": 2993,
    "Uncommon": 703,
    "Ultra-Rare": 871,
    "Epic": 712,
    "Legendary": 604,
    "Rare": 1015,
    "S1": 44,
    "S2": 228,
    "S3": 5758,
    "S4": 868,
    "S1 Common": 16,
    "S1 Uncommon": 9,
    "S1 Ultra-Rare": 7,
    "S1 Epic": 11,
    "S2 Uncommon": 17,
    "S2 Epic": 32,
    "S2 Common": 83,
    "S2 Ultra-Rare": 17,
    "S2 Legendary": 72,
    "S1 Legendary": 1,
    "S2 Rare": 7,
    "S3 Ultra-Rare": 755,
    "S3 Epic": 627,
    "S3 Common": 2366,
    "S3 Rare": 967,
    "S3 Legendary": 498,
    "S3 Uncommon": 545,
    "S4 Uncommon": 132,
    "S4 Epic": 42,
    "S4 Ultra-Rare": 92,
    "S4 Rare": 41,
    "S4 Legendary": 33,
    "S4 Common": 528
  },
  {
    "Nation": "Portsville",
    "Junk Value": 2606.08,
    "Bank": 6202.95,
    "Deck Value": 207335.26,
    "Card Count": 4452,
    "Deck Capacity": 4779,
    "Legendary Value Raw": 154262.09,
    "Legendary Value": 74.4,
    "Legendary": 2349,
    "Uncommon": 280,
    "Ultra-Rare": 695,
    "Common": 708,
    "Epic": 194,
    "Rare": 226,
    "S1": 262,
    "S2": 944,
    "S3": 2901,
    "S4": 345,
    "S1 Legendary": 106,
    "S1 Uncommon": 66,
    "S2 Legendary": 812,
    "S1 Ultra-Rare": 6,
    "S1 Common": 73,
    "S2 Epic": 23,
    "S2 Uncommon": 25,
    "S1 Epic": 9,
    "S2 Common": 77,
    "S2 Ultra-Rare": 5,
    "S3 Legendary": 1329,
    "S3 Uncommon": 157,
    "S3 Common": 483,
    "S3 Rare": 174,
    "S3 Epic": 143,
    "S3 Ultra-Rare": 615,
    "S2 Rare": 2,
    "S4 Common": 75,
    "S4 Uncommon": 32,
    "S4 Ultra-Rare": 69,
    "S4 Epic": 19,
    "S4 Legendary": 102,
    "S1 Rare": 2,
    "S4 Rare": 48
  },
  {
    "Nation": "Captain Woodhouse",
    "Junk Value": 2699.29,
    "Bank": 4011.41,
    "Deck Value": 203593.26,
    "Card Count": 9217,
    "Deck Capacity": 12688,
    "Legendary Value Raw": 115937.35,
    "Legendary Value": 56.95,
    "Legendary": 1212,
    "Common": 2699,
    "Ultra-Rare": 2593,
    "Rare": 277,
    "Epic": 1822,
    "Uncommon": 614,
    "S1": 1500,
    "S2": 2453,
    "S3": 4918,
    "S4": 346,
    "S1 Legendary": 589,
    "S2 Common": 1280,
    "S1 Ultra-Rare": 79,
    "S1 Common": 545,
    "S1 Rare": 33,
    "S2 Legendary": 359,
    "S1 Epic": 82,
    "S1 Uncommon": 172,
    "S2 Ultra-Rare": 371,
    "S2 Uncommon": 200,
    "S2 Epic": 186,
    "S2 Rare": 57,
    "S3 Epic": 1410,
    "S3 Ultra-Rare": 2089,
    "S3 Uncommon": 221,
    "S3 Common": 807,
    "S3 Legendary": 225,
    "S3 Rare": 166,
    "S4 Epic": 144,
    "S4 Common": 67,
    "S4 Uncommon": 21,
    "S4 Rare": 21,
    "S4 Legendary": 39,
    "S4 Ultra-Rare": 54
  },
  {
    "Nation": "Thorn1000",
    "Junk Value": 2611.63,
    "Bank": 1259.64,
    "Deck Value": 198827.82,
    "Card Count": 4979,
    "Deck Capacity": 5592,
    "Legendary Value Raw": 147610.06,
    "Legendary Value": 74.24,
    "Common": 1288,
    "Epic": 354,
    "Legendary": 2358,
    "Rare": 382,
    "Ultra-Rare": 226,
    "Uncommon": 371,
    "S1": 86,
    "S2": 247,
    "S3": 4495,
    "S4": 151,
    "S1 Common": 35,
    "S1 Epic": 7,
    "S2 Legendary": 172,
    "S2 Common": 43,
    "S1 Legendary": 6,
    "S2 Epic": 5,
    "S2 Rare": 5,
    "S2 Ultra-Rare": 5,
    "S2 Uncommon": 17,
    "S1 Uncommon": 32,
    "S1 Rare": 5,
    "S3 Uncommon": 319,
    "S3 Legendary": 2075,
    "S3 Ultra-Rare": 214,
    "S3 Rare": 371,
    "S3 Common": 1196,
    "S3 Epic": 320,
    "S1 Ultra-Rare": 1,
    "S4 Legendary": 105,
    "S4 Common": 14,
    "S4 Ultra-Rare": 6,
    "S4 Epic": 22,
    "S4 Uncommon": 3,
    "S4 Rare": 1
  },
  {
    "Nation": "East Chimore",
    "Junk Value": 5699.39,
    "Bank": 360.03,
    "Deck Value": 180436.6,
    "Card Count": 15275,
    "Deck Capacity": 15336,
    "Legendary Value Raw": 87861.84,
    "Legendary Value": 48.69,
    "Epic": 8025,
    "Uncommon": 1322,
    "Rare": 870,
    "Legendary": 1507,
    "Ultra-Rare": 412,
    "Common": 3139,
    "S1": 165,
    "S2": 839,
    "S3": 12470,
    "S4": 1801,
    "S1 Epic": 71,
    "S2 Epic": 699,
    "S1 Uncommon": 27,
    "S1 Rare": 12,
    "S2 Legendary": 20,
    "S2 Ultra-Rare": 16,
    "S2 Uncommon": 42,
    "S2 Common": 47,
    "S2 Rare": 15,
    "S3 Common": 2616,
    "S3 Epic": 6225,
    "S3 Rare": 800,
    "S3 Ultra-Rare": 351,
    "S3 Uncommon": 1101,
    "S3 Legendary": 1377,
    "S1 Common": 41,
    "S1 Ultra-Rare": 10,
    "S1 Legendary": 4,
    "S4 Common": 435,
    "S4 Rare": 43,
    "S4 Ultra-Rare": 35,
    "S4 Uncommon": 152,
    "S4 Epic": 1030,
    "S4 Legendary": 106
  },
  {
    "Nation": "Frisbeeteria",
    "Junk Value": 19800.42,
    "Bank": 54434.65,
    "Deck Value": 178598.51,
    "Card Count": 38302,
    "Deck Capacity": 40558,
    "Legendary Value Raw": 156731.25,
    "Legendary Value": 87.76,
    "Epic": 36122,
    "Legendary": 1729,
    "Common": 352,
    "Uncommon": 70,
    "Ultra-Rare": 17,
    "Rare": 12,
    "S1": 7427,
    "S2": 13904,
    "S3": 16970,
    "S4": 1,
    "S1 Epic": 5904,
    "S1 Legendary": 1290,
    "S2 Epic": 13301,
    "S1 Common": 168,
    "S2 Legendary": 386,
    "S1 Uncommon": 55,
    "S1 Ultra-Rare": 9,
    "S1 Rare": 1,
    "S2 Common": 184,
    "S2 Rare": 11,
    "S2 Uncommon": 15,
    "S2 Ultra-Rare": 7,
    "S3 Epic": 16917,
    "S3 Legendary": 52,
    "S3 Ultra-Rare": 1,
    "S4 Legendary": 1
  },
  {
    "Nation": "Philville2",
    "Junk Value": 1633.25,
    "Bank": 16.32,
    "Deck Value": 172721.4,
    "Card Count": 2962,
    "Deck Capacity": 3186,
    "Legendary Value Raw": 102211.96,
    "Legendary Value": 59.18,
    "Common": 880,
    "Uncommon": 235,
    "Legendary": 1554,
    "Ultra-Rare": 126,
    "Rare": 100,
    "Epic": 67,
    "S2": 1352,
    "S1": 66,
    "S3": 1045,
    "S4": 499,
    "S2 Common": 526,
    "S1 Uncommon": 4,
    "S1 Common": 4,
    "S2 Legendary": 612,
    "S1 Legendary": 53,
    "S2 Uncommon": 182,
    "S2 Ultra-Rare": 17,
    "S2 Rare": 8,
    "S2 Epic": 7,
    "S1 Epic": 4,
    "S3 Uncommon": 19,
    "S3 Common": 217,
    "S3 Legendary": 610,
    "S3 Epic": 45,
    "S3 Ultra-Rare": 79,
    "S3 Rare": 75,
    "S4 Legendary": 279,
    "S4 Ultra-Rare": 29,
    "S1 Ultra-Rare": 1,
    "S4 Rare": 17,
    "S4 Uncommon": 30,
    "S4 Common": 133,
    "S4 Epic": 11
  },
  {
    "Nation": "Feu De Glace",
    "Junk Value": 1104.54,
    "Bank": 27199.76,
    "Deck Value": 167799.02,
    "Card Count": 1637,
    "Deck Capacity": 4479,
    "Legendary Value Raw": 143964.71,
    "Legendary Value": 85.8,
    "Legendary": 1024,
    "Uncommon": 60,
    "Ultra-Rare": 128,
    "Common": 294,
    "Epic": 98,
    "Rare": 33,
    "S2": 636,
    "S1": 655,
    "S3": 274,
    "S4": 72,
    "S2 Legendary": 431,
    "S1 Uncommon": 37,
    "S1 Ultra-Rare": 104,
    "S1 Common": 119,
    "S1 Epic": 82,
    "S1 Legendary": 292,
    "S1 Rare": 21,
    "S2 Rare": 9,
    "S2 Ultra-Rare": 21,
    "S2 Common": 143,
    "S2 Epic": 13,
    "S2 Uncommon": 19,
    "S3 Epic": 3,
    "S3 Legendary": 231,
    "S3 Uncommon": 3,
    "S3 Common": 31,
    "S3 Ultra-Rare": 3,
    "S3 Rare": 3,
    "S4 Legendary": 70,
    "S4 Common": 1,
    "S4 Uncommon": 1
  },
  {
    "Nation": "Dr Hooves",
    "Junk Value": 1545.3,
    "Bank": 11675.0,
    "Deck Value": 164144.56,
    "Card Count": 7158,
    "Deck Capacity": 9862,
    "Legendary Value Raw": 83057.54,
    "Legendary Value": 50.6,
    "Common": 3085,
    "Uncommon": 1677,
    "Rare": 604,
    "Ultra-Rare": 333,
    "Epic": 190,
    "Legendary": 1269,
    "S1": 312,
    "S2": 1168,
    "S3": 4094,
    "S4": 1584,
    "S1 Common": 142,
    "S2 Common": 435,
    "S1 Uncommon": 96,
    "S2 Uncommon": 408,
    "S2 Rare": 78,
    "S1 Ultra-Rare": 15,
    "S1 Rare": 35,
    "S1 Epic": 9,
    "S1 Legendary": 15,
    "S2 Ultra-Rare": 32,
    "S2 Legendary": 201,
    "S2 Epic": 14,
    "S3 Uncommon": 637,
    "S3 Ultra-Rare": 225,
    "S3 Common": 1672,
    "S3 Rare": 370,
    "S3 Legendary": 1028,
    "S3 Epic": 162,
    "S4 Common": 836,
    "S4 Uncommon": 536,
    "S4 Epic": 5,
    "S4 Rare": 121,
    "S4 Ultra-Rare": 61,
    "S4 Legendary": 25
  },
  {
    "Nation": "The Shaymen",
    "Junk Value": 2805.0,
    "Bank": 12843.34,
    "Deck Value": 160036.69,
    "Card Count": 2805,
    "Deck Capacity": 4010,
    "Legendary Value Raw": 160039.03,
    "Legendary Value": 100.0,
    "Legendary": 2805,
    "S1": 64,
    "S2": 764,
    "S3": 1849,
    "S4": 128,
    "S1 Legendary": 64,
    "S2 Legendary": 764,
    "S3 Legendary": 1849,
    "S4 Legendary": 128
  },
  {
    "Nation": "Ever Testing",
    "Junk Value": 5091.84,
    "Bank": 1276.19,
    "Deck Value": 156839.37,
    "Card Count": 15678,
    "Deck Capacity": 16074,
    "Legendary Value Raw": 82553.42,
    "Legendary Value": 52.64,
    "Common": 4709,
    "Epic": 7877,
    "Uncommon": 877,
    "Legendary": 912,
    "Ultra-Rare": 752,
    "Rare": 551,
    "S1": 372,
    "S2": 3862,
    "S3": 11182,
    "S4": 262,
    "S1 Common": 180,
    "S1 Epic": 137,
    "S2 Epic": 1935,
    "S1 Uncommon": 28,
    "S1 Legendary": 8,
    "S1 Ultra-Rare": 12,
    "S2 Legendary": 195,
    "S2 Common": 1446,
    "S2 Uncommon": 157,
    "S2 Rare": 66,
    "S2 Ultra-Rare": 63,
    "S1 Rare": 7,
    "S3 Common": 2930,
    "S3 Uncommon": 671,
    "S3 Epic": 5800,
    "S3 Rare": 436,
    "S3 Ultra-Rare": 636,
    "S3 Legendary": 709,
    "S4 Uncommon": 21,
    "S4 Common": 153,
    "S4 Ultra-Rare": 41,
    "S4 Rare": 42,
    "S4 Epic": 5
  },
  {
    "Nation": "Troc",
    "Junk Value": 1584.26,
    "Bank": 383.55,
    "Deck Value": 140396.9,
    "Card Count": 1843,
    "Deck Capacity": 2000,
    "Legendary Value Raw": 98835.82,
    "Legendary Value": 70.4,
    "Legendary": 1548,
    "Ultra-Rare": 66,
    "Epic": 40,
    "Common": 96,
    "Rare": 51,
    "Uncommon": 42,
    "S1": 17,
    "S2": 130,
    "S3": 1324,
    "S4": 372,
    "S1 Legendary": 15,
    "S2 Legendary": 124,
    "S3 Legendary": 1137,
    "S3 Ultra-Rare": 17,
    "S3 Epic": 31,
    "S3 Common": 77,
    "S3 Rare": 43,
    "S3 Uncommon": 19,
    "S2 Uncommon": 2,
    "S1 Uncommon": 1,
    "S2 Epic": 2,
    "S4 Legendary": 272,
    "S2 Common": 2,
    "S4 Ultra-Rare": 49,
    "S4 Common": 16,
    "S4 Uncommon": 20,
    "S4 Epic": 7,
    "S4 Rare": 8,
    "S1 Common": 1
  },
  {
    "Nation": "Rotenaplistan",
    "Junk Value": 2427.17,
    "Bank": 4584.43,
    "Deck Value": 133731.52,
    "Card Count": 5072,
    "Deck Capacity": 5784,
    "Legendary Value Raw": 93010.09,
    "Legendary Value": 69.55,
    "Common": 687,
    "Epic": 1353,
    "Ultra-Rare": 758,
    "Uncommon": 444,
    "Legendary": 1570,
    "Rare": 260,
    "S1": 88,
    "S2": 383,
    "S3": 4238,
    "S4": 363,
    "S1 Common": 21,
    "S2 Epic": 34,
    "S1 Ultra-Rare": 11,
    "S1 Uncommon": 31,
    "S1 Epic": 13,
    "S2 Common": 101,
    "S2 Legendary": 112,
    "S2 Ultra-Rare": 73,
    "S2 Rare": 24,
    "S2 Uncommon": 39,
    "S1 Rare": 6,
    "S3 Epic": 1279,
    "S3 Ultra-Rare": 659,
    "S3 Common": 488,
    "S3 Uncommon": 345,
    "S3 Rare": 219,
    "S3 Legendary": 1248,
    "S1 Legendary": 6,
    "S4 Legendary": 204,
    "S4 Epic": 27,
    "S4 Uncommon": 29,
    "S4 Common": 77,
    "S4 Ultra-Rare": 15,
    "S4 Rare": 11
  },
  {
    "Nation": "The Overseer",
    "Junk Value": 1700.31,
    "Bank": 82.48,
    "Deck Value": 120486.68,
    "Card Count": 2357,
    "Deck Capacity": 2500,
    "Legendary Value Raw": 100571.98,
    "Legendary Value": 83.47,
    "Ultra-Rare": 155,
    "Legendary": 1647,
    "Epic": 26,
    "Common": 391,
    "Uncommon": 108,
    "Rare": 30,
    "S1": 20,
    "S2": 112,
    "S3": 1952,
    "S4": 273,
    "S1 Ultra-Rare": 3,
    "S1 Legendary": 11,
    "S1 Epic": 2,
    "S2 Legendary": 81,
    "S1 Common": 2,
    "S2 Ultra-Rare": 16,
    "S2 Uncommon": 5,
    "S2 Common": 7,
    "S2 Epic": 1,
    "S2 Rare": 2,
    "S1 Rare": 1,
    "S3 Common": 211,
    "S3 Uncommon": 60,
    "S3 Legendary": 1522,
    "S3 Ultra-Rare": 121,
    "S3 Rare": 19,
    "S3 Epic": 19,
    "S1 Uncommon": 1,
    "S4 Uncommon": 42,
    "S4 Rare": 8,
    "S4 Common": 171,
    "S4 Ultra-Rare": 15,
    "S4 Legendary": 33,
    "S4 Epic": 4
  },
  {
    "Nation": "Ioavollr",
    "Junk Value": 1659.51,
    "Bank": 164.29,
    "Deck Value": 114250.63,
    "Card Count": 3259,
    "Deck Capacity": 5864,
    "Legendary Value Raw": 64385.63,
    "Legendary Value": 56.35,
    "Ultra-Rare": 563,
    "Epic": 1023,
    "Legendary": 1023,
    "Uncommon": 171,
    "Common": 386,
    "Rare": 93,
    "S1": 281,
    "S2": 1196,
    "S3": 1712,
    "S4": 70,
    "S1 Ultra-Rare": 68,
    "S1 Epic": 46,
    "S1 Legendary": 87,
    "S1 Uncommon": 38,
    "S1 Common": 24,
    "S1 Rare": 18,
    "S2 Uncommon": 69,
    "S2 Ultra-Rare": 326,
    "S2 Legendary": 584,
    "S2 Common": 97,
    "S2 Epic": 91,
    "S2 Rare": 29,
    "S3 Rare": 39,
    "S3 Common": 251,
    "S3 Uncommon": 41,
    "S3 Ultra-Rare": 162,
    "S3 Epic": 868,
    "S3 Legendary": 351,
    "S4 Uncommon": 23,
    "S4 Epic": 18,
    "S4 Common": 14,
    "S4 Ultra-Rare": 7,
    "S4 Rare": 7,
    "S4 Legendary": 1
  },
  {
    "Nation": "Minskiev",
    "Junk Value": 1197.28,
    "Bank": 189.77,
    "Deck Value": 109692.89,
    "Card Count": 2288,
    "Deck Capacity": 6344,
    "Legendary Value Raw": 87376.25,
    "Legendary Value": 79.66,
    "Legendary": 1118,
    "Epic": 91,
    "Uncommon": 291,
    "Ultra-Rare": 62,
    "Rare": 43,
    "Common": 683,
    "S1": 233,
    "S2": 1400,
    "S3": 649,
    "S4": 6,
    "S1 Legendary": 172,
    "S1 Epic": 21,
    "S1 Uncommon": 20,
    "S1 Ultra-Rare": 6,
    "S2 Legendary": 911,
    "S1 Rare": 3,
    "S2 Common": 323,
    "S2 Ultra-Rare": 33,
    "S2 Uncommon": 64,
    "S2 Rare": 11,
    "S2 Epic": 58,
    "S1 Common": 11,
    "S3 Common": 348,
    "S3 Uncommon": 207,
    "S3 Ultra-Rare": 23,
    "S3 Legendary": 30,
    "S3 Epic": 12,
    "S3 Rare": 29,
    "S4 Legendary": 5,
    "S4 Common": 1
  },
  {
    "Nation": "Siwale",
    "Junk Value": 1166.51,
    "Bank": 3403.52,
    "Deck Value": 108472.83,
    "Card Count": 1409,
    "Deck Capacity": 3186,
    "Legendary Value Raw": 95251.08,
    "Legendary Value": 87.81,
    "Common": 71,
    "Legendary": 1074,
    "Ultra-Rare": 61,
    "Epic": 156,
    "Uncommon": 32,
    "Rare": 15,
    "S1": 718,
    "S2": 219,
    "S3": 471,
    "S4": 1,
    "S1 Common": 70,
    "S1 Legendary": 407,
    "S2 Legendary": 214,
    "S1 Ultra-Rare": 58,
    "S1 Epic": 143,
    "S1 Uncommon": 27,
    "S1 Rare": 13,
    "S2 Uncommon": 4,
    "S2 Epic": 1,
    "S3 Legendary": 452,
    "S3 Epic": 12,
    "S3 Rare": 2,
    "S3 Ultra-Rare": 3,
    "S3 Uncommon": 1,
    "S3 Common": 1,
    "S4 Legendary": 1
  },
  {
    "Nation": "Yodle",
    "Junk Value": 1544.81,
    "Bank": 1136.68,
    "Deck Value": 107516.87,
    "Card Count": 29044,
    "Deck Capacity": 29074,
    "Legendary Value Raw": 2617.77,
    "Legendary Value": 2.43,
    "Common": 13336,
    "Rare": 4663,
    "Uncommon": 7305,
    "Ultra-Rare": 2811,
    "Epic": 890,
    "Legendary": 39,
    "S1": 3458,
    "S2": 11536,
    "S3": 12301,
    "S4": 1749,
    "S1 Common": 1797,
    "S1 Rare": 390,
    "S1 Uncommon": 912,
    "S1 Ultra-Rare": 260,
    "S1 Epic": 97,
    "S2 Rare": 1762,
    "S2 Common": 4880,
    "S2 Uncommon": 3392,
    "S2 Ultra-Rare": 1312,
    "S1 Legendary": 2,
    "S2 Epic": 183,
    "S2 Legendary": 7,
    "S3 Ultra-Rare": 1131,
    "S3 Epic": 543,
    "S3 Common": 5741,
    "S3 Uncommon": 2515,
    "S3 Legendary": 25,
    "S3 Rare": 2346,
    "S4 Uncommon": 486,
    "S4 Common": 918,
    "S4 Rare": 165,
    "S4 Ultra-Rare": 108,
    "S4 Epic": 67,
    "S4 Legendary": 5
  },
  {
    "Nation": "Triseria",
    "Junk Value": 1435.89,
    "Bank": 9415.73,
    "Deck Value": 107280.53,
    "Card Count": 2837,
    "Deck Capacity": 5864,
    "Legendary Value Raw": 98153.82,
    "Legendary Value": 91.49,
    "Legendary": 1396,
    "Common": 1069,
    "Uncommon": 196,
    "Rare": 124,
    "Epic": 30,
    "Ultra-Rare": 22,
    "S1": 79,
    "S2": 606,
    "S3": 1804,
    "S4": 348,
    "S1 Legendary": 71,
    "S2 Legendary": 588,
    "S2 Common": 7,
    "S2 Uncommon": 7,
    "S2 Rare": 2,
    "S2 Epic": 2,
    "S3 Legendary": 649,
    "S3 Common": 830,
    "S3 Uncommon": 165,
    "S3 Ultra-Rare": 12,
    "S3 Rare": 120,
    "S3 Epic": 28,
    "S1 Uncommon": 7,
    "S1 Common": 1,
    "S4 Legendary": 88,
    "S4 Common": 231,
    "S4 Rare": 2,
    "S4 Uncommon": 17,
    "S4 Ultra-Rare": 10
  },
  {
    "Nation": "Benevolent 1",
    "Junk Value": 782.55,
    "Bank": 20153.86,
    "Deck Value": 99568.85,
    "Card Count": 4543,
    "Deck Capacity": 6372,
    "Legendary Value Raw": 39561.6,
    "Legendary Value": 39.73,
    "Epic": 231,
    "Uncommon": 809,
    "Common": 1940,
    "Rare": 383,
    "Ultra-Rare": 716,
    "Legendary": 464,
    "S1": 1477,
    "S2": 1189,
    "S3": 1390,
    "S4": 487,
    "S1 Epic": 103,
    "S1 Uncommon": 267,
    "S1 Common": 762,
    "S1 Rare": 155,
    "S2 Uncommon": 306,
    "S1 Ultra-Rare": 67,
    "S2 Common": 477,
    "S2 Ultra-Rare": 147,
    "S1 Legendary": 123,
    "S2 Rare": 46,
    "S2 Legendary": 176,
    "S2 Epic": 37,
    "S3 Ultra-Rare": 309,
    "S3 Legendary": 145,
    "S3 Common": 573,
    "S3 Uncommon": 176,
    "S3 Rare": 119,
    "S3 Epic": 68,
    "S4 Ultra-Rare": 193,
    "S4 Uncommon": 60,
    "S4 Legendary": 20,
    "S4 Common": 128,
    "S4 Rare": 63,
    "S4 Epic": 23
  },
  {
    "Nation": "Valoptia",
    "Junk Value": 1062.52,
    "Bank": 416.48,
    "Deck Value": 99043.41,
    "Card Count": 1401,
    "Deck Capacity": 2336,
    "Legendary Value Raw": 81356.71,
    "Legendary Value": 82.14,
    "Legendary": 1051,
    "Common": 162,
    "Rare": 146,
    "Ultra-Rare": 10,
    "Epic": 14,
    "Uncommon": 18,
    "S1": 195,
    "S2": 181,
    "S3": 664,
    "S4": 361,
    "S1 Legendary": 185,
    "S2 Legendary": 172,
    "S3 Legendary": 389,
    "S3 Common": 110,
    "S3 Rare": 141,
    "S3 Ultra-Rare": 8,
    "S1 Rare": 2,
    "S3 Epic": 5,
    "S2 Uncommon": 4,
    "S1 Common": 8,
    "S2 Common": 3,
    "S3 Uncommon": 11,
    "S2 Ultra-Rare": 1,
    "S4 Legendary": 305,
    "S4 Common": 41,
    "S4 Epic": 9,
    "S4 Uncommon": 3,
    "S4 Ultra-Rare": 1,
    "S2 Rare": 1,
    "S4 Rare": 2
  },
  {
    "Nation": "Apexiala",
    "Junk Value": 1945.12,
    "Bank": 3300.44,
    "Deck Value": 97271.9,
    "Card Count": 42268,
    "Deck Capacity": 42284,
    "Legendary Value Raw": 47365.07,
    "Legendary Value": 48.69,
    "Common": 31717,
    "Uncommon": 5855,
    "Rare": 1893,
    "Ultra-Rare": 1471,
    "Legendary": 750,
    "Epic": 582,
    "S2": 14110,
    "S1": 1176,
    "S3": 25581,
    "S4": 1401,
    "S2 Common": 9868,
    "S1 Common": 506,
    "S1 Uncommon": 350,
    "S2 Uncommon": 2313,
    "S1 Rare": 157,
    "S1 Ultra-Rare": 96,
    "S2 Ultra-Rare": 525,
    "S1 Legendary": 28,
    "S1 Epic": 39,
    "S2 Epic": 276,
    "S2 Rare": 748,
    "S2 Legendary": 380,
    "S3 Common": 20363,
    "S3 Rare": 863,
    "S3 Uncommon": 3033,
    "S3 Legendary": 336,
    "S3 Ultra-Rare": 743,
    "S3 Epic": 243,
    "S4 Common": 980,
    "S4 Rare": 125,
    "S4 Ultra-Rare": 107,
    "S4 Uncommon": 159,
    "S4 Legendary": 6,
    "S4 Epic": 24
  },
  {
    "Nation": "K16",
    "Junk Value": 1527.74,
    "Bank": 301.48,
    "Deck Value": 96178.62,
    "Card Count": 4968,
    "Deck Capacity": 5500,
    "Legendary Value Raw": 83010.54,
    "Legendary Value": 86.31,
    "Legendary": 1256,
    "Common": 2474,
    "Uncommon": 344,
    "Rare": 225,
    "Epic": 320,
    "Ultra-Rare": 349,
    "S1": 74,
    "S2": 66,
    "S3": 573,
    "S4": 4255,
    "S1 Legendary": 17,
    "S2 Legendary": 25,
    "S2 Common": 27,
    "S2 Uncommon": 12,
    "S3 Rare": 15,
    "S3 Legendary": 100,
    "S3 Epic": 26,
    "S3 Common": 368,
    "S3 Ultra-Rare": 44,
    "S1 Common": 34,
    "S3 Uncommon": 20,
    "S4 Common": 2045,
    "S4 Ultra-Rare": 303,
    "S4 Epic": 283,
    "S4 Uncommon": 302,
    "S4 Legendary": 1114,
    "S4 Rare": 208,
    "S1 Uncommon": 10,
    "S2 Epic": 1,
    "S1 Epic": 10,
    "S2 Rare": 1,
    "S1 Ultra-Rare": 2,
    "S1 Rare": 1
  },
  {
    "Nation": "Lumity",
    "Junk Value": 75.81,
    "Bank": 48.3,
    "Deck Value": 95489.12,
    "Card Count": 5850,
    "Deck Capacity": 6336,
    "Legendary Value Raw": 0,
    "Legendary Value": 0.0,
    "Common": 5441,
    "Uncommon": 384,
    "Epic": 4,
    "Rare": 20,
    "Ultra-Rare": 1,
    "S3": 4365,
    "S4": 1485,
    "S3 Common": 4193,
    "S3 Uncommon": 168,
    "S3 Epic": 4,
    "S4 Common": 1248,
    "S4 Uncommon": 216,
    "S4 Rare": 20,
    "S4 Ultra-Rare": 1
  },
  {
    "Nation": "Sylh Alanor",
    "Junk Value": 1030.96,
    "Bank": 1255.62,
    "Deck Value": 92087.69,
    "Card Count": 1178,
    "Deck Capacity": 3186,
    "Legendary Value Raw": 88083.34,
    "Legendary Value": 95.65,
    "Legendary": 1005,
    "Common": 86,
    "Rare": 14,
    "Epic": 41,
    "Ultra-Rare": 20,
    "Uncommon": 12,
    "S1": 278,
    "S2": 735,
    "S3": 154,
    "S4": 11,
    "S1 Legendary": 261,
    "S2 Common": 69,
    "S1 Rare": 3,
    "S2 Legendary": 627,
    "S2 Epic": 25,
    "S1 Epic": 6,
    "S1 Ultra-Rare": 6,
    "S2 Uncommon": 4,
    "S2 Ultra-Rare": 8,
    "S2 Rare": 2,
    "S1 Uncommon": 2,
    "S3 Legendary": 114,
    "S3 Common": 15,
    "S3 Rare": 7,
    "S3 Ultra-Rare": 6,
    "S3 Uncommon": 4,
    "S3 Epic": 8,
    "S4 Epic": 2,
    "S4 Rare": 2,
    "S4 Common": 2,
    "S4 Legendary": 3,
    "S4 Uncommon": 2
  },
  {
    "Nation": "Midlands",
    "Junk Value": 2784.11,
    "Bank": 2711.24,
    "Deck Value": 86855.44,
    "Card Count": 7817,
    "Deck Capacity": 8958,
    "Legendary Value Raw": 58982.91,
    "Legendary Value": 67.91,
    "Uncommon": 1291,
    "Epic": 3215,
    "Common": 146,
    "Ultra-Rare": 1323,
    "Rare": 996,
    "Legendary": 846,
    "S1": 169,
    "S2": 1249,
    "S3": 5767,
    "S4": 632,
    "S1 Uncommon": 30,
    "S1 Epic": 44,
    "S1 Common": 7,
    "S1 Ultra-Rare": 22,
    "S1 Rare": 12,
    "S1 Legendary": 54,
    "S2 Uncommon": 169,
    "S2 Rare": 119,
    "S2 Legendary": 616,
    "S2 Ultra-Rare": 138,
    "S2 Epic": 186,
    "S2 Common": 21,
    "S3 Common": 110,
    "S3 Ultra-Rare": 1024,
    "S3 Rare": 731,
    "S3 Legendary": 168,
    "S3 Epic": 2852,
    "S3 Uncommon": 882,
    "S4 Ultra-Rare": 139,
    "S4 Uncommon": 210,
    "S4 Rare": 134,
    "S4 Epic": 133,
    "S4 Common": 8,
    "S4 Legendary": 8
  },
  {
    "Nation": "Klaus Devestatorie",
    "Junk Value": 3887.13,
    "Bank": 14104.52,
    "Deck Value": 86324.4,
    "Card Count": 11209,
    "Deck Capacity": 11592,
    "Legendary Value Raw": 56816.13,
    "Legendary Value": 65.82,
    "Ultra-Rare": 1406,
    "Common": 1978,
    "Epic": 5234,
    "Rare": 726,
    "Uncommon": 943,
    "Legendary": 922,
    "S1": 692,
    "S2": 160,
    "S3": 9952,
    "S4": 405,
    "S1 Ultra-Rare": 190,
    "S1 Common": 250,
    "S1 Epic": 105,
    "S1 Rare": 36,
    "S1 Uncommon": 97,
    "S1 Legendary": 14,
    "S2 Epic": 66,
    "S2 Uncommon": 43,
    "S2 Rare": 21,
    "S2 Common": 22,
    "S2 Ultra-Rare": 5,
    "S3 Common": 1649,
    "S3 Epic": 4795,
    "S3 Uncommon": 778,
    "S3 Legendary": 880,
    "S3 Ultra-Rare": 1189,
    "S3 Rare": 661,
    "S2 Legendary": 3,
    "S4 Rare": 8,
    "S4 Epic": 268,
    "S4 Legendary": 25,
    "S4 Common": 57,
    "S4 Uncommon": 25,
    "S4 Ultra-Rare": 22
  },
  {
    "Nation": "Elegarth",
    "Junk Value": 915.72,
    "Bank": 1118.09,
    "Deck Value": 83620.14,
    "Card Count": 2483,
    "Deck Capacity": 4479,
    "Legendary Value Raw": 54286.04,
    "Legendary Value": 64.92,
    "Uncommon": 245,
    "Legendary": 748,
    "Common": 517,
    "Ultra-Rare": 469,
    "Epic": 113,
    "Rare": 391,
    "S1": 342,
    "S2": 787,
    "S3": 1083,
    "S4": 271,
    "S1 Uncommon": 65,
    "S1 Legendary": 184,
    "S2 Legendary": 269,
    "S1 Common": 63,
    "S1 Ultra-Rare": 14,
    "S1 Epic": 13,
    "S2 Epic": 8,
    "S1 Rare": 3,
    "S2 Common": 76,
    "S2 Ultra-Rare": 113,
    "S2 Rare": 296,
    "S2 Uncommon": 25,
    "S3 Ultra-Rare": 334,
    "S3 Legendary": 260,
    "S3 Common": 246,
    "S3 Epic": 62,
    "S3 Uncommon": 106,
    "S3 Rare": 75,
    "S4 Epic": 30,
    "S4 Legendary": 35,
    "S4 Rare": 17,
    "S4 Uncommon": 49,
    "S4 Common": 132,
    "S4 Ultra-Rare": 8
  },
  {
    "Nation": "One Small Island",
    "Junk Value": 901.0,
    "Bank": 106.73,
    "Deck Value": 78139.73,
    "Card Count": 1983,
    "Deck Capacity": 4037,
    "Legendary Value Raw": 52647.86,
    "Legendary Value": 67.38,
    "Legendary": 785,
    "Common": 695,
    "Uncommon": 203,
    "Epic": 169,
    "Rare": 59,
    "Ultra-Rare": 72,
    "S1": 271,
    "S2": 1318,
    "S3": 300,
    "S4": 94,
    "S1 Legendary": 74,
    "S1 Common": 78,
    "S1 Uncommon": 17,
    "S1 Epic": 89,
    "S2 Epic": 38,
    "S2 Common": 555,
    "S2 Legendary": 532,
    "S1 Rare": 4,
    "S1 Ultra-Rare": 9,
    "S2 Uncommon": 158,
    "S2 Rare": 25,
    "S2 Ultra-Rare": 10,
    "S3 Legendary": 147,
    "S3 Ultra-Rare": 43,
    "S3 Epic": 29,
    "S3 Common": 43,
    "S3 Uncommon": 16,
    "S3 Rare": 22,
    "S4 Legendary": 32,
    "S4 Common": 19,
    "S4 Rare": 8,
    "S4 Epic": 13,
    "S4 Uncommon": 12,
    "S4 Ultra-Rare": 10
  },
  {
    "Nation": "New Sunville",
    "Junk Value": 843.16,
    "Bank": 274.91,
    "Deck Value": 73703.11,
    "Card Count": 2876,
    "Deck Capacity": 5393,
    "Legendary Value Raw": 41819.44,
    "Legendary Value": 56.74,
    "Common": 1011,
    "Uncommon": 487,
    "Rare": 113,
    "Epic": 319,
    "Ultra-Rare": 371,
    "Legendary": 575,
    "S2": 1197,
    "S1": 160,
    "S3": 1355,
    "S4": 164,
    "S2 Common": 479,
    "S1 Common": 37,
    "S1 Uncommon": 32,
    "S1 Rare": 9,
    "S2 Epic": 58,
    "S1 Ultra-Rare": 22,
    "S1 Epic": 31,
    "S1 Legendary": 29,
    "S2 Ultra-Rare": 84,
    "S2 Uncommon": 358,
    "S2 Legendary": 169,
    "S2 Rare": 49,
    "S3 Common": 374,
    "S3 Legendary": 356,
    "S3 Uncommon": 91,
    "S3 Ultra-Rare": 259,
    "S3 Epic": 220,
    "S3 Rare": 55,
    "S4 Uncommon": 6,
    "S4 Epic": 10,
    "S4 Legendary": 21,
    "S4 Common": 121,
    "S4 Ultra-Rare": 6
  },
  {
    "Nation": "Empire Of Caldrasa",
    "Junk Value": 103.59,
    "Bank": 102.05,
    "Deck Value": 72887.22,
    "Card Count": 1114,
    "Deck Capacity": 2000,
    "Legendary Value Raw": 2311.32,
    "Legendary Value": 3.17,
    "Epic": 67,
    "Common": 289,
    "Rare": 434,
    "Uncommon": 208,
    "Ultra-Rare": 74,
    "Legendary": 42,
    "S2": 35,
    "S3": 789,
    "S1": 24,
    "S4": 266,
    "S2 Epic": 1,
    "S2 Common": 22,
    "S2 Rare": 5,
    "S2 Uncommon": 5,
    "S2 Ultra-Rare": 2,
    "S3 Common": 170,
    "S3 Rare": 424,
    "S3 Epic": 58,
    "S3 Uncommon": 120,
    "S3 Ultra-Rare": 13,
    "S3 Legendary": 4,
    "S1 Common": 16,
    "S1 Ultra-Rare": 1,
    "S1 Uncommon": 4,
    "S1 Epic": 1,
    "S1 Rare": 2,
    "S4 Common": 81,
    "S4 Uncommon": 79,
    "S4 Ultra-Rare": 58,
    "S4 Legendary": 38,
    "S4 Epic": 7,
    "S4 Rare": 3
  },
  {
    "Nation": "Anjan Kloss",
    "Junk Value": 3286.07,
    "Bank": 1165.5,
    "Deck Value": 72330.3,
    "Card Count": 19401,
    "Deck Capacity": 19500,
    "Legendary Value Raw": 56263.32,
    "Legendary Value": 77.79,
    "Common": 12092,
    "Legendary": 923,
    "Uncommon": 1629,
    "Ultra-Rare": 306,
    "Rare": 252,
    "Epic": 4199,
    "S2": 98,
    "S1": 70,
    "S3": 4665,
    "S4": 14568,
    "S2 Common": 27,
    "S2 Legendary": 3,
    "S2 Uncommon": 20,
    "S2 Ultra-Rare": 7,
    "S1 Legendary": 7,
    "S2 Rare": 2,
    "S2 Epic": 39,
    "S3 Common": 722,
    "S3 Uncommon": 776,
    "S3 Legendary": 589,
    "S3 Ultra-Rare": 227,
    "S3 Epic": 2248,
    "S3 Rare": 103,
    "S1 Epic": 36,
    "S1 Uncommon": 9,
    "S1 Common": 14,
    "S1 Ultra-Rare": 3,
    "S1 Rare": 1,
    "S4 Legendary": 324,
    "S4 Common": 11329,
    "S4 Epic": 1876,
    "S4 Uncommon": 824,
    "S4 Rare": 146,
    "S4 Ultra-Rare": 69
  },
  {
    "Nation": "Shibutani",
    "Junk Value": 818.44,
    "Bank": 378.26,
    "Deck Value": 72327.52,
    "Card Count": 3250,
    "Deck Capacity": 4037,
    "Legendary Value Raw": 49305.79,
    "Legendary Value": 68.17,
    "Epic": 285,
    "Ultra-Rare": 381,
    "Uncommon": 611,
    "Legendary": 558,
    "Common": 1119,
    "Rare": 296,
    "S1": 219,
    "S2": 468,
    "S3": 2499,
    "S4": 64,
    "S1 Epic": 84,
    "S1 Ultra-Rare": 56,
    "S1 Uncommon": 16,
    "S1 Legendary": 37,
    "S2 Legendary": 134,
    "S2 Common": 182,
    "S1 Rare": 5,
    "S1 Common": 21,
    "S2 Uncommon": 57,
    "S2 Ultra-Rare": 58,
    "S2 Epic": 31,
    "S2 Rare": 6,
    "S3 Common": 906,
    "S3 Epic": 156,
    "S3 Legendary": 371,
    "S3 Uncommon": 531,
    "S3 Ultra-Rare": 254,
    "S3 Rare": 281,
    "S4 Ultra-Rare": 13,
    "S4 Epic": 14,
    "S4 Uncommon": 7,
    "S4 Legendary": 16,
    "S4 Common": 10,
    "S4 Rare": 4
  },
  {
    "Nation": "Mind The Gap",
    "Junk Value": 234.87,
    "Bank": 4.62,
    "Deck Value": 70047.35,
    "Card Count": 2470,
    "Deck Capacity": 2500,
    "Legendary Value Raw": 0,
    "Legendary Value": 0.0,
    "Uncommon": 688,
    "Common": 447,
    "Rare": 355,
    "Ultra-Rare": 980,
    "S2": 782,
    "S3": 1649,
    "S1": 34,
    "S4": 5,
    "S2 Uncommon": 607,
    "S2 Common": 94,
    "S2 Rare": 79,
    "S2 Ultra-Rare": 2,
    "S3 Common": 348,
    "S3 Rare": 276,
    "S3 Ultra-Rare": 977,
    "S1 Uncommon": 30,
    "S3 Uncommon": 48,
    "S1 Ultra-Rare": 1,
    "S1 Common": 3,
    "S4 Uncommon": 3,
    "S4 Common": 2
  },
  {
    "Nation": "The Bank Of Caprica",
    "Junk Value": 30.62,
    "Bank": 495.35,
    "Deck Value": 69148.14,
    "Card Count": 2299,
    "Deck Capacity": 2592,
    "Legendary Value Raw": 0,
    "Legendary Value": 0.0,
    "Common": 1077,
    "Uncommon": 373,
    "Rare": 846,
    "Ultra-Rare": 1,
    "Epic": 2,
    "S2": 865,
    "S1": 1,
    "S3": 1301,
    "S4": 132,
    "S2 Common": 714,
    "S2 Uncommon": 151,
    "S1 Uncommon": 1,
    "S3 Common": 295,
    "S3 Uncommon": 213,
    "S3 Rare": 791,
    "S3 Ultra-Rare": 1,
    "S3 Epic": 1,
    "S4 Rare": 55,
    "S4 Common": 68,
    "S4 Uncommon": 8,
    "S4 Epic": 1
  },
  {
    "Nation": "Drew Durrnil",
    "Junk Value": 916.56,
    "Bank": 53.9,
    "Deck Value": 65267.67,
    "Card Count": 3372,
    "Deck Capacity": 3505,
    "Legendary Value Raw": 40316.22,
    "Legendary Value": 61.77,
    "Epic": 317,
    "Ultra-Rare": 321,
    "Common": 1131,
    "Legendary": 654,
    "Rare": 378,
    "Uncommon": 571,
    "S1": 46,
    "S2": 311,
    "S3": 2858,
    "S4": 157,
    "S1 Epic": 3,
    "S1 Ultra-Rare": 5,
    "S1 Common": 20,
    "S2 Legendary": 14,
    "S2 Rare": 41,
    "S2 Epic": 39,
    "S2 Ultra-Rare": 106,
    "S2 Uncommon": 52,
    "S2 Common": 59,
    "S1 Rare": 11,
    "S1 Uncommon": 4,
    "S3 Uncommon": 503,
    "S3 Epic": 269,
    "S3 Ultra-Rare": 199,
    "S3 Common": 1029,
    "S3 Rare": 317,
    "S3 Legendary": 541,
    "S1 Legendary": 3,
    "S4 Legendary": 96,
    "S4 Uncommon": 12,
    "S4 Common": 23,
    "S4 Rare": 9,
    "S4 Epic": 6,
    "S4 Ultra-Rare": 11
  },
  {
    "Nation": "Power For People",
    "Junk Value": 137.05,
    "Bank": 1696.65,
    "Deck Value": 63507.29,
    "Card Count": 3621,
    "Deck Capacity": 3894,
    "Legendary Value Raw": 2691.09,
    "Legendary Value": 4.24,
    "Uncommon": 530,
    "Rare": 194,
    "Common": 2705,
    "Legendary": 35,
    "Ultra-Rare": 100,
    "Epic": 57,
    "S1": 38,
    "S2": 106,
    "S3": 3470,
    "S4": 7,
    "S1 Uncommon": 17,
    "S1 Rare": 5,
    "S1 Common": 14,
    "S1 Legendary": 1,
    "S2 Common": 51,
    "S2 Uncommon": 23,
    "S2 Rare": 18,
    "S2 Ultra-Rare": 8,
    "S2 Epic": 6,
    "S3 Common": 2640,
    "S3 Ultra-Rare": 91,
    "S3 Epic": 51,
    "S3 Rare": 164,
    "S3 Uncommon": 490,
    "S3 Legendary": 34,
    "S1 Ultra-Rare": 1,
    "S4 Rare": 7
  },
  {
    "Nation": "Giraffeton",
    "Junk Value": 1630.34,
    "Bank": 7843.19,
    "Deck Value": 63394.44,
    "Card Count": 40519,
    "Deck Capacity": 50440,
    "Legendary Value Raw": 21858.29,
    "Legendary Value": 34.48,
    "Uncommon": 5120,
    "Common": 30814,
    "Ultra-Rare": 2016,
    "Rare": 1542,
    "Epic": 728,
    "Legendary": 299,
    "S1": 61,
    "S2": 3967,
    "S3": 36254,
    "S4": 237,
    "S1 Uncommon": 15,
    "S1 Common": 27,
    "S2 Uncommon": 830,
    "S2 Ultra-Rare": 852,
    "S2 Rare": 281,
    "S2 Epic": 271,
    "S2 Common": 1680,
    "S1 Rare": 6,
    "S2 Legendary": 53,
    "S1 Ultra-Rare": 7,
    "S1 Epic": 4,
    "S3 Common": 28954,
    "S3 Ultra-Rare": 1145,
    "S3 Uncommon": 4227,
    "S3 Epic": 447,
    "S3 Rare": 1239,
    "S3 Legendary": 242,
    "S1 Legendary": 2,
    "S4 Legendary": 2,
    "S4 Uncommon": 48,
    "S4 Common": 153,
    "S4 Ultra-Rare": 12,
    "S4 Rare": 16,
    "S4 Epic": 6
  },
  {
    "Nation": "Volikara",
    "Junk Value": 744.68,
    "Bank": 9202.44,
    "Deck Value": 62437.71,
    "Card Count": 2526,
    "Deck Capacity": 3000,
    "Legendary Value Raw": 48986.97,
    "Legendary Value": 78.46,
    "Common": 1118,
    "Uncommon": 360,
    "Ultra-Rare": 130,
    "Epic": 131,
    "Legendary": 624,
    "Rare": 163,
    "S1": 153,
    "S2": 190,
    "S3": 1295,
    "S4": 888,
    "S1 Common": 70,
    "S1 Uncommon": 47,
    "S1 Ultra-Rare": 5,
    "S1 Epic": 7,
    "S2 Uncommon": 51,
    "S2 Legendary": 18,
    "S2 Epic": 3,
    "S2 Common": 91,
    "S2 Rare": 13,
    "S2 Ultra-Rare": 14,
    "S3 Rare": 92,
    "S3 Common": 626,
    "S3 Legendary": 300,
    "S3 Ultra-Rare": 67,
    "S3 Uncommon": 156,
    "S3 Epic": 54,
    "S1 Rare": 18,
    "S1 Legendary": 6,
    "S4 Epic": 67,
    "S4 Common": 331,
    "S4 Legendary": 300,
    "S4 Uncommon": 106,
    "S4 Ultra-Rare": 44,
    "S4 Rare": 40
  },
  {
    "Nation": "Super Awesome Fun Times",
    "Junk Value": 1772.81,
    "Bank": 3178.34,
    "Deck Value": 61707.48,
    "Card Count": 28272,
    "Deck Capacity": 28674,
    "Legendary Value Raw": 39940.22,
    "Legendary Value": 64.73,
    "Ultra-Rare": 1607,
    "Rare": 1739,
    "Epic": 700,
    "Uncommon": 7495,
    "Common": 16166,
    "Legendary": 565,
    "S1": 992,
    "S2": 7108,
    "S3": 12476,
    "S4": 7696,
    "S1 Ultra-Rare": 131,
    "S1 Rare": 96,
    "S1 Epic": 78,
    "S1 Uncommon": 330,
    "S1 Common": 352,
    "S2 Uncommon": 1600,
    "S2 Ultra-Rare": 345,
    "S2 Common": 4670,
    "S2 Epic": 145,
    "S2 Rare": 301,
    "S1 Legendary": 5,
    "S2 Legendary": 47,
    "S3 Uncommon": 3349,
    "S3 Common": 7038,
    "S3 Rare": 838,
    "S3 Ultra-Rare": 624,
    "S3 Epic": 251,
    "S3 Legendary": 376,
    "S4 Common": 4106,
    "S4 Uncommon": 2216,
    "S4 Rare": 504,
    "S4 Ultra-Rare": 507,
    "S4 Legendary": 137,
    "S4 Epic": 226
  },
  {
    "Nation": "Andusre",
    "Junk Value": 851.28,
    "Bank": 190.88,
    "Deck Value": 59945.59,
    "Card Count": 1032,
    "Deck Capacity": 3186,
    "Legendary Value Raw": 58864.59,
    "Legendary Value": 98.2,
    "Common": 78,
    "Legendary": 840,
    "Uncommon": 72,
    "Epic": 7,
    "Rare": 18,
    "Ultra-Rare": 17,
    "S1": 83,
    "S2": 737,
    "S3": 129,
    "S4": 83,
    "S1 Common": 14,
    "S2 Legendary": 643,
    "S1 Legendary": 67,
    "S1 Uncommon": 1,
    "S2 Uncommon": 46,
    "S2 Common": 31,
    "S1 Epic": 1,
    "S2 Rare": 5,
    "S2 Ultra-Rare": 11,
    "S2 Epic": 1,
    "S3 Uncommon": 24,
    "S3 Legendary": 71,
    "S3 Rare": 13,
    "S3 Common": 10,
    "S3 Ultra-Rare": 6,
    "S3 Epic": 5,
    "S4 Legendary": 59,
    "S4 Uncommon": 1,
    "S4 Common": 23
  },
  {
    "Nation": "Inven",
    "Junk Value": 462.6,
    "Bank": 3339.78,
    "Deck Value": 58617.09,
    "Card Count": 1386,
    "Deck Capacity": 3606,
    "Legendary Value Raw": 26275.97,
    "Legendary Value": 44.83,
    "Uncommon": 421,
    "Epic": 125,
    "Rare": 57,
    "Legendary": 341,
    "Common": 265,
    "Ultra-Rare": 177,
    "S1": 196,
    "S2": 387,
    "S3": 591,
    "S4": 212,
    "S1 Uncommon": 48,
    "S1 Epic": 34,
    "S1 Rare": 20,
    "S1 Legendary": 29,
    "S1 Common": 27,
    "S1 Ultra-Rare": 38,
    "S2 Uncommon": 242,
    "S2 Legendary": 38,
    "S2 Common": 37,
    "S2 Ultra-Rare": 32,
    "S2 Epic": 26,
    "S2 Rare": 12,
    "S3 Legendary": 245,
    "S3 Uncommon": 82,
    "S3 Ultra-Rare": 97,
    "S3 Common": 96,
    "S3 Epic": 48,
    "S3 Rare": 23,
    "S4 Common": 105,
    "S4 Epic": 17,
    "S4 Ultra-Rare": 10,
    "S4 Rare": 2,
    "S4 Uncommon": 49,
    "S4 Legendary": 29
  },
  {
    "Nation": "Numero Capitan",
    "Junk Value": 694.49,
    "Bank": 1019.76,
    "Deck Value": 57455.6,
    "Card Count": 1905,
    "Deck Capacity": 3186,
    "Legendary Value Raw": 50640.95,
    "Legendary Value": 88.14,
    "Rare": 163,
    "Common": 439,
    "Ultra-Rare": 260,
    "Epic": 122,
    "Uncommon": 362,
    "Legendary": 559,
    "S1": 382,
    "S2": 835,
    "S3": 580,
    "S4": 108,
    "S1 Rare": 40,
    "S1 Common": 108,
    "S1 Ultra-Rare": 60,
    "S1 Epic": 36,
    "S1 Uncommon": 70,
    "S2 Legendary": 171,
    "S1 Legendary": 68,
    "S2 Common": 224,
    "S2 Uncommon": 211,
    "S2 Ultra-Rare": 114,
    "S2 Rare": 73,
    "S2 Epic": 42,
    "S3 Uncommon": 71,
    "S3 Ultra-Rare": 82,
    "S3 Rare": 48,
    "S3 Legendary": 236,
    "S3 Common": 102,
    "S3 Epic": 41,
    "S4 Legendary": 84,
    "S4 Uncommon": 10,
    "S4 Epic": 3,
    "S4 Rare": 2,
    "S4 Common": 5,
    "S4 Ultra-Rare": 4
  },
  {
    "Nation": "Waterfall State",
    "Junk Value": 1037.29,
    "Bank": 316.73,
    "Deck Value": 57111.03,
    "Card Count": 6627,
    "Deck Capacity": 7558,
    "Legendary Value Raw": 49924.36,
    "Legendary Value": 87.42,
    "Common": 4569,
    "Uncommon": 546,
    "Legendary": 812,
    "Ultra-Rare": 199,
    "Epic": 225,
    "Rare": 276,
    "S1": 856,
    "S2": 1478,
    "S3": 4133,
    "S4": 160,
    "S1 Common": 296,
    "S1 Uncommon": 274,
    "S2 Legendary": 198,
    "S1 Ultra-Rare": 71,
    "S2 Common": 875,
    "S1 Epic": 26,
    "S1 Rare": 176,
    "S1 Legendary": 13,
    "S2 Rare": 72,
    "S2 Uncommon": 180,
    "S2 Epic": 88,
    "S2 Ultra-Rare": 65,
    "S3 Common": 3266,
    "S3 Legendary": 580,
    "S3 Ultra-Rare": 61,
    "S3 Rare": 27,
    "S3 Uncommon": 88,
    "S3 Epic": 111,
    "S4 Common": 132,
    "S4 Legendary": 21,
    "S4 Rare": 1,
    "S4 Uncommon": 4,
    "S4 Ultra-Rare": 2
  },
  {
    "Nation": "Bastile",
    "Junk Value": 843.65,
    "Bank": 8794.03,
    "Deck Value": 56119.63,
    "Card Count": 5241,
    "Deck Capacity": 5500,
    "Legendary Value Raw": 40529.21,
    "Legendary Value": 72.22,
    "Legendary": 503,
    "Uncommon": 645,
    "Common": 2810,
    "Ultra-Rare": 419,
    "Epic": 393,
    "Rare": 471,
    "S1": 49,
    "S2": 79,
    "S3": 2628,
    "S4": 2485,
    "S1 Legendary": 7,
    "S1 Uncommon": 6,
    "S1 Common": 20,
    "S1 Ultra-Rare": 8,
    "S1 Epic": 6,
    "S2 Common": 40,
    "S1 Rare": 2,
    "S2 Uncommon": 5,
    "S2 Legendary": 13,
    "S2 Rare": 6,
    "S2 Epic": 11,
    "S2 Ultra-Rare": 4,
    "S3 Common": 1434,
    "S3 Epic": 202,
    "S3 Uncommon": 267,
    "S3 Legendary": 374,
    "S3 Rare": 223,
    "S3 Ultra-Rare": 128,
    "S4 Uncommon": 367,
    "S4 Common": 1316,
    "S4 Rare": 240,
    "S4 Legendary": 109,
    "S4 Epic": 174,
    "S4 Ultra-Rare": 279
  },
  {
    "Nation": "Qingque",
    "Junk Value": 120.79,
    "Bank": 60.95,
    "Deck Value": 53797.4,
    "Card Count": 1060,
    "Deck Capacity": 1500,
    "Legendary Value Raw": 0,
    "Legendary Value": 0.0,
    "Common": 369,
    "Uncommon": 178,
    "Rare": 173,
    "Ultra-Rare": 206,
    "Epic": 134,
    "S1": 91,
    "S2": 70,
    "S3": 557,
    "S4": 342,
    "S1 Common": 59,
    "S1 Uncommon": 26,
    "S1 Rare": 4,
    "S2 Uncommon": 37,
    "S3 Common": 242,
    "S2 Common": 20,
    "S3 Uncommon": 56,
    "S3 Ultra-Rare": 109,
    "S3 Rare": 126,
    "S2 Ultra-Rare": 6,
    "S1 Ultra-Rare": 2,
    "S3 Epic": 24,
    "S2 Rare": 3,
    "S4 Epic": 106,
    "S4 Common": 48,
    "S4 Rare": 40,
    "S4 Ultra-Rare": 89,
    "S2 Epic": 4,
    "S4 Uncommon": 59
  },
  {
    "Nation": "Grea Kriopia",
    "Junk Value": 397.82,
    "Bank": 263.4,
    "Deck Value": 52117.63,
    "Card Count": 991,
    "Deck Capacity": 2779,
    "Legendary Value Raw": 29431.8,
    "Legendary Value": 56.47,
    "Legendary": 332,
    "Ultra-Rare": 71,
    "Common": 382,
    "Rare": 42,
    "Epic": 88,
    "Uncommon": 76,
    "S1": 71,
    "S2": 822,
    "S3": 59,
    "S4": 39,
    "S1 Legendary": 40,
    "S1 Ultra-Rare": 6,
    "S2 Common": 363,
    "S1 Rare": 2,
    "S1 Epic": 16,
    "S2 Ultra-Rare": 53,
    "S2 Epic": 58,
    "S1 Uncommon": 4,
    "S2 Legendary": 252,
    "S1 Common": 3,
    "S2 Uncommon": 63,
    "S2 Rare": 33,
    "S3 Legendary": 14,
    "S3 Ultra-Rare": 11,
    "S3 Rare": 5,
    "S3 Common": 13,
    "S3 Uncommon": 6,
    "S3 Epic": 10,
    "S4 Legendary": 26,
    "S4 Epic": 4,
    "S4 Rare": 2,
    "S4 Uncommon": 3,
    "S4 Ultra-Rare": 1,
    "S4 Common": 3
  },
  {
    "Nation": "Humansanity",
    "Junk Value": 591.06,
    "Bank": 917.61,
    "Deck Value": 51650.77,
    "Card Count": 892,
    "Deck Capacity": 3186,
    "Legendary Value Raw": 46353.14,
    "Legendary Value": 89.74,
    "Legendary": 538,
    "Uncommon": 59,
    "Rare": 96,
    "Ultra-Rare": 65,
    "Epic": 73,
    "Common": 61,
    "S1": 84,
    "S2": 772,
    "S3": 36,
    "S1 Legendary": 51,
    "S2 Uncommon": 45,
    "S1 Uncommon": 5,
    "S2 Rare": 87,
    "S2 Ultra-Rare": 45,
    "S2 Legendary": 485,
    "S1 Epic": 8,
    "S1 Ultra-Rare": 12,
    "S1 Common": 6,
    "S1 Rare": 2,
    "S2 Epic": 58,
    "S2 Common": 52,
    "S3 Uncommon": 9,
    "S3 Rare": 7,
    "S3 Ultra-Rare": 8,
    "S3 Common": 3,
    "S3 Epic": 7,
    "S3 Legendary": 2
  },
  {
    "Nation": "Hyperwolf",
    "Junk Value": 817.13,
    "Bank": 210.47,
    "Deck Value": 51402.45,
    "Card Count": 3489,
    "Deck Capacity": 3836,
    "Legendary Value Raw": 45097.33,
    "Legendary Value": 87.73,
    "Epic": 197,
    "Legendary": 621,
    "Common": 1213,
    "Ultra-Rare": 204,
    "Rare": 360,
    "Uncommon": 894,
    "S2": 106,
    "S1": 143,
    "S3": 2899,
    "S4": 341,
    "S2 Epic": 6,
    "S1 Legendary": 3,
    "S1 Common": 111,
    "S2 Ultra-Rare": 30,
    "S2 Rare": 11,
    "S2 Legendary": 7,
    "S1 Uncommon": 21,
    "S2 Common": 30,
    "S2 Uncommon": 22,
    "S3 Common": 976,
    "S3 Legendary": 549,
    "S3 Epic": 129,
    "S3 Uncommon": 806,
    "S3 Rare": 319,
    "S3 Ultra-Rare": 120,
    "S1 Ultra-Rare": 4,
    "S1 Epic": 1,
    "S1 Rare": 3,
    "S4 Common": 96,
    "S4 Rare": 27,
    "S4 Uncommon": 45,
    "S4 Ultra-Rare": 50,
    "S4 Legendary": 62,
    "S4 Epic": 61
  },
  {
    "Nation": "Ballotonia",
    "Junk Value": 1339.82,
    "Bank": 1935.35,
    "Deck Value": 51043.55,
    "Card Count": 6471,
    "Deck Capacity": 12688,
    "Legendary Value Raw": 45268.41,
    "Legendary Value": 88.69,
    "Uncommon": 1520,
    "Common": 1242,
    "Ultra-Rare": 1307,
    "Rare": 995,
    "Epic": 834,
    "Legendary": 573,
    "S1": 3651,
    "S2": 833,
    "S3": 1062,
    "S4": 925,
    "S1 Uncommon": 1055,
    "S1 Common": 668,
    "S1 Ultra-Rare": 726,
    "S1 Rare": 602,
    "S2 Epic": 124,
    "S1 Epic": 416,
    "S1 Legendary": 184,
    "S2 Rare": 103,
    "S2 Common": 135,
    "S2 Legendary": 169,
    "S2 Ultra-Rare": 167,
    "S2 Uncommon": 135,
    "S3 Rare": 166,
    "S3 Ultra-Rare": 197,
    "S3 Legendary": 215,
    "S3 Common": 193,
    "S3 Uncommon": 154,
    "S3 Epic": 137,
    "S4 Common": 246,
    "S4 Legendary": 5,
    "S4 Ultra-Rare": 217,
    "S4 Rare": 124,
    "S4 Uncommon": 176,
    "S4 Epic": 157
  },
  {
    "Nation": "Ducky",
    "Junk Value": 560.09,
    "Bank": 7100.36,
    "Deck Value": 49999.24,
    "Card Count": 2829,
    "Deck Capacity": 3250,
    "Legendary Value Raw": 40320.93,
    "Legendary Value": 80.64,
    "Ultra-Rare": 83,
    "Uncommon": 286,
    "Common": 1819,
    "Rare": 103,
    "Legendary": 484,
    "Epic": 54,
    "S1": 52,
    "S2": 56,
    "S3": 1054,
    "S4": 1667,
    "S1 Ultra-Rare": 7,
    "S1 Uncommon": 11,
    "S1 Common": 19,
    "S1 Rare": 8,
    "S2 Uncommon": 14,
    "S2 Legendary": 6,
    "S2 Common": 28,
    "S2 Rare": 2,
    "S2 Epic": 4,
    "S2 Ultra-Rare": 2,
    "S3 Common": 655,
    "S3 Uncommon": 101,
    "S3 Rare": 58,
    "S3 Legendary": 189,
    "S3 Ultra-Rare": 31,
    "S3 Epic": 20,
    "S1 Epic": 4,
    "S1 Legendary": 3,
    "S4 Uncommon": 160,
    "S4 Common": 1117,
    "S4 Legendary": 286,
    "S4 Rare": 35,
    "S4 Epic": 26,
    "S4 Ultra-Rare": 43
  },
  {
    "Nation": "Cleon The First",
    "Junk Value": 31.66,
    "Bank": 545.08,
    "Deck Value": 48689.31,
    "Card Count": 2204,
    "Deck Capacity": 2592,
    "Legendary Value Raw": 73.25,
    "Legendary Value": 0.15,
    "Common": 2016,
    "Epic": 8,
    "Uncommon": 130,
    "Rare": 49,
    "Legendary": 1,
    "S2": 1614,
    "S1": 3,
    "S3": 469,
    "S4": 118,
    "S2 Common": 1521,
    "S1 Epic": 2,
    "S2 Uncommon": 93,
    "S1 Uncommon": 1,
    "S3 Common": 397,
    "S3 Uncommon": 20,
    "S3 Rare": 47,
    "S3 Epic": 4,
    "S3 Legendary": 1,
    "S4 Common": 98,
    "S4 Epic": 2,
    "S4 Uncommon": 16,
    "S4 Rare": 2
  },
  {
    "Nation": "Hujen",
    "Junk Value": 694.14,
    "Bank": 4133.24,
    "Deck Value": 48448.54,
    "Card Count": 1826,
    "Deck Capacity": 1918,
    "Legendary Value Raw": 22542.54,
    "Legendary Value": 46.53,
    "Uncommon": 304,
    "Epic": 457,
    "Ultra-Rare": 275,
    "Rare": 153,
    "Common": 244,
    "Legendary": 393,
    "S1": 76,
    "S2": 280,
    "S3": 1407,
    "S4": 63,
    "S1 Uncommon": 8,
    "S1 Epic": 59,
    "S1 Ultra-Rare": 5,
    "S1 Rare": 1,
    "S2 Uncommon": 68,
    "S2 Common": 34,
    "S2 Ultra-Rare": 37,
    "S2 Legendary": 57,
    "S2 Epic": 76,
    "S2 Rare": 8,
    "S3 Epic": 319,
    "S3 Common": 173,
    "S3 Ultra-Rare": 227,
    "S3 Rare": 137,
    "S3 Legendary": 331,
    "S3 Uncommon": 220,
    "S1 Common": 1,
    "S1 Legendary": 2,
    "S4 Common": 36,
    "S4 Rare": 7,
    "S4 Uncommon": 8,
    "S4 Ultra-Rare": 6,
    "S4 Epic": 3,
    "S4 Legendary": 3
  },
  {
    "Nation": "The Rhein States",
    "Junk Value": 525.28,
    "Bank": 1306.04,
    "Deck Value": 44620.8,
    "Card Count": 2150,
    "Deck Capacity": 3606,
    "Legendary Value Raw": 30307.92,
    "Legendary Value": 67.92,
    "Legendary": 424,
    "Common": 798,
    "Uncommon": 452,
    "Epic": 79,
    "Ultra-Rare": 156,
    "Rare": 241,
    "S2": 418,
    "S1": 164,
    "S3": 1148,
    "S4": 420,
    "S2 Legendary": 185,
    "S1 Legendary": 90,
    "S2 Common": 80,
    "S1 Uncommon": 31,
    "S1 Common": 15,
    "S1 Epic": 12,
    "S1 Ultra-Rare": 9,
    "S1 Rare": 7,
    "S2 Rare": 57,
    "S2 Epic": 24,
    "S2 Uncommon": 66,
    "S2 Ultra-Rare": 6,
    "S3 Ultra-Rare": 128,
    "S3 Legendary": 149,
    "S3 Common": 438,
    "S3 Epic": 38,
    "S3 Rare": 138,
    "S3 Uncommon": 257,
    "S4 Common": 265,
    "S4 Rare": 39,
    "S4 Ultra-Rare": 13,
    "S4 Uncommon": 98,
    "S4 Epic": 5
  },
  {
    "Nation": "Rhenna",
    "Junk Value": 692.63,
    "Bank": 521.74,
    "Deck Value": 44221.56,
    "Card Count": 2866,
    "Deck Capacity": 3288,
    "Legendary Value Raw": 30467.78,
    "Legendary Value": 68.9,
    "Epic": 320,
    "Legendary": 467,
    "Common": 933,
    "Uncommon": 882,
    "Ultra-Rare": 61,
    "Rare": 203,
    "S1": 55,
    "S2": 53,
    "S3": 2661,
    "S4": 97,
    "S1 Epic": 10,
    "S2 Epic": 12,
    "S2 Legendary": 4,
    "S2 Common": 18,
    "S2 Uncommon": 18,
    "S1 Uncommon": 6,
    "S1 Common": 34,
    "S2 Ultra-Rare": 1,
    "S3 Common": 835,
    "S3 Uncommon": 838,
    "S3 Legendary": 448,
    "S3 Rare": 190,
    "S3 Epic": 296,
    "S1 Rare": 4,
    "S3 Ultra-Rare": 54,
    "S4 Legendary": 15,
    "S4 Ultra-Rare": 5,
    "S4 Common": 46,
    "S4 Uncommon": 20,
    "S1 Ultra-Rare": 1,
    "S4 Epic": 2,
    "S4 Rare": 9
  },
  {
    "Nation": "Montrandec",
    "Junk Value": 1667.41,
    "Bank": 3.95,
    "Deck Value": 44088.3,
    "Card Count": 5620,
    "Deck Capacity": 5770,
    "Legendary Value Raw": 38176.26,
    "Legendary Value": 86.59,
    "Legendary": 525,
    "Epic": 2014,
    "Ultra-Rare": 422,
    "Common": 1481,
    "Uncommon": 724,
    "Rare": 454,
    "S1": 418,
    "S2": 1554,
    "S3": 3644,
    "S4": 4,
    "S1 Legendary": 13,
    "S1 Epic": 27,
    "S1 Ultra-Rare": 82,
    "S1 Common": 157,
    "S1 Uncommon": 91,
    "S2 Epic": 89,
    "S1 Rare": 48,
    "S2 Common": 934,
    "S2 Rare": 67,
    "S2 Legendary": 283,
    "S2 Uncommon": 166,
    "S2 Ultra-Rare": 15,
    "S3 Epic": 1898,
    "S3 Rare": 336,
    "S3 Uncommon": 466,
    "S3 Common": 390,
    "S3 Ultra-Rare": 325,
    "S3 Legendary": 229,
    "S4 Rare": 3,
    "S4 Uncommon": 1
  },
  {
    "Nation": "The Hoard Of The Dragon",
    "Junk Value": 340.17,
    "Bank": 238.52,
    "Deck Value": 42510.95,
    "Card Count": 2095,
    "Deck Capacity": 4000,
    "Legendary Value Raw": 23008.98,
    "Legendary Value": 54.12,
    "Legendary": 233,
    "Common": 712,
    "Rare": 328,
    "Ultra-Rare": 129,
    "Epic": 88,
    "Uncommon": 605,
    "S1": 9,
    "S2": 15,
    "S3": 2005,
    "S4": 66,
    "S1 Legendary": 2,
    "S2 Common": 7,
    "S2 Rare": 3,
    "S2 Legendary": 2,
    "S2 Ultra-Rare": 1,
    "S3 Common": 672,
    "S3 Rare": 322,
    "S3 Legendary": 229,
    "S3 Epic": 83,
    "S3 Ultra-Rare": 125,
    "S3 Uncommon": 574,
    "S2 Uncommon": 1,
    "S1 Uncommon": 3,
    "S1 Rare": 1,
    "S1 Ultra-Rare": 1,
    "S1 Common": 1,
    "S2 Epic": 1,
    "S1 Epic": 1,
    "S4 Rare": 2,
    "S4 Epic": 3,
    "S4 Common": 32,
    "S4 Uncommon": 27,
    "S4 Ultra-Rare": 2
  },
  {
    "Nation": "Kyorgia",
    "Junk Value": 347.97,
    "Bank": 412.08,
    "Deck Value": 40877.76,
    "Card Count": 668,
    "Deck Capacity": 1642,
    "Legendary Value Raw": 19934.68,
    "Legendary Value": 48.77,
    "Ultra-Rare": 61,
    "Epic": 175,
    "Uncommon": 68,
    "Legendary": 244,
    "Common": 87,
    "Rare": 33,
    "S1": 94,
    "S2": 497,
    "S3": 54,
    "S4": 23,
    "S1 Ultra-Rare": 15,
    "S1 Epic": 19,
    "S1 Uncommon": 19,
    "S1 Legendary": 21,
    "S1 Common": 16,
    "S1 Rare": 4,
    "S2 Epic": 145,
    "S2 Uncommon": 38,
    "S2 Ultra-Rare": 33,
    "S2 Common": 59,
    "S2 Legendary": 206,
    "S2 Rare": 16,
    "S3 Rare": 12,
    "S3 Ultra-Rare": 12,
    "S3 Uncommon": 10,
    "S3 Common": 11,
    "S3 Epic": 7,
    "S3 Legendary": 2,
    "S4 Epic": 4,
    "S4 Legendary": 15,
    "S4 Rare": 1,
    "S4 Common": 1,
    "S4 Uncommon": 1,
    "S4 Ultra-Rare": 1
  },
  {
    "Nation": "Parenthos",
    "Junk Value": 682.68,
    "Bank": 1889.15,
    "Deck Value": 40455.6,
    "Card Count": 2796,
    "Deck Capacity": 3288,
    "Legendary Value Raw": 37476.41,
    "Legendary Value": 92.64,
    "Common": 1213,
    "Rare": 227,
    "Epic": 189,
    "Uncommon": 473,
    "Legendary": 517,
    "Ultra-Rare": 177,
    "S1": 353,
    "S2": 113,
    "S3": 1326,
    "S4": 1004,
    "S1 Common": 149,
    "S1 Rare": 52,
    "S1 Epic": 22,
    "S1 Uncommon": 78,
    "S1 Legendary": 21,
    "S1 Ultra-Rare": 31,
    "S2 Uncommon": 21,
    "S2 Epic": 10,
    "S2 Rare": 28,
    "S2 Common": 31,
    "S2 Ultra-Rare": 18,
    "S2 Legendary": 5,
    "S3 Legendary": 287,
    "S3 Epic": 102,
    "S3 Ultra-Rare": 80,
    "S3 Common": 642,
    "S3 Rare": 83,
    "S3 Uncommon": 132,
    "S4 Common": 391,
    "S4 Rare": 64,
    "S4 Uncommon": 242,
    "S4 Ultra-Rare": 48,
    "S4 Legendary": 204,
    "S4 Epic": 55
  },
  {
    "Nation": "Venico",
    "Junk Value": 424.08,
    "Bank": 1090.45,
    "Deck Value": 39751.03,
    "Card Count": 2145,
    "Deck Capacity": 2500,
    "Legendary Value Raw": 13220.91,
    "Legendary Value": 33.26,
    "Uncommon": 252,
    "Common": 1078,
    "Rare": 170,
    "Ultra-Rare": 196,
    "Epic": 175,
    "Legendary": 274,
    "S1": 31,
    "S2": 26,
    "S3": 1377,
    "S4": 711,
    "S1 Uncommon": 14,
    "S2 Common": 11,
    "S2 Rare": 2,
    "S2 Uncommon": 11,
    "S3 Common": 804,
    "S3 Rare": 146,
    "S3 Uncommon": 177,
    "S3 Ultra-Rare": 126,
    "S3 Epic": 123,
    "S2 Ultra-Rare": 1,
    "S1 Epic": 1,
    "S1 Common": 12,
    "S1 Rare": 2,
    "S1 Ultra-Rare": 1,
    "S3 Legendary": 1,
    "S4 Legendary": 271,
    "S4 Common": 251,
    "S4 Epic": 51,
    "S4 Uncommon": 50,
    "S4 Ultra-Rare": 68,
    "S4 Rare": 20,
    "S1 Legendary": 1,
    "S2 Legendary": 1
  },
  {
    "Nation": "Cavedweller",
    "Junk Value": 354.2,
    "Bank": 1080.18,
    "Deck Value": 38935.26,
    "Card Count": 768,
    "Deck Capacity": 2779,
    "Legendary Value Raw": 34569.55,
    "Legendary Value": 88.79,
    "Ultra-Rare": 106,
    "Uncommon": 112,
    "Common": 190,
    "Rare": 23,
    "Epic": 23,
    "Legendary": 314,
    "S1": 143,
    "S2": 606,
    "S3": 13,
    "S4": 6,
    "S1 Ultra-Rare": 16,
    "S1 Uncommon": 34,
    "S1 Common": 26,
    "S1 Rare": 4,
    "S1 Epic": 5,
    "S1 Legendary": 58,
    "S2 Common": 159,
    "S2 Ultra-Rare": 87,
    "S2 Rare": 18,
    "S2 Legendary": 253,
    "S2 Epic": 18,
    "S2 Uncommon": 71,
    "S3 Ultra-Rare": 2,
    "S3 Uncommon": 6,
    "S3 Common": 1,
    "S3 Legendary": 3,
    "S3 Rare": 1,
    "S4 Ultra-Rare": 1,
    "S4 Common": 4,
    "S4 Uncommon": 1
  },
  {
    "Nation": "Xink Cards",
    "Junk Value": 655.0,
    "Bank": 598.75,
    "Deck Value": 37747.21,
    "Card Count": 655,
    "Deck Capacity": 750,
    "Legendary Value Raw": 37747.99,
    "Legendary Value": 100.0,
    "Legendary": 655,
    "S1": 25,
    "S2": 19,
    "S3": 515,
    "S4": 96,
    "S1 Legendary": 25,
    "S2 Legendary": 19,
    "S3 Legendary": 515,
    "S4 Legendary": 96
  },
  {
    "Nation": "Richardian Savoy",
    "Junk Value": 920.77,
    "Bank": 1251.08,
    "Deck Value": 37138.73,
    "Card Count": 3539,
    "Deck Capacity": 4010,
    "Legendary Value Raw": 26534.32,
    "Legendary Value": 71.45,
    "Legendary": 436,
    "Uncommon": 479,
    "Epic": 745,
    "Common": 1252,
    "Rare": 248,
    "Ultra-Rare": 379,
    "S1": 108,
    "S2": 974,
    "S3": 2375,
    "S4": 82,
    "S1 Legendary": 2,
    "S1 Uncommon": 17,
    "S1 Epic": 17,
    "S2 Common": 413,
    "S2 Legendary": 18,
    "S2 Uncommon": 273,
    "S2 Rare": 114,
    "S2 Ultra-Rare": 69,
    "S2 Epic": 87,
    "S1 Common": 62,
    "S1 Rare": 7,
    "S3 Uncommon": 180,
    "S3 Common": 757,
    "S3 Epic": 636,
    "S3 Rare": 122,
    "S3 Ultra-Rare": 295,
    "S3 Legendary": 385,
    "S1 Ultra-Rare": 3,
    "S4 Rare": 5,
    "S4 Ultra-Rare": 12,
    "S4 Uncommon": 9,
    "S4 Common": 20,
    "S4 Legendary": 31,
    "S4 Epic": 5
  },
  {
    "Nation": "Obrimenja",
    "Junk Value": 409.68,
    "Bank": 206.48,
    "Deck Value": 36914.11,
    "Card Count": 1952,
    "Deck Capacity": 2000,
    "Legendary Value Raw": 22931.84,
    "Legendary Value": 62.12,
    "Legendary": 359,
    "Rare": 64,
    "Common": 1113,
    "Ultra-Rare": 47,
    "Uncommon": 343,
    "Epic": 26,
    "S2": 16,
    "S1": 14,
    "S3": 1525,
    "S4": 397,
    "S2 Legendary": 6,
    "S2 Rare": 2,
    "S1 Legendary": 5,
    "S2 Common": 3,
    "S3 Ultra-Rare": 37,
    "S3 Common": 881,
    "S3 Uncommon": 240,
    "S3 Epic": 23,
    "S3 Rare": 49,
    "S3 Legendary": 295,
    "S2 Epic": 1,
    "S1 Uncommon": 2,
    "S1 Rare": 3,
    "S1 Common": 3,
    "S2 Ultra-Rare": 1,
    "S1 Epic": 1,
    "S2 Uncommon": 3,
    "S4 Common": 226,
    "S4 Legendary": 53,
    "S4 Ultra-Rare": 9,
    "S4 Uncommon": 98,
    "S4 Rare": 10,
    "S4 Epic": 1
  },
  {
    "Nation": "Luzbian",
    "Junk Value": 22.19,
    "Bank": 37.26,
    "Deck Value": 36053.65,
    "Card Count": 642,
    "Deck Capacity": 668,
    "Legendary Value Raw": 0,
    "Legendary Value": 0.0,
    "Common": 379,
    "Uncommon": 156,
    "Epic": 12,
    "Ultra-Rare": 23,
    "Rare": 72,
    "S2": 94,
    "S1": 10,
    "S3": 492,
    "S4": 46,
    "S2 Common": 48,
    "S2 Uncommon": 30,
    "S2 Epic": 7,
    "S2 Ultra-Rare": 3,
    "S1 Common": 4,
    "S1 Uncommon": 4,
    "S2 Rare": 6,
    "S3 Common": 298,
    "S3 Rare": 58,
    "S3 Uncommon": 111,
    "S3 Ultra-Rare": 20,
    "S3 Epic": 5,
    "S1 Rare": 2,
    "S4 Common": 29,
    "S4 Uncommon": 11,
    "S4 Rare": 6
  },
  {
    "Nation": "Anarco Argentina",
    "Junk Value": 553.09,
    "Bank": 2028.03,
    "Deck Value": 35129.25,
    "Card Count": 14122,
    "Deck Capacity": 14500,
    "Legendary Value Raw": 2686.48,
    "Legendary Value": 7.65,
    "Common": 8184,
    "Uncommon": 2943,
    "Rare": 1889,
    "Ultra-Rare": 823,
    "Epic": 247,
    "Legendary": 36,
    "S2": 747,
    "S1": 199,
    "S3": 11597,
    "S4": 1579,
    "S2 Common": 519,
    "S1 Common": 101,
    "S1 Uncommon": 48,
    "S1 Rare": 31,
    "S1 Ultra-Rare": 16,
    "S2 Rare": 69,
    "S1 Epic": 3,
    "S2 Uncommon": 121,
    "S2 Ultra-Rare": 25,
    "S2 Epic": 12,
    "S3 Common": 6465,
    "S3 Uncommon": 2568,
    "S3 Rare": 1659,
    "S3 Ultra-Rare": 661,
    "S3 Epic": 211,
    "S3 Legendary": 33,
    "S2 Legendary": 1,
    "S4 Uncommon": 206,
    "S4 Rare": 130,
    "S4 Common": 1099,
    "S4 Ultra-Rare": 121,
    "S4 Epic": 21,
    "S4 Legendary": 2
  },
  {
    "Nation": "Kakastania",
    "Junk Value": 701.36,
    "Bank": 2865.8,
    "Deck Value": 34825.63,
    "Card Count": 3080,
    "Deck Capacity": 3255,
    "Legendary Value Raw": 27624.9,
    "Legendary Value": 79.32,
    "Common": 1251,
    "Ultra-Rare": 215,
    "Rare": 272,
    "Uncommon": 497,
    "Legendary": 397,
    "Epic": 448,
    "S2": 234,
    "S1": 237,
    "S3": 2535,
    "S4": 74,
    "S2 Common": 171,
    "S1 Common": 107,
    "S1 Ultra-Rare": 24,
    "S1 Rare": 49,
    "S1 Uncommon": 31,
    "S1 Legendary": 9,
    "S1 Epic": 17,
    "S2 Uncommon": 25,
    "S2 Epic": 6,
    "S2 Ultra-Rare": 9,
    "S2 Legendary": 13,
    "S2 Rare": 10,
    "S3 Common": 936,
    "S3 Epic": 416,
    "S3 Legendary": 368,
    "S3 Uncommon": 435,
    "S3 Rare": 205,
    "S3 Ultra-Rare": 175,
    "S4 Ultra-Rare": 7,
    "S4 Common": 37,
    "S4 Epic": 9,
    "S4 Legendary": 7,
    "S4 Uncommon": 6,
    "S4 Rare": 8
  },
  {
    "Nation": "Rain Delay",
    "Junk Value": 1456.2,
    "Bank": 576.89,
    "Deck Value": 34378.77,
    "Card Count": 16130,
    "Deck Capacity": 16166,
    "Legendary Value Raw": 19300.91,
    "Legendary Value": 56.14,
    "Rare": 1628,
    "Common": 6620,
    "Ultra-Rare": 2117,
    "Uncommon": 4422,
    "Epic": 1195,
    "Legendary": 148,
    "S1": 4167,
    "S2": 3671,
    "S3": 7788,
    "S4": 504,
    "S1 Rare": 348,
    "S1 Common": 1490,
    "S1 Ultra-Rare": 577,
    "S1 Uncommon": 1247,
    "S1 Epic": 414,
    "S2 Common": 1571,
    "S1 Legendary": 91,
    "S2 Uncommon": 925,
    "S2 Epic": 262,
    "S2 Ultra-Rare": 564,
    "S2 Rare": 322,
    "S2 Legendary": 27,
    "S3 Common": 3368,
    "S3 Uncommon": 2090,
    "S3 Epic": 487,
    "S3 Rare": 908,
    "S3 Ultra-Rare": 908,
    "S3 Legendary": 27,
    "S4 Uncommon": 160,
    "S4 Ultra-Rare": 68,
    "S4 Common": 191,
    "S4 Rare": 50,
    "S4 Epic": 32,
    "S4 Legendary": 3
  },
  {
    "Nation": "Independent Federation Of Croatia",
    "Junk Value": 712.17,
    "Bank": 68.13,
    "Deck Value": 33989.45,
    "Card Count": 2939,
    "Deck Capacity": 4931,
    "Legendary Value Raw": 29626.16,
    "Legendary Value": 87.16,
    "Common": 1237,
    "Legendary": 299,
    "Epic": 737,
    "Ultra-Rare": 45,
    "Uncommon": 466,
    "Rare": 155,
    "S1": 648,
    "S2": 359,
    "S3": 1880,
    "S4": 52,
    "S1 Common": 133,
    "S1 Legendary": 235,
    "S2 Legendary": 44,
    "S1 Epic": 147,
    "S1 Ultra-Rare": 30,
    "S1 Uncommon": 81,
    "S1 Rare": 22,
    "S2 Epic": 224,
    "S2 Ultra-Rare": 9,
    "S2 Common": 19,
    "S2 Rare": 14,
    "S2 Uncommon": 49,
    "S3 Common": 1080,
    "S3 Epic": 337,
    "S3 Rare": 105,
    "S3 Ultra-Rare": 5,
    "S3 Uncommon": 334,
    "S3 Legendary": 19,
    "S4 Rare": 14,
    "S4 Epic": 29,
    "S4 Ultra-Rare": 1,
    "S4 Uncommon": 2,
    "S4 Common": 5,
    "S4 Legendary": 1
  },
  {
    "Nation": "The United Peoples Of Centrism",
    "Junk Value": 303.95,
    "Bank": 2267.05,
    "Deck Value": 33427.14,
    "Card Count": 3446,
    "Deck Capacity": 6833,
    "Legendary Value Raw": 521.02,
    "Legendary Value": 1.56,
    "Uncommon": 1282,
    "Common": 1385,
    "Rare": 219,
    "Ultra-Rare": 190,
    "Epic": 364,
    "Legendary": 6,
    "S1": 392,
    "S2": 1661,
    "S3": 1376,
    "S4": 17,
    "S1 Uncommon": 147,
    "S1 Common": 131,
    "S1 Rare": 40,
    "S2 Rare": 119,
    "S1 Ultra-Rare": 49,
    "S2 Ultra-Rare": 78,
    "S1 Epic": 24,
    "S2 Common": 541,
    "S2 Uncommon": 887,
    "S2 Epic": 34,
    "S2 Legendary": 2,
    "S1 Legendary": 1,
    "S3 Common": 713,
    "S3 Epic": 289,
    "S3 Rare": 60,
    "S3 Uncommon": 248,
    "S3 Ultra-Rare": 63,
    "S3 Legendary": 3,
    "S4 Epic": 17
  },
  {
    "Nation": "Radicalania",
    "Junk Value": 1814.16,
    "Bank": 507.62,
    "Deck Value": 33212.19,
    "Card Count": 8670,
    "Deck Capacity": 9074,
    "Legendary Value Raw": 24715.54,
    "Legendary Value": 74.42,
    "Uncommon": 379,
    "Ultra-Rare": 6808,
    "Rare": 34,
    "Common": 1011,
    "Legendary": 409,
    "Epic": 29,
    "S1": 15,
    "S2": 479,
    "S3": 7050,
    "S4": 1126,
    "S1 Uncommon": 14,
    "S2 Ultra-Rare": 5,
    "S2 Uncommon": 242,
    "S2 Rare": 5,
    "S2 Common": 55,
    "S2 Legendary": 170,
    "S2 Epic": 2,
    "S3 Ultra-Rare": 6776,
    "S3 Legendary": 228,
    "S3 Epic": 19,
    "S3 Rare": 11,
    "S3 Uncommon": 5,
    "S3 Common": 11,
    "S1 Epic": 1,
    "S4 Common": 945,
    "S4 Uncommon": 118,
    "S4 Legendary": 11,
    "S4 Ultra-Rare": 27,
    "S4 Rare": 18,
    "S4 Epic": 7
  },
  {
    "Nation": "Refiria",
    "Junk Value": 333.98,
    "Bank": 244.31,
    "Deck Value": 33186.75,
    "Card Count": 1389,
    "Deck Capacity": 2005,
    "Legendary Value Raw": 19760.95,
    "Legendary Value": 59.54,
    "Legendary": 269,
    "Common": 533,
    "Uncommon": 427,
    "Epic": 55,
    "Ultra-Rare": 54,
    "Rare": 51,
    "S2": 395,
    "S1": 71,
    "S3": 897,
    "S4": 26,
    "S2 Legendary": 123,
    "S2 Common": 185,
    "S1 Uncommon": 11,
    "S1 Legendary": 21,
    "S1 Epic": 9,
    "S1 Ultra-Rare": 2,
    "S1 Common": 20,
    "S2 Uncommon": 52,
    "S2 Ultra-Rare": 11,
    "S2 Epic": 13,
    "S2 Rare": 11,
    "S1 Rare": 8,
    "S3 Uncommon": 364,
    "S3 Common": 326,
    "S3 Legendary": 125,
    "S3 Rare": 32,
    "S3 Epic": 33,
    "S3 Ultra-Rare": 17,
    "S4 Ultra-Rare": 24,
    "S4 Common": 2
  },
  {
    "Nation": "Caffeinated",
    "Junk Value": 931.89,
    "Bank": 1912.7,
    "Deck Value": 32400.24,
    "Card Count": 5587,
    "Deck Capacity": 6270,
    "Legendary Value Raw": 8807.02,
    "Legendary Value": 27.18,
    "Common": 1229,
    "Epic": 1201,
    "Rare": 598,
    "Ultra-Rare": 565,
    "Uncommon": 1882,
    "Legendary": 112,
    "S1": 4402,
    "S2": 343,
    "S3": 722,
    "S4": 120,
    "S1 Common": 915,
    "S1 Epic": 977,
    "S1 Rare": 471,
    "S1 Ultra-Rare": 530,
    "S1 Uncommon": 1486,
    "S1 Legendary": 23,
    "S2 Common": 208,
    "S2 Ultra-Rare": 19,
    "S2 Rare": 10,
    "S2 Legendary": 60,
    "S2 Epic": 10,
    "S2 Uncommon": 36,
    "S3 Common": 60,
    "S3 Uncommon": 356,
    "S3 Rare": 86,
    "S3 Epic": 185,
    "S3 Ultra-Rare": 13,
    "S3 Legendary": 22,
    "S4 Rare": 31,
    "S4 Epic": 29,
    "S4 Common": 46,
    "S4 Ultra-Rare": 3,
    "S4 Legendary": 7,
    "S4 Uncommon": 4
  },
  {
    "Nation": "Pinky Queen",
    "Junk Value": 524.07,
    "Bank": 510.67,
    "Deck Value": 32300.52,
    "Card Count": 3882,
    "Deck Capacity": 7212,
    "Legendary Value Raw": 14356.47,
    "Legendary Value": 44.45,
    "Epic": 399,
    "Rare": 367,
    "Ultra-Rare": 336,
    "Legendary": 203,
    "Common": 1862,
    "Uncommon": 715,
    "S1": 429,
    "S2": 1014,
    "S3": 2389,
    "S4": 50,
    "S1 Epic": 82,
    "S1 Rare": 47,
    "S1 Ultra-Rare": 33,
    "S1 Legendary": 51,
    "S1 Common": 163,
    "S1 Uncommon": 53,
    "S2 Common": 399,
    "S2 Epic": 116,
    "S2 Legendary": 106,
    "S2 Uncommon": 234,
    "S2 Ultra-Rare": 64,
    "S2 Rare": 95,
    "S3 Common": 1287,
    "S3 Ultra-Rare": 234,
    "S3 Uncommon": 422,
    "S3 Epic": 189,
    "S3 Rare": 211,
    "S3 Legendary": 46,
    "S4 Rare": 14,
    "S4 Epic": 12,
    "S4 Common": 13,
    "S4 Ultra-Rare": 5,
    "S4 Uncommon": 6
  },
  {
    "Nation": "Sea Dolphin Lovers",
    "Junk Value": 802.09,
    "Bank": 104.93,
    "Deck Value": 32257.89,
    "Card Count": 2237,
    "Deck Capacity": 3606,
    "Legendary Value Raw": 27425.09,
    "Legendary Value": 85.02,
    "Legendary": 341,
    "Common": 434,
    "Uncommon": 323,
    "Ultra-Rare": 203,
    "Epic": 800,
    "Rare": 136,
    "S1": 612,
    "S2": 662,
    "S3": 963,
    "S1 Legendary": 95,
    "S1 Common": 181,
    "S1 Uncommon": 84,
    "S1 Ultra-Rare": 83,
    "S1 Epic": 112,
    "S2 Legendary": 191,
    "S1 Rare": 57,
    "S2 Epic": 150,
    "S2 Ultra-Rare": 57,
    "S2 Common": 118,
    "S2 Uncommon": 122,
    "S2 Rare": 24,
    "S3 Uncommon": 117,
    "S3 Ultra-Rare": 63,
    "S3 Legendary": 55,
    "S3 Epic": 538,
    "S3 Common": 135,
    "S3 Rare": 55
  }
]